Workbook
Name __R: '[2]YM Tranche 2'!$F$7
Name _2484_1_00: "Project_number"
Name a: '[3]Cash Flow'!$A$14:$W$194
Name a: '[3]Cash Flow'!$A$14:$W$194
Name Button_1: "CalifornianCasa_UnitDetails_List"
Name Button_80: "The_Bonavista_UnitDetails_List"
Name CashFlow: '[5]Cash Flow'!$A$14:$W$194
Name CashFlow: '[5]Cash Flow'!$A$14:$W$194
Name chart_balance: OFFSET(#REF!,2,0,#REF!,1)
Name chart_date: OFFSET(#REF!,2,0,#REF!,1)
Name chart_date1: OFFSET(#REF!,2,0,#REF!,1)
Name Chart1: [6]MADRONA!$M$4
Name Chart1: [6]MADRONA!$M$4
Name Chart2: [6]MADRONA!$N$2
Name Chart2: [6]MADRONA!$N$2
Name compound_period: INDEX({2,12,4,1},MATCH(#REF!,Summary!compound_periods,0))
Name compound_period: INDEX({2,12,4,1},MATCH(#REF!,[0]!compound_periods,0))
Name compound_periods: {"Semi-Annually";"Monthly";"Quarterly";"Annually"}
Name compound_periods: {"Semi-Annually";"Monthly";"Quarterly";"Annually"}
Name data: '[7]download realigned'!$A$1:$Y$12683
Name DEBT: '[8]Senior Mortgage'!$A$12:$F$32
Name DEBT: '[8]Senior Mortgage'!$A$12:$F$32
Name FlatRentRoll: [9]WAVG!$A$7:$J$65536
Name FlatRentRoll: [9]WAVG!$A$7:$J$65536
Name frequency: {"Annually";"Semi-Annually";"Quarterly";"Bi-Monthly";"Monthly";"Semi-Monthly";"Bi-Weekly";"Weekly"}
Name frequency: {"Annually";"Semi-Annually";"Quarterly";"Bi-Monthly";"Monthly";"Semi-Monthly";"Bi-Weekly";"Weekly"}
Name fuck: [6]MADRONA!$B$68:$B$73
Name fuck: [6]MADRONA!$B$68:$B$73
Name fuckyou: [6]MADRONA!$B$24:$Q$54
Name fuckyou: [6]MADRONA!$B$24:$Q$54
Name h: [6]MADRONA!$B$94:$C$153
Name h: [6]MADRONA!$B$94:$C$153
Name ImportName: [5]Summary!$C$7
Name ImportName: [5]Summary!$C$7
Name IrrLookupRange: '[5]Financing CF '!$F$7:$AB$49
Name IrrLookupRange: '[5]Financing CF '!$F$7:$AB$49
Name Maxs: 'Int Reserve - A-B Loan'!$I$24:$I$29
Name Maxs: 'Int Reserve - Single Loan'!$V$24:$V$29
Name Maxs2: 'Int Reserve - A-B Loan'!$R$24:$R$29
Name Maxs2: 'Int Reserve - Single Loan'!$I$24:$I$29
Name Mins: 'Int Reserve - A-B Loan'!$H$24:$H$29
Name Mins: 'Int Reserve - Single Loan'!$U$24:$U$29
Name Mins2: 'Int Reserve - A-B Loan'!$Q$24:$Q$29
Name Mins2: 'Int Reserve - Single Loan'!$H$24:$H$29
Name months_per_period: INDEX({12,6,3,2,1,0.5,0.5,0.25},MATCH(#REF!,Summary!frequency,0))
Name months_per_period: INDEX({12,6,3,2,1,0.5,0.5,0.25},MATCH(#REF!,frequency,0))
Name nio: '[10]Globa Ass''ns'!$J$8
Name nio: '[10]Globa Ass''ns'!$J$8
Name periods_per_year: INDEX({1,2,4,6,12,24,26,52},MATCH(#REF!,Summary!frequency,0))
Name periods_per_year: INDEX({1,2,4,6,12,24,26,52},MATCH(#REF!,frequency,0))
Name Pivot: "Rollover!$A$1:$G$10"
Name Rates: 'Int Reserve - A-B Loan'!$J$24:$J$29
Name Rates: 'Int Reserve - Single Loan'!$W$24:$W$29
Name Rates2: 'Int Reserve - A-B Loan'!$S$24:$S$29
Name Rates2: 'Int Reserve - Single Loan'!$J$24:$J$29
Name REFI: '[8]Senior Mortgage'!$AT$5:$AV$304
Name REFI: '[8]Senior Mortgage'!$AT$5:$AV$304
Name Table2: '[8]Senior Mortgage'!$AE$5:$AK$304
Name Table2: '[8]Senior Mortgage'!$AE$5:$AK$304
Name Table3: '[8]Senior Mortgage'!$AE$5:$AK$304

Sheet Summary
B2: Loan Summary | M2: CCS Approval Authority
B4: Location | F4: <Google Maps Link> | M4: David Lyons / Lujane Abdelgadir | N4: On Vacation? | O4: No
B5: Connect | F5: <Connect Link> | M5: Antoni Kajetanowicz | N5: On Vacation? | O5: No
B6: Target Funding | F6: <Date> | M6: Scott Coates | N6: On Vacation? | O6: No
B7: Type | C7: Loan Purpose | D7: <Select> | N7: Approvers Delegated (only if on vacation)? | O7: <Select>
C8: Housing | D8: =Economics!F203 -> <Housing Type> | N8: Gross Loan > $50M? | O8: =+IF(Economics!I64>50000000,"Yes","No") -> #N/A
C9: Program | D9: =Economics!F204 -> <Program> | N9: Gross Loan / Res Value > 90% (> 75% in AB & NS)? | O9: =+IF(AND(OR(Economics!F201=ControlBackEnd!C7,Economics!F201=ControlBackEnd!C6),Economics!I64/Economics!H34>0.75),"Yes",IF(Economics!I64/Economics!H34>0.9,"Yes","No")) -> #N/A
B10: Points | C10: Affordability | D10: =Economics!F217 -> 0 | N10: Retirement Home? | O10: =+IF(Economics!F203=ControlBackEnd!C13,"Yes","No") -> No
C11: Accessibility | D11: =Economics!F219 -> 0 | N11: Student Housing? | O11: =+IF(Economics!F203=ControlBackEnd!C11,"Yes","No") -> No
C12: Energy | D12: =Economics!F218 -> 0 | N12: Leased Land? | O12: <Select>
B13: Loan | C13: Gross Amount | D13: =+Economics!I64 -> #N/A | N13: Market with Population < 50,000? | O13: <Select> | P13: Click the Red Circle for Markets (use your judgement) and reference the Blue Circle for Population
C14: Term | D14: =+Economics!I68 -> 0 | N14: Request for approval of a subordinate debt? | O14: No
C15: Amortization | D15: =Economics!I69 -> 0 | M15: Rob Kumer | N15: Gross Loan > $50M? | O15: =+IF(Economics!I64>50000000,"Yes","No") -> #N/A
B16: Sponsor | C16: Name | D16: <Sponsor> | F16: <Link to company website>
C17: Experience | D17: <Select> | F17: <Very brief summary, note any concerns> | M17: CCS Approvers
C18: Guarantee | D18: <Select> | F18: <Note any concerns> | M18: David Lyons | N18: =+IF(O4="Yes","No","Yes") -> Yes
C19: CANLII Search | D19: <Completed?> | F19: <Note any concerns> | M19: Antoni Kajetanowicz | N19: =+IF(O5="Yes","No","Yes") -> Yes
C20: Net Worth | D20: <Reported NW> | F20: <Note any concerns> | M20: Scott Coates | N20: =+IF(O6="Yes","No",IF(COUNTIFS(O8:O14,"Yes")+COUNTIFS(O4:O5,"Yes")>0,"Yes","No")) -> No | O20: cc Scott in Adobe Sign for all CCS he is not approving
B21: UW Notes | C21: Gross LTV | D21: =Economics!I80 -> #N/A | F21: <Note any concerns> | M21: Rob Kumer | N21: =+IF(O15="Yes","Yes",IF(AND(O6="Yes",O7="No",COUNTIFS(O8:O13,"Yes")+COUNTIFS(O4:O5,"Yes")>0),"Yes","No")) -> #N/A
C22: Gross Loan / Res Value | D22: =+Economics!I64/Economics!H34 -> #N/A | F22: <Note any concerns>
C23: Value / Unit | D23: =Economics!I34 -> #DIV/0! | F23: =+Economics!G34 -> 0 | G23: <Note any concerns; based on what cap rate (speak to cap rate stress)>
C24: Net DSC (@ Max Rate) | D24: =Economics!H84 -> #NUM! | F24: <Note any concerns; if below minimum, why?>
C25: Max Rate / Buydown | D25: =IF(AND(Economics!I68=5,Economics!J72=0),TEXT(Economics!I71,"0.00%")&" / "&"NIL",IF(AND(Economics!I68=10,Economics!J73=0),TEXT(Economics!I71,"0.00%")&" / "&"NIL",IF(Economics!I68=5,TEXT(Economics!I71,"0.00%")&" / "&TEXT(Economics!J72,"$#,#"),TEXT(Economics!I71,"0.00%")&" / "&TEXT(Economics!J73,"$#,#")))) -> #N/A | F25: <Note any concerns>
C26: Equity | D26: =+Economics!H54-Economics!I64 -> #N/A | F26: <Discuss with Antoni and Brian if below $250k>
C27: Actual Vacancy | D27: =+Economics!AQ18 -> - | F27: <EGI Test?> | G27: <Note any concerns; lease up / separate res & commercial EGI test?>
B28: Key Risks | F28: <Note primary risks with deal>
B30: 5yr Pricing
B32: Loan Spread | D32: 0 | F32: Net Spread | G32: KS Return ($) | H32: KS Return (%) | I32: KS Margin
B33: Broker Spread | D33: 0 | F33: =F34-1 -> -4 | G33: =ROUND('Buydown Calc'!$D$6*I33/10000*$D$13+$D$36*$D$13/10000,-3) -> #N/A | H33: =G33/$D$13 -> #N/A | I33: =+(F33-$D$33-$D$34-$D$35) -> #N/A
B34: Servicing Spread | D34: {=+INDEX(ControlBackEnd!$H$3:$H$8,_xlfn.XMATCH(Summary!$D$13,ControlBackEnd!$G$3:$G$8,-1))} -> #N/A | F34: =F35-1 -> -3 | G34: =ROUND('Buydown Calc'!$D$6*I34/10000*$D$13+$D$36*$D$13/10000,-3) -> #N/A | H34: =G34/$D$13 -> #N/A | I34: =+(F34-$D$33-$D$34-$D$35) -> #N/A
B35: Agg Spread | D35: 0 | F35: =F36-1 -> -2 | G35: =ROUND('Buydown Calc'!$D$6*I35/10000*$D$13+$D$36*$D$13/10000,-3) -> #N/A | H35: =G35/$D$13 -> #N/A | I35: =+(F35-$D$33-$D$34-$D$35) -> #N/A
B36: Lender Fee | D36: 0 | F36: =F37-1 -> -1 | G36: =ROUND('Buydown Calc'!$D$6*I36/10000*$D$13+$D$36*$D$13/10000,-3) -> #N/A | H36: =G36/$D$13 -> #N/A | I36: =+(F36-$D$33-$D$34-$D$35) -> #N/A
F37: =+D32-D33 -> 0 | G37: =ROUND('Buydown Calc'!$D$6*I37/10000*$D$13+$D$36*$D$13/10000,-3) -> #N/A | H37: =G37/$D$13 -> #N/A | I37: =+(F37-$D$33-$D$34-$D$35) -> #N/A
F38: =F37+1 -> 1 | G38: =ROUND('Buydown Calc'!$D$6*I38/10000*$D$13+$D$36*$D$13/10000,-3) -> #N/A | H38: =G38/$D$13 -> #N/A | I38: =+(F38-$D$33-$D$34-$D$35) -> #N/A
F39: =F38+1 -> 2 | G39: =ROUND('Buydown Calc'!$D$6*I39/10000*$D$13+$D$36*$D$13/10000,-3) -> #N/A | H39: =G39/$D$13 -> #N/A | I39: =+(F39-$D$33-$D$34-$D$35) -> #N/A
F40: =F39+1 -> 3 | G40: =ROUND('Buydown Calc'!$D$6*I40/10000*$D$13+$D$36*$D$13/10000,-3) -> #N/A | H40: =G40/$D$13 -> #N/A | I40: =+(F40-$D$33-$D$34-$D$35) -> #N/A
F41: =F40+1 -> 4 | G41: =ROUND('Buydown Calc'!$D$6*I41/10000*$D$13+$D$36*$D$13/10000,-3) -> #N/A | H41: =G41/$D$13 -> #N/A | I41: =+(F41-$D$33-$D$34-$D$35) -> #N/A
B43: 10yr Pricing
B45: Loan Spread | D45: 0 | F45: Net Spread | G45: KS Return ($) | H45: KS Return (%) | I45: KS Margin
B46: Broker Spread | D46: 0 | F46: =F47-1 -> -4 | G46: =ROUND('Buydown Calc'!$D$7*I46/10000*$D$13+$D$49*$D$13/10000,-3) -> #N/A | H46: =G46/$D$13 -> #N/A | I46: =+(F46-$D$46-$D$47-$D$48) -> #N/A
B47: Servicing Spread | D47: {=+INDEX(ControlBackEnd!$H$3:$H$8,_xlfn.XMATCH(Summary!$D$13,ControlBackEnd!$G$3:$G$8,-1))} -> #N/A | F47: =F48-1 -> -3 | G47: =ROUND('Buydown Calc'!$D$7*I47/10000*$D$13+$D$49*$D$13/10000,-3) -> #N/A | H47: =G47/$D$13 -> #N/A | I47: =+(F47-$D$46-$D$47-$D$48) -> #N/A
B48: Agg Spread | D48: 0 | F48: =F49-1 -> -2 | G48: =ROUND('Buydown Calc'!$D$7*I48/10000*$D$13+$D$49*$D$13/10000,-3) -> #N/A | H48: =G48/$D$13 -> #N/A | I48: =+(F48-$D$46-$D$47-$D$48) -> #N/A
B49: Lender Fee | D49: 0 | F49: =F50-1 -> -1 | G49: =ROUND('Buydown Calc'!$D$7*I49/10000*$D$13+$D$49*$D$13/10000,-3) -> #N/A | H49: =G49/$D$13 -> #N/A | I49: =+(F49-$D$46-$D$47-$D$48) -> #N/A
F50: =+D45-D46 -> 0 | G50: =ROUND('Buydown Calc'!$D$7*I50/10000*$D$13+$D$49*$D$13/10000,-3) -> #N/A | H50: =G50/$D$13 -> #N/A | I50: =+(F50-$D$46-$D$47-$D$48) -> #N/A
F51: =F50+1 -> 1 | G51: =ROUND('Buydown Calc'!$D$7*I51/10000*$D$13+$D$49*$D$13/10000,-3) -> #N/A | H51: =G51/$D$13 -> #N/A | I51: =+(F51-$D$46-$D$47-$D$48) -> #N/A
F52: =F51+1 -> 2 | G52: =ROUND('Buydown Calc'!$D$7*I52/10000*$D$13+$D$49*$D$13/10000,-3) -> #N/A | H52: =G52/$D$13 -> #N/A | I52: =+(F52-$D$46-$D$47-$D$48) -> #N/A
F53: =F52+1 -> 3 | G53: =ROUND('Buydown Calc'!$D$7*I53/10000*$D$13+$D$49*$D$13/10000,-3) -> #N/A | H53: =G53/$D$13 -> #N/A | I53: =+(F53-$D$46-$D$47-$D$48) -> #N/A
F54: =F53+1 -> 4 | G54: =ROUND('Buydown Calc'!$D$7*I54/10000*$D$13+$D$49*$D$13/10000,-3) -> #N/A | H54: =G54/$D$13 -> #N/A | I54: =+(F54-$D$46-$D$47-$D$48) -> #N/A

Sheet Economics
C2: KingSett CMHC | L2: Underwriting Comments | N2: KingSett Bridge | W2: CMHC Benchmarks | AA2: Borrower | AD2: Variance
H3: KingSett CMHC | S3: KingSett Bridge | W3: CMHC Benchmarks | AA3: Borrower
E4: Occupied | F4: Units | G4: Size | H4: Total | I4: Per Unit | J4: PSF | P4: Occupied | Q4: Units | R4: Size | S4: Total | T4: Per Unit | U4: PSF | W4: Total | X4: /Unit | Y4: %EGI | AA4: Total | AB4: /Unit | AD4: Total | AE4: /Unit | AF4: %Delta | AI4: CMHC Avg | AJ4: CCS Delta
C5: Bachelor | E5: =+IF($F$200="Construction Financing",'Rent Roll'!G16,'Rent Roll'!G3) -> 0 | F5: =+IF($F$200="Construction Financing",'Rent Roll'!H16,'Rent Roll'!H3) -> 0 | G5: =+IF($F$200="Construction Financing",'Rent Roll'!I16,'Rent Roll'!I3) -> - | H5: =+IF($F$200="Construction Financing",'Rent Roll'!J16,'Rent Roll'!J3) -> 0 | I5: =+IF($F$200="Construction Financing",'Rent Roll'!K16,'Rent Roll'!K3) -> - | J5: =IFERROR(I5/G5,"") | N5: =C5 -> Bachelor | P5: =+E5 -> 0 | Q5: =+F5 -> 0 | R5: =+G5 -> - | S5: =+H5 -> 0 | T5: =+I5 -> - | U5: =IFERROR(T5/R5,"") | W5: =X5*F5*12 -> 0 | AA5: =AB5*F5*12 -> 0 | AD5: =HLOOKUP($AE$36,$H$3:$AA$33,ROW()-2,FALSE)-HLOOKUP($AE$35,$H$3:$AA$33,ROW()-2,FALSE) -> #N/A | AE5: =IFERROR(AD5/F5/12,"") | AF5: =IFERROR(AD5/HLOOKUP($AE$35,$H$3:$AA$33,3,FALSE),"") | AH5: see cell AI:199 for table for CCS | AJ5: =IFERROR(IF(ISBLANK(AI5),"-",+I5-AI5),"-") -> -
C6: 1 Bedroom | E6: =+IF($F$200="Construction Financing",'Rent Roll'!G17,'Rent Roll'!G4) -> 0 | F6: =+IF($F$200="Construction Financing",'Rent Roll'!H17,'Rent Roll'!H4) -> 0 | G6: =+IF($F$200="Construction Financing",'Rent Roll'!I17,'Rent Roll'!I4) -> - | H6: =+IF($F$200="Construction Financing",'Rent Roll'!J17,'Rent Roll'!J4) -> 0 | I6: =+IF($F$200="Construction Financing",'Rent Roll'!K17,'Rent Roll'!K4) -> - | J6: =IFERROR(I6/G6,"") | N6: =C6 -> 1 Bedroom | P6: =+E6 -> 0 | Q6: =+F6 -> 0 | R6: =+G6 -> - | S6: =+H6 -> 0 | T6: =+I6 -> - | U6: =IFERROR(T6/R6,"") | W6: =X6*F6*12 -> 0 | AA6: =AB6*F6*12 -> 0 | AD6: =HLOOKUP($AE$36,$H$3:$AA$33,ROW()-2,FALSE)-HLOOKUP($AE$35,$H$3:$AA$33,ROW()-2,FALSE) -> #N/A | AE6: =IFERROR(AD6/F6/12,"") | AF6: =IFERROR(AD6/HLOOKUP($AE$35,$H$3:$AA$33,4,FALSE),"") | AJ6: =IFERROR(IF(ISBLANK(AI6),"-",+I6-AI6),"-") -> -
C7: 2 Bedroom | E7: =+IF($F$200="Construction Financing",'Rent Roll'!G18,'Rent Roll'!G5) -> 0 | F7: =+IF($F$200="Construction Financing",'Rent Roll'!H18,'Rent Roll'!H5) -> 0 | G7: =+IF($F$200="Construction Financing",'Rent Roll'!I18,'Rent Roll'!I5) -> - | H7: =+IF($F$200="Construction Financing",'Rent Roll'!J18,'Rent Roll'!J5) -> 0 | I7: =+IF($F$200="Construction Financing",'Rent Roll'!K18,'Rent Roll'!K5) -> - | J7: =IFERROR(I7/G7,"") | N7: =C7 -> 2 Bedroom | P7: =+E7 -> 0 | Q7: =+F7 -> 0 | R7: =+G7 -> - | S7: =+H7 -> 0 | T7: =+I7 -> - | U7: =IFERROR(T7/R7,"") | W7: =X7*F7*12 -> 0 | AA7: =AB7*F7*12 -> 0 | AD7: =HLOOKUP($AE$36,$H$3:$AA$33,ROW()-2,FALSE)-HLOOKUP($AE$35,$H$3:$AA$33,ROW()-2,FALSE) -> #N/A | AE7: =IFERROR(AD7/F7/12,"") | AF7: =IFERROR(AD7/HLOOKUP($AE$35,$H$3:$AA$33,5,FALSE),"") | AJ7: =IFERROR(IF(ISBLANK(AI7),"-",+I7-AI7),"-") -> -
C8: 3 Bedroom | E8: =+IF($F$200="Construction Financing",'Rent Roll'!G19,'Rent Roll'!G6) -> 0 | F8: =+IF($F$200="Construction Financing",'Rent Roll'!H19,'Rent Roll'!H6) -> 0 | G8: =+IF($F$200="Construction Financing",'Rent Roll'!I19,'Rent Roll'!I6) -> - | H8: =+IF($F$200="Construction Financing",'Rent Roll'!J19,'Rent Roll'!J6) -> 0 | I8: =+IF($F$200="Construction Financing",'Rent Roll'!K19,'Rent Roll'!K6) -> - | J8: =IFERROR(I8/G8,"") | N8: =C8 -> 3 Bedroom | P8: =+E8 -> 0 | Q8: =+F8 -> 0 | R8: =+G8 -> - | S8: =+H8 -> 0 | T8: =+I8 -> - | U8: =IFERROR(T8/R8,"") | W8: =X8*F8*12 -> 0 | AA8: =AB8*F8*12 -> 0 | AD8: =HLOOKUP($AE$36,$H$3:$AA$33,ROW()-2,FALSE)-HLOOKUP($AE$35,$H$3:$AA$33,ROW()-2,FALSE) -> #N/A | AE8: =IFERROR(AD8/F8/12,"") | AF8: =IFERROR(AD8/HLOOKUP($AE$35,$H$3:$AA$33,6,FALSE),"") | AJ8: =IFERROR(IF(ISBLANK(AI8),"-",+I8-AI8),"-") -> -
C9: 4+ Bedroom | E9: =+IF($F$200="Construction Financing",'Rent Roll'!G20,'Rent Roll'!G7) -> 0 | F9: =+IF($F$200="Construction Financing",'Rent Roll'!H20,'Rent Roll'!H7) -> 0 | G9: =+IF($F$200="Construction Financing",'Rent Roll'!I20,'Rent Roll'!I7) -> - | H9: =+IF($F$200="Construction Financing",'Rent Roll'!J20,'Rent Roll'!J7) -> 0 | I9: =+IF($F$200="Construction Financing",'Rent Roll'!K20,'Rent Roll'!K7) -> - | J9: =IFERROR(I9/G9,"") | N9: =C9 -> 4+ Bedroom | P9: =+E9 -> 0 | Q9: =+F9 -> 0 | R9: =+G9 -> - | S9: =+H9 -> 0 | T9: =+I9 -> - | U9: =IFERROR(T9/R9,"") | W9: =X9*F9*12 -> 0 | AA9: =AB9*F9*12 -> 0 | AD9: =HLOOKUP($AE$36,$H$3:$AA$33,ROW()-2,FALSE)-HLOOKUP($AE$35,$H$3:$AA$33,ROW()-2,FALSE) -> #N/A | AE9: =IFERROR(AD9/F9/12,"") | AF9: =IFERROR(AD9/HLOOKUP($AE$35,$H$3:$AA$33,7,FALSE),"") | AJ9: =IFERROR(IF(ISBLANK(AI9),"-",+I9-AI9),"-") -> -
C10: Bachelor (Affordable) | E10: =+IF($F$200="Construction Financing",'Rent Roll'!G21,'Rent Roll'!G8) -> 0 | F10: =+IF($F$200="Construction Financing",'Rent Roll'!H21,'Rent Roll'!H8) -> 0 | G10: =+IF($F$200="Construction Financing",'Rent Roll'!I21,'Rent Roll'!I8) -> - | H10: =+IF($F$200="Construction Financing",'Rent Roll'!J21,'Rent Roll'!J8) -> 0 | I10: =+IF($F$200="Construction Financing",'Rent Roll'!K21,'Rent Roll'!K8) -> - | J10: =IFERROR(I10/G10,"") | N10: =C10 -> Bachelor (Affordable) | P10: =+E10 -> 0 | Q10: =+F10 -> 0 | R10: =+G10 -> - | S10: =+H10 -> 0 | T10: =+I10 -> - | U10: =IFERROR(T10/R10,"") | W10: =X10*F10*12 -> 0 | AA10: =AB10*F10*12 -> 0 | AD10: =HLOOKUP($AE$36,$H$3:$AA$33,ROW()-2,FALSE)-HLOOKUP($AE$35,$H$3:$AA$33,ROW()-2,FALSE) -> #N/A | AE10: =IFERROR(AD10/F10/12,"") | AF10: =IFERROR(AD10/HLOOKUP($AE$35,$H$3:$AA$33,8,FALSE),"") | AJ10: =IFERROR(IF(ISBLANK(AI10),"-",+I10-AI10),"-") -> -
C11: 1 Bedroom (Affordable) | E11: =+IF($F$200="Construction Financing",'Rent Roll'!G22,'Rent Roll'!G9) -> 0 | F11: =+IF($F$200="Construction Financing",'Rent Roll'!H22,'Rent Roll'!H9) -> 0 | G11: =+IF($F$200="Construction Financing",'Rent Roll'!I22,'Rent Roll'!I9) -> - | H11: =+IF($F$200="Construction Financing",'Rent Roll'!J22,'Rent Roll'!J9) -> 0 | I11: =+IF($F$200="Construction Financing",'Rent Roll'!K22,'Rent Roll'!K9) -> - | J11: =IFERROR(I11/G11,"") | N11: =C11 -> 1 Bedroom (Affordable) | P11: =+E11 -> 0 | Q11: =+F11 -> 0 | R11: =+G11 -> - | S11: =+H11 -> 0 | T11: =+I11 -> - | U11: =IFERROR(T11/R11,"") | W11: =X11*F11*12 -> 0 | AA11: =AB11*F11*12 -> 0 | AD11: =HLOOKUP($AE$36,$H$3:$AA$33,ROW()-2,FALSE)-HLOOKUP($AE$35,$H$3:$AA$33,ROW()-2,FALSE) -> #N/A | AE11: =IFERROR(AD11/F11/12,"") | AF11: =IFERROR(AD11/HLOOKUP($AE$35,$H$3:$AA$33,9,FALSE),"") | AJ11: =IFERROR(IF(ISBLANK(AI11),"-",+I11-AI11),"-") -> -
C12: 2 Bedroom (Affordable) | E12: =+IF($F$200="Construction Financing",'Rent Roll'!G23,'Rent Roll'!G10) -> 0 | F12: =+IF($F$200="Construction Financing",'Rent Roll'!H23,'Rent Roll'!H10) -> 0 | G12: =+IF($F$200="Construction Financing",'Rent Roll'!I23,'Rent Roll'!I10) -> - | H12: =+IF($F$200="Construction Financing",'Rent Roll'!J23,'Rent Roll'!J10) -> 0 | I12: =+IF($F$200="Construction Financing",'Rent Roll'!K23,'Rent Roll'!K10) -> - | J12: =IFERROR(I12/G12,"") | N12: =C12 -> 2 Bedroom (Affordable) | P12: =+E12 -> 0 | Q12: =+F12 -> 0 | R12: =+G12 -> - | S12: =+H12 -> 0 | T12: =+I12 -> - | U12: =IFERROR(T12/R12,"") | W12: =X12*F12*12 -> 0 | AA12: =AB12*F12*12 -> 0 | AD12: =HLOOKUP($AE$36,$H$3:$AA$33,ROW()-2,FALSE)-HLOOKUP($AE$35,$H$3:$AA$33,ROW()-2,FALSE) -> #N/A | AE12: =IFERROR(AD12/F12/12,"") | AF12: =IFERROR(AD12/HLOOKUP($AE$35,$H$3:$AA$33,10,FALSE),"") | AJ12: =IFERROR(IF(ISBLANK(AI12),"-",+I12-AI12),"-") -> -
C13: 3 Bedroom (Affordable) | E13: =+IF($F$200="Construction Financing",'Rent Roll'!G24,'Rent Roll'!G11) -> 0 | F13: =+IF($F$200="Construction Financing",'Rent Roll'!H24,'Rent Roll'!H11) -> 0 | G13: =+IF($F$200="Construction Financing",'Rent Roll'!I24,'Rent Roll'!I11) -> - | H13: =+IF($F$200="Construction Financing",'Rent Roll'!J24,'Rent Roll'!J11) -> 0 | I13: =+IF($F$200="Construction Financing",'Rent Roll'!K24,'Rent Roll'!K11) -> - | J13: =IFERROR(I13/G13,"") | N13: =C13 -> 3 Bedroom (Affordable) | P13: =+E13 -> 0 | Q13: =+F13 -> 0 | R13: =+G13 -> - | S13: =+H13 -> 0 | T13: =+I13 -> - | U13: =IFERROR(T13/R13,"") | W13: =X13*F13*12 -> 0 | AA13: =AB13*F13*12 -> 0 | AD13: =HLOOKUP($AE$36,$H$3:$AA$33,ROW()-2,FALSE)-HLOOKUP($AE$35,$H$3:$AA$33,ROW()-2,FALSE) -> #N/A | AE13: =IFERROR(AD13/F13/12,"") | AF13: =IFERROR(AD13/HLOOKUP($AE$35,$H$3:$AA$33,11,FALSE),"") | AJ13: =IFERROR(IF(ISBLANK(AI13),"-",+I13-AI13),"-") -> -
C14: 4+ Bedroom (Affordable) | E14: =+IF($F$200="Construction Financing",'Rent Roll'!G25,'Rent Roll'!G12) -> 0 | F14: =+IF($F$200="Construction Financing",'Rent Roll'!H25,'Rent Roll'!H12) -> 0 | G14: =+IF($F$200="Construction Financing",'Rent Roll'!I25,'Rent Roll'!I12) -> - | H14: =+IF($F$200="Construction Financing",'Rent Roll'!J25,'Rent Roll'!J12) -> 0 | I14: =+IF($F$200="Construction Financing",'Rent Roll'!K25,'Rent Roll'!K12) -> - | J14: =IFERROR(I14/G14,"") | N14: =C14 -> 4+ Bedroom (Affordable) | P14: =+E14 -> 0 | Q14: =+F14 -> 0 | R14: =+G14 -> - | S14: =+H14 -> 0 | T14: =+I14 -> - | U14: =IFERROR(T14/R14,"") | W14: =X14*F14*12 -> 0 | AA14: =AB14*F14*12 -> 0 | AD14: =HLOOKUP($AE$36,$H$3:$AA$33,ROW()-2,FALSE)-HLOOKUP($AE$35,$H$3:$AA$33,ROW()-2,FALSE) -> #N/A | AE14: =IFERROR(AD14/F14/12,"") | AF14: =IFERROR(AD14/HLOOKUP($AE$35,$H$3:$AA$33,12,FALSE),"") | AJ14: =IFERROR(IF(ISBLANK(AI14),"-",+I14-AI14),"-") -> -
C15: Total Rental Income | E15: =+SUM(E5:E14) -> 0 | F15: =+SUM(F5:F14) -> 0 | G15: =IF(SUMPRODUCT(F5:F14,G5:G14)/F15=0,"-",SUMPRODUCT(F5:F14,G5:G14)/F15) -> #DIV/0! | H15: =+SUM(H5:H14) -> 0 | I15: =H15/F15/12 -> #DIV/0! | J15: =IFERROR(I15/G15,"N/A") -> N/A | N15: Total Rental Income | P15: =+SUM(P5:P14) -> 0 | Q15: =+SUM(Q5:Q14) -> 0 | R15: =IF(SUMPRODUCT(Q5:Q14,R5:R14)/Q15=0,"-",SUMPRODUCT(Q5:Q14,R5:R14)/Q15) -> #DIV/0! | S15: =+SUM(S5:S14) -> 0 | T15: =S15/Q15/12 -> #DIV/0! | U15: =IFERROR(I15/G15,"N/A") -> N/A | W15: =SUBTOTAL(9,W4:W14) -> 0 | X15: =W15/F15/12 -> #DIV/0! | AA15: =SUBTOTAL(9,AA5:AA14) -> 0 | AB15: =AA15/$F$15/12 -> #DIV/0! | AD15: =HLOOKUP($AE$36,$H$3:$AA$33,ROW()-2,FALSE)-HLOOKUP($AE$35,$H$3:$AA$33,ROW()-2,FALSE) -> #N/A | AE15: =AD15/$F$15 -> #N/A | AF15: =IFERROR(AD15/HLOOKUP($AE$35,$H$3:$AA$33,13,FALSE),"")
C16: (+) UG Parking | E16: 1 | F16: 0 | G16: 0 | H16: =F16*E16*(G16*12) -> 0 | N16: (+) UG Parking | P16: =+E16 -> 1 | Q16: =+F16 -> 0 | R16: =+G16 -> 0 | S16: =Q16*P16*(R16*12) -> 0 | AD16: =HLOOKUP($AE$36,$H$3:$AA$33,ROW()-2,FALSE)-HLOOKUP($AE$35,$H$3:$AA$33,ROW()-2,FALSE) -> #N/A | AE16: =AD16/$F$15 -> #N/A | AF16: =IFERROR(AD16/HLOOKUP($AE$35,$H$3:$AA$33,15,FALSE),"")
C17: (+) EX Parking | E17: 1 | F17: 0 | G17: 0 | H17: =F17*E17*(G17*12) -> 0 | N17: (+) EX Parking | P17: =+E17 -> 1 | Q17: =+F17 -> 0 | R17: =+G17 -> 0 | S17: =Q17*P17*(R17*12) -> 0 | AD17: =HLOOKUP($AE$36,$H$3:$AA$33,ROW()-2,FALSE)-HLOOKUP($AE$35,$H$3:$AA$33,ROW()-2,FALSE) -> #N/A | AE17: =AD17/$F$15 -> #N/A | AF17: =IFERROR(AD17/HLOOKUP($AE$35,$H$3:$AA$33,16,FALSE),"") | AJ17: CMHC Zone | AK17: 2023 | AL17: =AK17-1 -> 2022 | AM17: =AL17-1 -> 2021 | AN17: =AM17-1 -> 2020 | AO17: =AN17-1 -> 2019 | AP17: 5Y Avg | AQ17: Subject Vacancy
C18: (+) Storage | E18: 1 | F18: 0 | G18: 0 | H18: =F18*E18*(G18*12) -> 0 | N18: (+) Storage | P18: =+E18 -> 1 | Q18: =+F18 -> 0 | R18: =+G18 -> 0 | S18: =Q18*P18*(R18*12) -> 0 | AD18: =HLOOKUP($AE$36,$H$3:$AA$33,ROW()-2,FALSE)-HLOOKUP($AE$35,$H$3:$AA$33,ROW()-2,FALSE) -> #N/A | AE18: =AD18/$F$15 -> #N/A | AF18: =IFERROR(AD18/HLOOKUP($AE$35,$H$3:$AA$33,16,FALSE),"") | AI18: Vacancy | AP18: =IFERROR(AVERAGE($AK$18:$AO$18),"-") -> - | AQ18: =IF(F15=0,"-",1-E15/F15) -> -
C19: (+) Other | H19: 0 | I19: =H19/$F$15 -> #DIV/0! | N19: (+) Other | S19: =+H19 -> 0 | T19: =S19/$F$15 -> #DIV/0! | AD19: =HLOOKUP($AE$36,$H$3:$AA$33,ROW()-2,FALSE)-HLOOKUP($AE$35,$H$3:$AA$33,ROW()-2,FALSE) -> #N/A | AE19: =AD19/$F$15 -> #N/A | AF19: =IFERROR(AD19/HLOOKUP($AE$35,$H$3:$AA$33,16,FALSE),"") | AI19: Rent YoY Change | AP19: =IFERROR(AVERAGE($AK$19:$AO$19),"-") -> -
C20: (-) Incentives | H20: 0 | I20: =H20/$F$15 -> #DIV/0! | N20: (-) Incentives | S20: =+H20 -> 0 | T20: =S20/$F$15 -> #DIV/0! | AD20: =HLOOKUP($AE$36,$H$3:$AA$33,ROW()-2,FALSE)-HLOOKUP($AE$35,$H$3:$AA$33,ROW()-2,FALSE) -> #N/A | AE20: =AD20/$F$15 -> #N/A | AF20: =IFERROR(AD20/HLOOKUP($AE$35,$H$3:$AA$33,16,FALSE),"")
C21: Potential Gross Income | H21: =+SUM(H15:H20) -> 0 | I21: =H21/F15/12 -> #DIV/0! | N21: Potential Gross Income | S21: =+SUM(S15:S20) -> 0 | T21: =S21/$Q$15/12 -> #DIV/0! | AA21: =SUBTOTAL(9,AA4:AA18) -> 0 | AB21: =AA21/$F$15/12 -> #DIV/0! | AD21: =HLOOKUP($AE$36,$H$3:$AA$33,ROW()-2,FALSE)-HLOOKUP($AE$35,$H$3:$AA$33,ROW()-2,FALSE) -> #N/A | AE21: =AD21/$F$15 -> #N/A | AF21: =IFERROR(AD21/HLOOKUP($AE$35,$H$3:$AA$33,16,FALSE),"") | AI21: =+G22 -> 0
C22: (-) Vacancy/bad debt | H22: =-H21*G22 -> 0 | N22: (-) Vacancy/bad debt | R22: =+G22 -> 0 | S22: =-S21*R22 -> 0 | AD22: =HLOOKUP($AE$36,$H$3:$AA$33,ROW()-2,FALSE)-HLOOKUP($AE$35,$H$3:$AA$33,ROW()-2,FALSE) -> #N/A | AE22: =AD22/$F$15 -> #N/A | AF22: =IFERROR(AD22/HLOOKUP($AE$35,$H$3:$AA$33,19,FALSE),"")
C23: Effective Gross Income | H23: =+SUM(H21:H22) -> 0 | I23: =H23/F15/12 -> #DIV/0! | N23: Effective Gross Income | S23: =+SUM(S21:S22) -> 0 | T23: =S23/$Q$15/12 -> #DIV/0! | AA23: =SUBTOTAL(9,AA4:AA22) -> 0 | AB23: =AA23/$F$15/12 -> #DIV/0! | AD23: =HLOOKUP($AE$36,$H$3:$AA$33,ROW()-2,FALSE)-HLOOKUP($AE$35,$H$3:$AA$33,ROW()-2,FALSE) -> #N/A | AE23: =AD23/$F$15 -> #N/A | AF23: =IFERROR(AD23/HLOOKUP($AE$35,$H$3:$AA$33,20,FALSE),"") | AI23: Opex | AJ23: 2024 Bills | AK23: 2024 O/S | AL23: 2024 Appraisal | AM23: KS Estimate | AN23: <- Change source description here, if applicable
C24: =+BenchmarkBackEnd!D4 -> (-) Property Taxes | H24: =IF(G24="",MAX(AJ24:AM24),_xlfn.XLOOKUP(G24,$AJ$23:$AM$23,$AJ24:$AM24))*(1+$AJ$30) -> 0 | I24: =H24/$F$15 -> #DIV/0! | N24: =+BenchmarkBackEnd!D4 -> (-) Property Taxes | S24: =+H24 -> 0 | T24: =S24/$Q$15 -> #DIV/0! | W24: =X24*$F$15 -> 0 | X24: =SUMIFS(BenchmarkBackEnd!$E:$E,BenchmarkBackEnd!$A:$A,Economics!$F$201,BenchmarkBackEnd!$B:$B,Economics!$F$206,BenchmarkBackEnd!$C:$C,Economics!$F$210,BenchmarkBackEnd!$D:$D,Economics!$C24) -> 0 | Y24: =SUMIFS(BenchmarkBackEnd!$F:$F,BenchmarkBackEnd!$A:$A,Economics!$F$201,BenchmarkBackEnd!$B:$B,Economics!$F$206,BenchmarkBackEnd!$C:$C,Economics!$F$210,BenchmarkBackEnd!$D:$D,Economics!$C24) -> 0 | AB24: =AA24/$F$15 -> #DIV/0! | AD24: =HLOOKUP($AE$36,$H$3:$AA$33,ROW()-2,FALSE)-HLOOKUP($AE$35,$H$3:$AA$33,ROW()-2,FALSE) -> #N/A | AE24: =AD24/$F$15 -> #N/A | AF24: =IFERROR(AD24/HLOOKUP($AE$35,$H$3:$AA$33,21,FALSE),"") | AI24: Property Taxes | AJ24: 0 | AK24: 0 | AL24: 0 | AM24: 0
C25: =+BenchmarkBackEnd!D5 -> (-) Insurance | H25: =IF(G25="",MAX(AJ25:AM25),_xlfn.XLOOKUP(G25,$AJ$23:$AM$23,$AJ25:$AM25))*(1+$AJ$30) -> 0 | I25: =H25/$F$15 -> #DIV/0! | N25: =+BenchmarkBackEnd!D5 -> (-) Insurance | S25: =+H25 -> 0 | T25: =S25/$Q$15 -> #DIV/0! | W25: =X25*$F$15 -> 0 | X25: =SUMIFS(BenchmarkBackEnd!$E:$E,BenchmarkBackEnd!$A:$A,Economics!$F$201,BenchmarkBackEnd!$B:$B,Economics!$F$206,BenchmarkBackEnd!$C:$C,Economics!$F$210,BenchmarkBackEnd!$D:$D,Economics!$C25) -> 0 | Y25: =SUMIFS(BenchmarkBackEnd!$F:$F,BenchmarkBackEnd!$A:$A,Economics!$F$201,BenchmarkBackEnd!$B:$B,Economics!$F$206,BenchmarkBackEnd!$C:$C,Economics!$F$210,BenchmarkBackEnd!$D:$D,Economics!$C25) -> 0 | AB25: =AA25/$F$15 -> #DIV/0! | AD25: =HLOOKUP($AE$36,$H$3:$AA$33,ROW()-2,FALSE)-HLOOKUP($AE$35,$H$3:$AA$33,ROW()-2,FALSE) -> #N/A | AE25: =AD25/$F$15 -> #N/A | AF25: =IFERROR(AD25/HLOOKUP($AE$35,$H$3:$AA$33,22,FALSE),"") | AI25: Insurance | AJ25: 0 | AK25: 0 | AL25: 0 | AM25: 0
C26: =+BenchmarkBackEnd!D6 -> (-) Utilities | D26: Landlord pays heating & hydro | H26: =IF(G26="",MAX(AJ26:AM26),_xlfn.XLOOKUP(G26,$AJ$23:$AM$23,$AJ26:$AM26))*(1+$AJ$30) -> 0 | I26: =H26/$F$15 -> #DIV/0! | N26: =+BenchmarkBackEnd!D6 -> (-) Utilities | S26: =+H26 -> 0 | T26: =S26/$Q$15 -> #DIV/0! | W26: =X26*$F$15 -> 0 | X26: =SUMIFS(BenchmarkBackEnd!$E:$E,BenchmarkBackEnd!$A:$A,Economics!$F$201,BenchmarkBackEnd!$B:$B,Economics!$F$206,BenchmarkBackEnd!$C:$C,Economics!$F$210,BenchmarkBackEnd!$D:$D,Economics!$C26) -> 0 | Y26: =SUMIFS(BenchmarkBackEnd!$F:$F,BenchmarkBackEnd!$A:$A,Economics!$F$201,BenchmarkBackEnd!$B:$B,Economics!$F$206,BenchmarkBackEnd!$C:$C,Economics!$F$210,BenchmarkBackEnd!$D:$D,Economics!$C26) -> 0 | AB26: =AA26/$F$15 -> #DIV/0! | AD26: =HLOOKUP($AE$36,$H$3:$AA$33,ROW()-2,FALSE)-HLOOKUP($AE$35,$H$3:$AA$33,ROW()-2,FALSE) -> #N/A | AE26: =AD26/$F$15 -> #N/A | AF26: =IFERROR(AD26/HLOOKUP($AE$35,$H$3:$AA$33,23,FALSE),"") | AI26: Utilities | AJ26: =Utilities!D21 -> 0 | AK26: 0 | AL26: 0 | AM26: 0
C27: =+BenchmarkBackEnd!D7 -> (-) Repairs and Maintenance | H27: =I27*$F$15 -> 0 | I27: =X27*(1+$AK$30) -> 4675 | N27: =+BenchmarkBackEnd!D7 -> (-) Repairs and Maintenance | S27: =T27*Q15 -> 0 | T27: =+I27 -> 4675 | W27: =X27*$F$15 -> 0 | X27: =SUMIFS(BenchmarkBackEnd!$E:$E,BenchmarkBackEnd!$A:$A,Economics!$F$201,BenchmarkBackEnd!$B:$B,Economics!$F$206,BenchmarkBackEnd!$C:$C,Economics!$F$210,BenchmarkBackEnd!$D:$D,Economics!$C27) -> 4675 | Y27: =SUMIFS(BenchmarkBackEnd!$F:$F,BenchmarkBackEnd!$A:$A,Economics!$F$201,BenchmarkBackEnd!$B:$B,Economics!$F$206,BenchmarkBackEnd!$C:$C,Economics!$F$210,BenchmarkBackEnd!$D:$D,Economics!$C27) -> 0 | AB27: =AA27/$F$15 -> #DIV/0! | AD27: =HLOOKUP($AE$36,$H$3:$AA$33,ROW()-2,FALSE)-HLOOKUP($AE$35,$H$3:$AA$33,ROW()-2,FALSE) -> #N/A | AE27: =AD27/$F$15 -> #N/A | AF27: =IFERROR(AD27/HLOOKUP($AE$35,$H$3:$AA$33,24,FALSE),"")
C28: =+BenchmarkBackEnd!D8 -> (-) Payroll & Administration | H28: =I28*$F$15 -> 0 | I28: =X28*(1+$AK$30) -> 3285 | N28: =+BenchmarkBackEnd!D8 -> (-) Payroll & Administration | S28: =T28*Q15 -> 0 | T28: =+I28 -> 3285 | W28: =X28*$F$15 -> 0 | X28: =SUMIFS(BenchmarkBackEnd!$E:$E,BenchmarkBackEnd!$A:$A,Economics!$F$201,BenchmarkBackEnd!$B:$B,Economics!$F$206,BenchmarkBackEnd!$C:$C,Economics!$F$210,BenchmarkBackEnd!$D:$D,Economics!$C28) -> 3285 | Y28: =SUMIFS(BenchmarkBackEnd!$F:$F,BenchmarkBackEnd!$A:$A,Economics!$F$201,BenchmarkBackEnd!$B:$B,Economics!$F$206,BenchmarkBackEnd!$C:$C,Economics!$F$210,BenchmarkBackEnd!$D:$D,Economics!$C28) -> 0 | AB28: =AA28/$F$15 -> #DIV/0! | AD28: =HLOOKUP($AE$36,$H$3:$AA$33,ROW()-2,FALSE)-HLOOKUP($AE$35,$H$3:$AA$33,ROW()-2,FALSE) -> #N/A | AE28: =AD28/$F$15 -> #N/A | AF28: =IFERROR(AD28/HLOOKUP($AE$35,$H$3:$AA$33,25,FALSE),"") | AI28: Growth | AJ28: Annualized | AK28: Total
C29: =+BenchmarkBackEnd!D10 -> (-) Other | G29: =Y29 -> 0.061 | H29: =G29*$H$23 -> 0 | I29: =H29/$F$15 -> #DIV/0! | N29: =+BenchmarkBackEnd!D10 -> (-) Other | R29: =+G29 -> 0.061 | S29: =R29*$S$23 -> 0 | T29: =S29/$Q$15 -> #DIV/0! | W29: =X29*F15 -> 0 | X29: =SUMIFS(BenchmarkBackEnd!$E:$E,BenchmarkBackEnd!$A:$A,Economics!$F$201,BenchmarkBackEnd!$B:$B,Economics!$F$206,BenchmarkBackEnd!$C:$C,Economics!$F$210,BenchmarkBackEnd!$D:$D,Economics!$C29) -> 0 | Y29: =SUMIFS(BenchmarkBackEnd!$F:$F,BenchmarkBackEnd!$A:$A,Economics!$F$201,BenchmarkBackEnd!$B:$B,Economics!$F$206,BenchmarkBackEnd!$C:$C,Economics!$F$210,BenchmarkBackEnd!$D:$D,Economics!$C29) -> 0.061 | AB29: =AA29/$F$15 -> #DIV/0! | AD29: =HLOOKUP($AE$36,$H$3:$AA$33,ROW()-2,FALSE)-HLOOKUP($AE$35,$H$3:$AA$33,ROW()-2,FALSE) -> #N/A | AE29: =AD29/$F$15 -> #N/A | AF29: =IFERROR(AD29/HLOOKUP($AE$35,$H$3:$AA$33,26,FALSE),"") | AI29: Rent | AJ29: 0 | AK29: =$AJ$29*Economics!$I$65 -> 0
C30: =+BenchmarkBackEnd!D11 -> (-) Management Fee | G30: =Y30 -> 0.22 | H30: =G30*$H$23 -> 0 | I30: =H30/$F$15 -> #DIV/0! | N30: =+BenchmarkBackEnd!D11 -> (-) Management Fee | R30: =+G30 -> 0.22 | S30: =R30*$S$23 -> 0 | T30: =S30/$Q$15 -> #DIV/0! | W30: =X30*F15 -> 0 | X30: =SUMIFS(BenchmarkBackEnd!$E:$E,BenchmarkBackEnd!$A:$A,Economics!$F$201,BenchmarkBackEnd!$B:$B,Economics!$F$206,BenchmarkBackEnd!$C:$C,Economics!$F$210,BenchmarkBackEnd!$D:$D,Economics!$C30) -> 0 | Y30: =SUMIFS(BenchmarkBackEnd!$F:$F,BenchmarkBackEnd!$A:$A,Economics!$F$201,BenchmarkBackEnd!$B:$B,Economics!$F$206,BenchmarkBackEnd!$C:$C,Economics!$F$210,BenchmarkBackEnd!$D:$D,Economics!$C30) -> 0.22 | AB30: =AA30/$F$15 -> #DIV/0! | AD30: =HLOOKUP($AE$36,$H$3:$AA$33,ROW()-2,FALSE)-HLOOKUP($AE$35,$H$3:$AA$33,ROW()-2,FALSE) -> #N/A | AE30: =AD30/$F$15 -> #N/A | AF30: =IFERROR(AD30/HLOOKUP($AE$35,$H$3:$AA$33,27,FALSE),"") | AI30: Opex | AJ30: 0 | AK30: =$AJ$30*$I$65 -> 0
C31: =+BenchmarkBackEnd!D12 -> (-) Replacement Reserve | H31: =W31*(1+$AK$30) -> 0 | I31: =H31/$F$15 -> #DIV/0! | N31: =+BenchmarkBackEnd!D12 -> (-) Replacement Reserve | S31: =+H31 -> 0 | T31: =S31/$Q$15 -> #DIV/0! | W31: =(F214*60*F15+F215*190+F216*12*300) -> 0 | X31: =F214*60 -> 0 | AB31: =AA31/$F$15 -> #DIV/0! | AD31: =HLOOKUP($AE$36,$H$3:$AA$33,ROW()-2,FALSE)-HLOOKUP($AE$35,$H$3:$AA$33,ROW()-2,FALSE) -> #N/A | AE31: =AD31/$F$15 -> #N/A | AF31: =IFERROR(AD31/HLOOKUP($AE$35,$H$3:$AA$33,28,FALSE),"") | AI31: Apply only for construction loans
C32: Operating Expenses | G32: =H32/H23 -> #DIV/0! | H32: =+SUM(H24:H31) -> 0 | I32: =H32/$F$15 -> #DIV/0! | N32: Operating Expenses | R32: =S32/S23 -> #DIV/0! | S32: =+SUM(S24:S31) -> 0 | T32: =S32/$Q$15 -> #DIV/0! | W32: =SUM(W24:W31) -> 0 | X32: =SUMIFS(BenchmarkBackEnd!$E:$E,BenchmarkBackEnd!$A:$A,Economics!$F$201,BenchmarkBackEnd!$B:$B,Economics!$F$206,BenchmarkBackEnd!$C:$C,Economics!$F$210,BenchmarkBackEnd!$D:$D,Economics!$C32) -> 0 | Y32: =SUMIFS(BenchmarkBackEnd!$F:$F,BenchmarkBackEnd!$A:$A,Economics!$F$201,BenchmarkBackEnd!$B:$B,Economics!$F$206,BenchmarkBackEnd!$C:$C,Economics!$F$210,BenchmarkBackEnd!$D:$D,Economics!$C32) -> 0 | AA32: =SUM(AA24:AA31) -> 0 | AB32: =AA32/$F$15 -> #DIV/0! | AD32: =HLOOKUP($AE$36,$H$3:$AA$33,ROW()-2,FALSE)-HLOOKUP($AE$35,$H$3:$AA$33,ROW()-2,FALSE) -> #N/A | AE32: =AD32/$F$15 -> #N/A | AF32: =IFERROR(AD32/HLOOKUP($AE$35,$H$3:$AA$33,29,FALSE),"")
C33: NOI | H33: =+H23-H32 -> 0 | I33: =H33/$F$15 -> #DIV/0! | N33: NOI | S33: =S23-S32 -> 0 | T33: =S33/$Q$15 -> #DIV/0! | AA33: =AA23-AA32 -> 0 | AB33: =AA33/$F$15 -> #DIV/0! | AD33: =HLOOKUP($AE$36,$H$3:$AA$33,ROW()-2,FALSE)-HLOOKUP($AE$35,$H$3:$AA$33,ROW()-2,FALSE) -> #N/A | AE33: =AD33/$F$15 -> #N/A | AF33: =IFERROR(AD33/HLOOKUP($AE$35,$H$3:$AA$33,29,FALSE),"")
C34: Value | F34: UW Cap Rate: | H34: =IFERROR(ROUND(H33/G34,-4),0) -> 0 | I34: =H34/$F$15 -> #DIV/0! | J34: =IFERROR(I34/G15,"N/A") -> N/A | N34: Value | Q34: UW Cap Rate: | S34: =S33/R34 -> #DIV/0! | T34: =S34/$Q$15 -> #DIV/0! | U34: =T34/$R$15 -> #DIV/0!
N35: Less: Cost to Complete | T35: =S35/$Q$15 -> #DIV/0! | U35: =T35/$R$15 -> #DIV/0! | AD35: Base
C36: Commercial | E36: Move-In | F36: Expiry | G36: Area | H36: Total | I36: Rate | N36: Adj. Value | Q36: Ind Cap Rate: | R36: =S33/S36 -> #DIV/0! | S36: =S34-S35 -> #DIV/0! | T36: =S36/$Q$15 -> #DIV/0! | U36: =T36/$R$15 -> #DIV/0! | AD36: Comparison
C37: Tenant 1 | H37: =G37*I37 -> 0
C38: Tenant 2 | H38: =G38*I38 -> 0 | N38: Loan Details | S38: SMF | T38: MLP | U38: Blended | AI38: Bridge Guidelines
C39: Tenant 3 | H39: =G39*I39 -> 0 | N39: Loan Amount | S39: 0 | T39: =S75 -> #N/A | U39: =+S79 -> #N/A | AI39: SMF capped at 65% LTV
C40: Tenant 4 | H40: =G40*I40 -> 0 | N40: Loan Split | S40: =+S39/$U$39 -> #N/A | T40: =+T39/$U$39 -> #N/A | U40: =+SUM(S40:T40) -> #N/A | AI40: Target approx. 70% SMF/30% MLP loan split or as Bryan permits
C41: Tenant 5 | H41: =G41*I41 -> 0 | N41: Lender | S41: KingSett | T41: KingSett
C42: Total Base Rent | G42: =+SUM(G37:G41) -> 0 | H42: =+SUM(H37:H41) -> 0 | I42: =H42/$G$42 -> #DIV/0! | N42: Prepayment Option | S42: Open after 6 | T42: Open after 6 | AI42: Open after 3 or 6 months (talk to Shawn). Generally only prepayable by CMHC refi (even if it's by another lender)
C43: (+) Parking | I43: =H43/$G$42 -> #DIV/0! | N43: Extension Option | S43: N/A | T43: N/A
C44: (+) Recoveries | H44: =+H48 -> 0 | I44: =H44/$G$42 -> #DIV/0! | N44: Term | S44: 12 | T44: 12 | AI44: client sees the "Blended" column numbers (not SMF/MLP breakdown), so keep numbers round
C45: Gross Rent | H45: =+SUM(H42:H44) -> 0 | I45: =H45/$G$42 -> #DIV/0! | N45: Amortization | S45: I/O | T45: I/O | AI45: 0.0495 | AJ45: Prime Rate
C46: (-) Vacancy/bad debt | H46: =-G46*H45 -> 0 | I46: =H46/$G$42 -> #DIV/0! | N46: Fee | S46: 0 | T46: 0 | U46: =(S46*S74+T46*S75)/S79 -> #N/A | AI46: SMF - min. 40bps per 12 mo. term / MLP - min. 100bps per 12 mo. term
C47: Effective Gross Income (EGI) | H47: =+SUM(H45:H46) -> 0 | I47: =H47/$G$42 -> #DIV/0! | N47: Interest Rate (Floor) | S47: =+$AI$45+S48 -> 0.0495 | T47: =+$AI$45+T48 -> #N/A | U47: =(S74*S47+S75*T47)/S79 -> #N/A | AJ47: Blended Floor (hardcode to T47 value to avoid circular reference)
C48: (-) Recoverable Expenses | I48: =H48/$G$42 -> #DIV/0! | N48: Fixed/Floating | S48: 0 | T48: =+((U39*U48)-(S39*S48))/T39 -> #N/A | U48: =+AI47-AI45 -> -0.0495 | AI48: SMF - min. 2.25% spread / MLP - min. 5.5% spread
C49: (-) Management Fee & Structural Reserve | H49: =+G49*H47 -> 0 | I49: =H49/$G$42 -> #DIV/0! | N49: Interest Reserve | S49: 0 | T49: 0 | U49: =+SUM(S49:T49) -> 0
C50: Operating Expenses | H50: =+SUM(H48:H49) -> 0 | I50: =H50/$G$42 -> #DIV/0!
C51: NOI | H51: =H47-H50 -> 0 | I51: =H51/$G$42 -> #DIV/0! | N51: Key Metrics | S51: SMF | T51: MLP
C52: Commercial Value | F52: UW Cap Rate: | H52: =IFERROR(ROUND(H51/G52,-4),0) -> 0 | I52: =H52/$G$42 -> #DIV/0! | N52: NOI / Debt | S52: =S33/S74 -> #DIV/0! | T52: =S33/S79 -> #N/A
C53: Combined NOI | H53: =+H33+H51 -> 0 | N53: LTV | S53: =S74/S36 -> #DIV/0! | T53: =S79/S36 -> #N/A
C54: Combined Value | F54: Blended Cap Rate: | G54: =H53/H54 -> #DIV/0! | H54: =H52+H34 -> 0 | N54: =+IF(F220=0,"LTPP","LTC") -> LTPP | S54: =S74/H56 -> #VALUE! | T54: =S79/H56 -> #N/A
N55: DSC | S55: =S33/$S$84 -> #DIV/0! | T55: =S33/$T$84 -> #N/A
C56: =+IF(F220=0,"Purchase Price","Development Cost") -> Purchase Price | F56: =+IF(F220=0,"Ind Cap Rate:","Dev Yield:") -> Ind Cap Rate: | G56: =IFERROR(H53/H56,"-") -> - | H56: =+IF(F220=0,"",F220) | I56: =IFERROR(H56/$F$15,"N/A") -> N/A | J56: =IFERROR(I56/$G$15,"N/A") -> N/A | N56: Loan per Unit | S56: =+S39/$Q$15 -> #DIV/0! | T56: =+SUM(S39:T39)/Q15 -> #N/A
AJ57: MLI Select | AK57: MLI Select | AL57: MLI Select | AM57: MLI Market | AN57: MLI Market
C58: Loan Details | G58: Min / Max | N58: Break-Even Analysis | S58: SMF | T58: MLP | AI58: Points | AJ58: 50 | AK58: 70 | AL58: 100
C59: Residential Net Loan | I59: =+IF(I68=5,$I$226,$J$226) -> 0 | AI59: Residential Net Loan | AJ59: =ROUNDDOWN(MIN(PV((1+AJ72/2)^(1/6)-1,AJ71*12,-$H$33/12/AJ73),IF(AJ57="MLI Market",0.85*$H$34,IF(AND($F$207="New Construction",$F$220<>0),0.95*$F$220, IF(AJ58<=50, 0.85*$H$34, 0.95*$H$34)))),-4) -> #N/A | AK59: =ROUNDDOWN(MIN(PV((1+AK72/2)^(1/6)-1,AK71*12,-$H$33/12/AK73),IF(AK57="MLI Market",0.85*$H$34,IF(AND($F$207="New Construction",$F$220<>0),0.95*$F$220, IF(AK58<=50, 0.85*$H$34, 0.95*$H$34)))),-4) -> #N/A | AL59: =ROUNDDOWN(MIN(PV((1+AL72/2)^(1/6)-1,AL71*12,-$H$33/12/AL73),IF(AL57="MLI Market",0.85*$H$34,IF(AND($F$207="New Construction",$F$220<>0),0.95*$F$220, IF(AL58<=50, 0.85*$H$34, 0.95*$H$34)))),-4) -> #N/A | AM59: =ROUNDDOWN(MIN(PV((1+AM72/2)^(1/6)-1,AM71*12,-$H$33/12/AM73),IF(AM57="MLI Market",0.85*$H$34,IF(AND($F$207="New Construction",$F$220<>0),0.95*$F$220, IF(AM58<=50, 0.85*$H$34, 0.95*$H$34)))),-4) -> #N/A | AN59: =ROUNDDOWN(MIN(PV((1+AN72/2)^(1/6)-1,AN71*12,-$H$33/12/AN73),IF(AN57="MLI Market",0.85*$H$34,IF(AND($F$207="New Construction",$F$220<>0),0.95*$F$220, IF(AN58<=50, 0.85*$H$34, 0.95*$H$34)))),-4) -> #N/A
C60: Commercial Net Loan | I60: =+IF(I68=5,$I$231,$J$231) -> 0 | AI60: Commercial Net Loan | AJ60: =ROUNDDOWN(IFERROR(MIN(PV((1+AJ72/2)^(1/6)-1,AJ71*12,-$H$51/12/AJ74),IF(AND($F$200="Construction Financing",$F$207="New Construction"),30%*$H$54,0.75*$H$52),IF($I$71="",9999999999,IF($H$52=0,9999999999,IF($F$220=0,9999999999,IF(OR($F$200="Construction Financing",AND($F$200="All Other Loan Purposes",$F$207="New Construction")),0.75*$F$220*$I$124,999999999))))),0),-4) -> 0 | AK60: =ROUNDDOWN(IFERROR(MIN(PV((1+AK72/2)^(1/6)-1,AK71*12,-$H$51/12/AK74),IF(AND($F$200="Construction Financing",$F$207="New Construction"),30%*$H$54,0.75*$H$52),IF($I$71="",9999999999,IF($H$52=0,9999999999,IF($F$220=0,9999999999,IF(OR($F$200="Construction Financing",AND($F$200="All Other Loan Purposes",$F$207="New Construction")),0.75*$F$220*$I$124,999999999))))),0),-4) -> 0 | AL60: =ROUNDDOWN(IFERROR(MIN(PV((1+AL72/2)^(1/6)-1,AL71*12,-$H$51/12/AL74),IF(AND($F$200="Construction Financing",$F$207="New Construction"),30%*$H$54,0.75*$H$52),IF($I$71="",9999999999,IF($H$52=0,9999999999,IF($F$220=0,9999999999,IF(OR($F$200="Construction Financing",AND($F$200="All Other Loan Purposes",$F$207="New Construction")),0.75*$F$220*$I$124,999999999))))),0),-4) -> 0 | AM60: =ROUNDDOWN(IFERROR(MIN(PV((1+AM72/2)^(1/6)-1,AM71*12,-$H$51/12/AM74),IF(AND($F$200="Construction Financing",$F$207="New Construction"),30%*$H$54,0.75*$H$52),IF($I$71="",9999999999,IF($H$52=0,9999999999,IF($F$220=0,9999999999,IF(OR($F$200="Construction Financing",AND($F$200="All Other Loan Purposes",$F$207="New Construction")),0.75*$F$220*$I$124,999999999))))),0),-4) -> 0 | AN60: =ROUNDDOWN(IFERROR(MIN(PV((1+AN72/2)^(1/6)-1,AN71*12,-$H$51/12/AN74),IF(AND($F$200="Construction Financing",$F$207="New Construction"),30%*$H$54,0.75*$H$52),IF($I$71="",9999999999,IF($H$52=0,9999999999,IF($F$220=0,9999999999,IF(OR($F$200="Construction Financing",AND($F$200="All Other Loan Purposes",$F$207="New Construction")),0.75*$F$220*$I$124,999999999))))),0),-4) -> 0
C61: Net Loan | I61: =+SUM(I59:I60) -> 0 | N61: Vacancy | S61: =1-(R34*S74+S32)/S21 -> #DIV/0! | T61: =1-(R34*S79+S32)/S21 -> #N/A | AI61: Total Net Loan | AJ61: =+IFERROR(SUM(AJ59:AJ60),AJ59) -> #N/A | AK61: =+IFERROR(SUM(AK59:AK60),AK59) -> #N/A | AL61: =+IFERROR(SUM(AL59:AL60),AL59) -> #N/A | AM61: =+IFERROR(SUM(AM59:AM60),AM59) -> #N/A | AN61: =+IFERROR(SUM(AN59:AN60),AN59) -> #N/A
C62: Premium | I62: =+I250*0 +IF(F208="Effective July 14, 2025", I250,I272) -> #N/A | N62: Rent Per Unit | S62: =((S74*R34+S32)/(1-R22)-SUM(S16:S18))/Q15/12 -> #DIV/0! | T62: =((S79*R34+S32)/(1-R22)-SUM(S16:S18))/Q15/12 -> #N/A | AI62: Premium Discount | AJ62: 0.1 | AK62: 0.2 | AL62: 0.3
C63: Application Fee | I63: =+I257 -> 0 | N63: Rent PSF | S63: =S62/$R$15 -> #DIV/0! | T63: =T62/$R$15 -> #N/A | AI63: Total Premium % | AJ63: =(INDEX('Premium&DSCBackEndNEW'!$L$6:$L$68,MATCH("X",'Premium&DSCBackEndNEW'!$G$6:$G$68,0)) +IF($F$200="Construction Financing",0,IF($F$205="Yes",0,0.0025)) +IF(AJ71<25,0,ROUNDUP((AJ71-25),1)/5*0.0025) +IF($I$155=0,(AJ60*1%)/AJ61,(AJ60*1%)/SUM($H$158,$I$155)) +IF($I$155=0,($H$158*0.5%)/AJ61,($H$158*0.5%)/SUM($H$158,$I$155)))*(1-AJ62) +$AJ$246/AJ61 -> #N/A | AK63: =(INDEX('Premium&DSCBackEndNEW'!$L$6:$L$68,MATCH("X",'Premium&DSCBackEndNEW'!$H$6:$H$68,0)) +IF($F$200="Construction Financing",0,IF($F$205="Yes",0,0.0025)) +IF(AK71<25,0,ROUNDUP((AK71-25),1)/5*0.0025) +IF($I$155=0,(AK60*1%)/AK61,(AK60*1%)/SUM($H$158,$I$155)) +IF($I$155=0,($H$158*0.5%)/AK61,($H$158*0.5%)/SUM($H$158,$I$155)))*(1-AK62) +$AJ$246/AK61 -> #N/A | AL63: =(INDEX('Premium&DSCBackEndNEW'!$L$6:$L$68,MATCH("X",'Premium&DSCBackEndNEW'!$I$6:$I$68,0)) +IF($F$200="Construction Financing",0,IF($F$205="Yes",0,0.0025)) +IF(AL71<25,0,ROUNDUP((AL71-25),1)/5*0.0025) +IF($I$155=0,(AL60*1%)/AL61,(AL60*1%)/SUM($H$158,$I$155)) +IF($I$155=0,($H$158*0.5%)/AL61,($H$158*0.5%)/SUM($H$158,$I$155)))*(1-AL62) +$AJ$246/AL61 -> #N/A | AM63: =INDEX('Premium&DSCBackEndNEW'!$L$6:$L$68,MATCH("X",'Premium&DSCBackEndNEW'!$J$6:$J$68,0))+IF($F$200="Construction Financing",0,IF($F$205="Yes",0,0.0025))+IF(AM71<25,0,ROUNDUP((AM71-25),1)/5*0.0025)+IF($I$155=0,(AM60*1%)/AM61,(AM60*1%)/SUM($H$158,$I$155))+IF($I$155=0,($H$158*0.5%)/AM61,($H$158*0.5%)/SUM($H$158,$I$155))+$AJ$246/AM61 -> #N/A | AN63: =INDEX('Premium&DSCBackEndNEW'!$L$6:$L$68,MATCH("X",'Premium&DSCBackEndNEW'!$K$6:$K$68,0))+IF($F$200="Construction Financing",0,IF($F$205="Yes",0,0.0025))+IF(AN71<25,0,ROUNDUP((AN71-25),1)/5*0.0025)+IF($I$155=0,(AN60*1%)/AN61,(AN60*1%)/SUM($H$158,$I$155))+IF($I$155=0,($H$158*0.5%)/AN61,($H$158*0.5%)/SUM($H$158,$I$155))+$AJ$246/AN61 -> #N/A
C64: Gross Loan | I64: =+SUM(I61:I63) -> #N/A | L64: =IFERROR(+IF(+Economics!H54-Economics!I64<250000,"<Discuss with Antoni and Brian if below $250k",""),"") | AI64: App Fee | AJ64: =$I$257 -> 0 | AK64: =$I$257 -> 0 | AL64: =$I$257 -> 0 | AM64: =$I$257 -> 0 | AN64: =$I$257 -> 0
B65: Construction | C65: Term
C66: Lender Fee | J66: =I66*I64 -> #N/A
C67: Rate | H67: =+"Prime Rate ("&TEXT(AI45,"0.000%")&") - "&TEXT(AI45-I67,"0.000%") -> Prime Rate (4.950%) - 4.950%
B68: Term | C68: Term | N68: =_xlfn.CONCAT("Leverage (@",S99*100,"%/",T99*100,"%)") -> Leverage (@7.5%/7.75%) | S68: SMF | T68: MLP | AI68: Premium | AJ68: =AJ63*AJ61 -> #N/A | AK68: =AK63*AK61 -> #N/A | AL68: =AL63*AL61 -> #N/A | AM68: =AM63*AM61 -> #N/A | AN68: =AN63*AN61 -> #N/A
C69: Amortization | G69: =IF(AND(F204="MLI Market",F207="Existing Property"),40, IF(AND(F204="MLI Market",F207="New Construction"),50, IF(AND(F204="MLI Select",SUM(F217:F219)<70),40, IF(AND(F204="MLI Select",SUM(F217:F219)<100),45, 50)))) -> 50 | N69: IRR Levered 0% | S69: =(1+RATE(S44,S47/12*S74,-(S74-(S46*S74)),S74))^12-1 -> #NUM! | T69: =(1+RATE(T44,T47/12*S75,-(S75-(T46*S75)),S75))^12-1 -> #N/A | AI69: Total Gross Loan | AJ69: =AJ68+AJ64+AJ61 -> #N/A | AK69: =AK68+AK64+AK61 -> #N/A | AL69: =AL68+AL64+AL61 -> #N/A | AM69: =AM68+AM64+AM61 -> #N/A | AN69: =AN68+AN64+AN61 -> #N/A
C70: Lender Fee | J70: =I70*I64 -> #N/A | N70: IRR Levered 50% | S70: =(1+RATE(S44,(S74*S47/12)-(50%*S74*S99/12),-((1-50%)*S74-(S46*S74)),S74-((S74*50%))))^12-1 -> #NUM! | T70: =(1+RATE(T44,(S75*T47/12)-(50%*S75*T99/12),-((1-50%)*S75-(T46*S75)),S75-((S75*50%))))^12-1 -> #N/A | AI70: Term | AJ70: 5 | AK70: 5 | AL70: 5 | AM70: 5 | AN70: 10
C71: CMHC Max Rate (per COI) | N71: IRR Levered 60% | S71: =(1+RATE(S44,(S74*S47/12)-(60%*S74*S99/12),-((1-60%)*S74-(S46*S74)),S74-((S74*60%))))^12-1 -> #NUM! | T71: =(1+RATE(T44,(S75*T47/12)-(60%*S75*T99/12),-((1-60%)*S75-(T46*S75)),S75-((S75*60%))))^12-1 -> #N/A | AI71: Amortization | AJ71: 40 | AK71: 45 | AL71: 50 | AM71: 30 | AN71: 30
C72: 5Y Indicative Rate & Est. Buydown | H72: =IFERROR(CONCATENATE("CMB (",TEXT($I$236,"0.000%"),") + ",TEXT($I$237,"0.000%")),"ERROR") -> CMB (3.310%) + 0.000% | I72: =+$I$239 -> 0.0331 | J72: =+'Buydown Calc'!$C$6 -> #N/A | AI72: Max Rate | AJ72: =+$I$71 -> 0 | AK72: =+$I$71 -> 0 | AL72: =+$I$71 -> 0 | AM72: =+$I$71 -> 0 | AN72: =+$I$71 -> 0
C73: 10Y Indicative Rate & Est. Buydown | H73: =IFERROR(CONCATENATE("CMB (",TEXT($J$236,"0.000%"),") + ",TEXT($J$237,"0.000%")),"ERROR") -> CMB (3.740%) + 0.000% | I73: =+$J$239 -> 0.0374 | J73: =+'Buydown Calc'!$C$7 -> #N/A | N73: Capital Stack | S73: Total | T73: Per Unit | AI73: Residential DSC | AJ73: =IF(AJ70=5,VLOOKUP($F$203&AJ$57&$F$211,'Premium&DSCBackEndNEW'!$B$74:$I$84,5,0),IF(AJ70=10,VLOOKUP($F$203&AJ$57&$F$211,'Premium&DSCBackEndNEW'!$B$74:$I$84,6,0),"ERROR")) -> #N/A | AK73: =IF(AK70=5,VLOOKUP($F$203&AK$57&$F$211,'Premium&DSCBackEndNEW'!$B$74:$I$84,5,0),IF(AK70=10,VLOOKUP($F$203&AK$57&$F$211,'Premium&DSCBackEndNEW'!$B$74:$I$84,6,0),"ERROR")) -> #N/A | AL73: =IF(AL70=5,VLOOKUP($F$203&AL$57&$F$211,'Premium&DSCBackEndNEW'!$B$74:$I$84,5,0),IF(AL70=10,VLOOKUP($F$203&AL$57&$F$211,'Premium&DSCBackEndNEW'!$B$74:$I$84,6,0),"ERROR")) -> #N/A | AM73: =IF(AM70=5,VLOOKUP($F$203&AM$57&$F$211,'Premium&DSCBackEndNEW'!$B$74:$I$84,5,0),IF(AM70=10,VLOOKUP($F$203&AM$57&$F$211,'Premium&DSCBackEndNEW'!$B$74:$I$84,6,0),"ERROR")) -> #N/A | AN73: =IF(AN70=5,VLOOKUP($F$203&AN$57&$F$211,'Premium&DSCBackEndNEW'!$B$74:$I$84,5,0),IF(AN70=10,VLOOKUP($F$203&AN$57&$F$211,'Premium&DSCBackEndNEW'!$B$74:$I$84,6,0),"ERROR")) -> #N/A
N74: SMF | Q74: =S74/$S$81 -> #DIV/0! | S74: =+S39 -> 0 | T74: =S74/$Q$15 -> #DIV/0! | AI74: Commercial DSC | AJ74: =IF(AJ70=5,VLOOKUP($F$203&AJ$57&$F$211,'Premium&DSCBackEndNEW'!$B$74:$I$84,7,0),IF(AJ70=10,VLOOKUP($F$203&AJ$57&$F$211,'Premium&DSCBackEndNEW'!$B$74:$I$84,8,0),"ERROR")) -> #N/A | AK74: =IF(AK70=5,VLOOKUP($F$203&AK$57&$F$211,'Premium&DSCBackEndNEW'!$B$74:$I$84,7,0),IF(AK70=10,VLOOKUP($F$203&AK$57&$F$211,'Premium&DSCBackEndNEW'!$B$74:$I$84,8,0),"ERROR")) -> #N/A | AL74: =IF(AL70=5,VLOOKUP($F$203&AL$57&$F$211,'Premium&DSCBackEndNEW'!$B$74:$I$84,7,0),IF(AL70=10,VLOOKUP($F$203&AL$57&$F$211,'Premium&DSCBackEndNEW'!$B$74:$I$84,8,0),"ERROR")) -> #N/A | AM74: =IF(AM70=5,VLOOKUP($F$203&AM$57&$F$211,'Premium&DSCBackEndNEW'!$B$74:$I$84,7,0),IF(AM70=10,VLOOKUP($F$203&AM$57&$F$211,'Premium&DSCBackEndNEW'!$B$74:$I$84,8,0),"ERROR")) -> #N/A | AN74: =IF(AN70=5,VLOOKUP($F$203&AN$57&$F$211,'Premium&DSCBackEndNEW'!$B$74:$I$84,7,0),IF(AN70=10,VLOOKUP($F$203&AN$57&$F$211,'Premium&DSCBackEndNEW'!$B$74:$I$84,8,0),"ERROR")) -> #N/A
C75: Key Metrics | G75: Min / Max | H75: Net | I75: Gross | N75: MLP | Q75: =S75/$S$81 -> #N/A | S75: =S79-S74 -> #N/A | T75: =S75/$Q$15 -> #N/A | AI75: Net LTV | AJ75: =IFERROR(AJ61/$H$54,AJ61/$H$34) -> #N/A | AK75: =IFERROR(AK61/$H$54,AK61/$H$34) -> #N/A | AL75: =IFERROR(AL61/$H$54,AL61/$H$34) -> #N/A | AM75: =IFERROR(AM61/$H$54,AM61/$H$34) -> #N/A | AN75: =IFERROR(AN61/$H$54,AN61/$H$34) -> #N/A
C76: Profit | I76: =+IFERROR($H$54-H118,$H$34-H118) -> 0
C77: Profit % of Costs | I77: =+I76/H118 -> #DIV/0!
C78: Development Yield | I78: =+IFERROR(H53/H118,H33/H118) -> #DIV/0!
C79: NOI/Debt | I79: =$H$53/I64 -> #N/A | N79: Total Debt Stack | Q79: =S79/$S$81 -> #N/A | S79: =+I64 -> #N/A | T79: =S79/$Q$15 -> #N/A | AI79: Recourse | AJ79: =IF(AJ58=100,"No","Yes") -> Yes | AK79: =IF(AK58=100,"No","Yes") -> Yes | AL79: =IF(AL58=100,"No","Yes") -> No | AM79: =IF(AM75<0.65000000001,"No","Yes") -> #N/A | AN79: =IF(AN75<0.65000000001,"No","Yes") -> #N/A
C80: LTV | G80: =+IF(F204="MLI Market",0.85,IF(AND(F204="MLI Select",F207="Existing Property",SUM(Economics!F217:F219)<51),0.85,IF(AND(F204="MLI Select",F207="Existing Property",SUM(Economics!F217:F219)>69),0.95,""))) | H80: =IFERROR(I61/$H$54,I61/$H$34) -> #DIV/0! | I80: =+IFERROR(I64/$H$54,I64/$H$34) -> #N/A | L80: =+IF(H80>VALUE(RIGHT(D224,3)),"add details for aggregators when sending OTP","") -> #DIV/0! | N80: Equity | Q80: =S80/$S$81 -> #DIV/0! | S80: =S81-S79 -> #DIV/0! | T80: =S80/$Q$15 -> #DIV/0! | AI80: Total Gross Annual Debt Service | AJ80: =(PMT((1+AJ72/2)^(1/6)-1,AJ71*12,-AJ69)*12) -> #N/A | AK80: =(PMT((1+AK72/2)^(1/6)-1,AK71*12,-AK69)*12) -> #N/A | AL80: =(PMT((1+AL72/2)^(1/6)-1,AL71*12,-AL69)*12) -> #N/A | AM80: =(PMT((1+AM72/2)^(1/6)-1,AM71*12,-AM69)*12) -> #N/A | AN80: =(PMT((1+AN72/2)^(1/6)-1,AN71*12,-AN69)*12) -> #N/A
C81: =+IF(F220=0,"LTPP","LTC") -> LTPP | G81: =+IF(H118=0,0.85,IF(AND(F204="MLI Select",F207="New Construction"),0.95,IF(OR(F200="Construction Financing",AND(F204="MLI Market",F207="New Construction")),1,""))) -> 0.85 | H81: =I61/H56 -> #VALUE! | I81: =I64/H56 -> #N/A | N81: Total Source of Funds | Q81: =SUM(Q76:Q80) -> #N/A | S81: =S36 -> #DIV/0! | T81: =S81/$Q$15 -> #DIV/0!
C82: 5Y DSC (Indicative Rate) | G82: =+IFERROR(VLOOKUP($F$203&$F$204&$F$211,'Premium&DSCBackEndNEW'!$B$74:$G$84,5,0),"") | H82: =$H$53/(PMT((1+$I$72/2)^(1/6)-1,$I$69*12,-$I$61)*12) -> #NUM! | I82: =$H$53/(PMT((1+$I$72/2)^(1/6)-1,$I$69*12,-$I$64)*12) -> #N/A
C83: 10Y DSC (Indicative Rate) | G83: =+IFERROR(VLOOKUP($F$203&$F$204&$F$211,'Premium&DSCBackEndNEW'!$B$74:$G$84,6,0),"") | H83: =$H$53/(PMT((1+$I$73/2)^(1/6)-1,$I$69*12,-$I$61)*12) -> #NUM! | I83: =$H$53/(PMT((1+$I$73/2)^(1/6)-1,$I$69*12,-$I$64)*12) -> #N/A | N83: Other (NO NEED TO INCLUDE THIS TABLE IN CCS) | S83: SMF | T83: MLP | U83: Blended
C84: DSC (Max Rate Per COI) | G84: =+IF(I68=5,D223,IF(I68=10,E223,"")) | H84: =$H$53/(PMT((1+$I$71/2)^(1/6)-1,$I$69*12,-$I$61)*12) -> #NUM! | I84: =$H$53/(PMT((1+$I$71/2)^(1/6)-1,$I$69*12,-$I$64)*12) -> #N/A | L84: =+IF(OR(AND(I68=5,H84<D223),AND(I68=10,H84<E223)),"add details for aggregators when sending OTP","") -> #NUM! | N84: Debt Service | S84: =S47*S74 -> 0 | T84: =T47*S75+S84 -> #N/A | U84: =+SUM(S84:T84) -> #N/A
C85: Loan Per Unit | I85: =I64/$F$15 -> #N/A | N85: Utilization
N86: Interest | S86: =S44/12*S85*S84 -> 0 | T86: =T44/12*T85*T84 -> #N/A | U86: =+SUM(S86:T86) -> #N/A
C87: Residential Key Metrics | H87: Net
C88: LTV | H88: =+I59/H34 -> #DIV/0!
C89: 5Y DSC (Indicative Rate) | H89: =$H$33/(PMT((1+$I72/2)^(1/6)-1,$I$69*12,-$I$59)*12) -> #NUM! | I89: DON'T INCLUDE THIS SECTION IN CCS
C90: 10Y DSC (Indicative Rate) | H90: =$H$33/(PMT((1+$I73/2)^(1/6)-1,$I$69*12,-$I$59)*12) -> #NUM!
C91: DSC (Max Rate Per COI) | H91: =$H$33/(PMT((1+$I71/2)^(1/6)-1,$I$69*12,-$I$59)*12) -> #NUM!
C93: Commercial Key Metrics | H93: Net
C94: LTV | H94: =+I60/H52 -> #DIV/0!
C95: 5Y DSC (Indicative Rate) | H95: =$H$51/(PMT((1+$I72/2)^(1/6)-1,$I$69*12,-$I$60)*12) -> #NUM! | I95: DON'T INCLUDE THIS SECTION IN CCS
C96: 10Y DSC (Indicative Rate) | H96: =$H$51/(PMT((1+$I73/2)^(1/6)-1,$I$69*12,-$I$60)*12) -> #NUM!
C97: DSC (Max Rate Per COI) | H97: =$H$51/(PMT((1+$I71/2)^(1/6)-1,$I$69*12,-$I$60)*12) -> #NUM!
B99: Term | C99: Sources | H99: Uses | N99: KS Cost of Leverage | S99: 0.075 | T99: 0.0775
C100: Net Loan | D100: =+I61 -> 0
D101: =+IF(I100>D100,I100-D100,"") | I101: =+IF(D100>I100,D100-I100,"")
C102: Total | D102: =SUM(D100:E101) -> 0 | H102: Total | I102: =SUM(I100:I101) -> 0
AI103: Testing, please ignore
...

Sheet Buydown Calc
C2: Loan | D2: =+IF(Economics!I155=0,Economics!I64,Economics!I158) -> #N/A
C3: Max Rate | D3: =+IF(Economics!I165="",Economics!I71,Economics!I165) -> 0
C5: Buydown | D5: Duration | E5: Loan Rate | F5: PMT | H5: Month | I5: 1 | J5: =I5+1 -> 2 | K5: =J5+1 -> 3 | L5: =K5+1 -> 4 | M5: =L5+1 -> 5 | N5: =M5+1 -> 6 | O5: =N5+1 -> 7 | P5: =O5+1 -> 8 | Q5: =P5+1 -> 9 | ... EJ5: =EI5+1 -> 132
B6: 5yr | C6: =+IF(E6>$D$3,D6*(E6-$D$3)*$D$2,0) -> #N/A | D6: =IFERROR((NPV(((1+(E6-0.01%)/2)^(2/12)-1),$I20:$EJ20)-NPV(((1+(E6+0.01%)/2)^(2/12)-1),$I20:$EJ20))/2,"") -> 0 | E6: =+Economics!I239 -> 0.0331 | F6: =IFERROR(-PMT((1+E6/2)^(2/12)-1,Economics!$I$160* 12, 10000),-PMT((1+E6/2)^(2/12)-1,Economics!$I$69* 12, 10000)) -> #NUM!
B7: 10yr | C7: =+IF(E7>$D$3,D7*(E7-$D$3)*$D$2,0) -> #N/A | D7: =IFERROR((NPV(((1+(E7-0.01%)/2)^(2/12)-1),$I21:$EJ21)-NPV(((1+(E7+0.01%)/2)^(2/12)-1),$I21:$EJ21))/2,"") -> 0 | E7: =+Economics!J239 -> 0.0374 | F7: =IFERROR(-PMT((1+E7/2)^(2/12)-1,Economics!$I$160* 12, 10000),-PMT((1+E7/2)^(2/12)-1,Economics!$I$69* 12, 10000)) -> #NUM! | H7: Balance
H8: 5yr | I8: =IF(I$5=1,10000,H8-H16) -> 10000 | J8: =IF(J$5=1,10000,I8-I16) -> #NUM! | K8: =IF(K$5=1,10000,J8-J16) -> #NUM! | L8: =IF(L$5=1,10000,K8-K16) -> #NUM! | M8: =IF(M$5=1,10000,L8-L16) -> #NUM! | N8: =IF(N$5=1,10000,M8-M16) -> #NUM! | O8: =IF(O$5=1,10000,N8-N16) -> #NUM! | P8: =IF(P$5=1,10000,O8-O16) -> #NUM! | ... EJ8: =IF(EJ$5=1,10000,EI8-EI16) -> #NUM!
H9: 10yr | I9: =IF(I$5=1,10000,H9-H17) -> 10000 | J9: =IF(J$5=1,10000,I9-I17) -> #NUM! | K9: =IF(K$5=1,10000,J9-J17) -> #NUM! | L9: =IF(L$5=1,10000,K9-K17) -> #NUM! | M9: =IF(M$5=1,10000,L9-L17) -> #NUM! | N9: =IF(N$5=1,10000,M9-M17) -> #NUM! | O9: =IF(O$5=1,10000,N9-N17) -> #NUM! | P9: =IF(P$5=1,10000,O9-O17) -> #NUM! | ... EJ9: =IF(EJ$5=1,10000,EI9-EI17) -> #NUM!
H11: Interest
H12: 5yr | I12: =IFERROR(ROUND(((1+$E6/2)^(2/12)-1)*I8,2),"") -> 27.4 | J12: =IFERROR(ROUND(((1+$E6/2)^(2/12)-1)*J8,2),"") | K12: =IFERROR(ROUND(((1+$E6/2)^(2/12)-1)*K8,2),"") | L12: =IFERROR(ROUND(((1+$E6/2)^(2/12)-1)*L8,2),"") | M12: =IFERROR(ROUND(((1+$E6/2)^(2/12)-1)*M8,2),"") | N12: =IFERROR(ROUND(((1+$E6/2)^(2/12)-1)*N8,2),"") | O12: =IFERROR(ROUND(((1+$E6/2)^(2/12)-1)*O8,2),"") | P12: =IFERROR(ROUND(((1+$E6/2)^(2/12)-1)*P8,2),"") | ... EJ12: =IFERROR(ROUND(((1+$E6/2)^(2/12)-1)*EJ8,2),"")
H13: 10yr | I13: =IFERROR(ROUND(((1+$E7/2)^(2/12)-1)*I9,2),"") -> 30.93 | J13: =IFERROR(ROUND(((1+$E7/2)^(2/12)-1)*J9,2),"") | K13: =IFERROR(ROUND(((1+$E7/2)^(2/12)-1)*K9,2),"") | L13: =IFERROR(ROUND(((1+$E7/2)^(2/12)-1)*L9,2),"") | M13: =IFERROR(ROUND(((1+$E7/2)^(2/12)-1)*M9,2),"") | N13: =IFERROR(ROUND(((1+$E7/2)^(2/12)-1)*N9,2),"") | O13: =IFERROR(ROUND(((1+$E7/2)^(2/12)-1)*O9,2),"") | P13: =IFERROR(ROUND(((1+$E7/2)^(2/12)-1)*P9,2),"") | ... EJ13: =IFERROR(ROUND(((1+$E7/2)^(2/12)-1)*EJ9,2),"")
H15: Principal
H16: 5yr | I16: =IF(I$5<5*12,$F6-I12,IF(I$5=5*12,I8,0)) -> #NUM! | J16: =IF(J$5<5*12,$F6-J12,IF(J$5=5*12,J8,0)) -> #NUM! | K16: =IF(K$5<5*12,$F6-K12,IF(K$5=5*12,K8,0)) -> #NUM! | L16: =IF(L$5<5*12,$F6-L12,IF(L$5=5*12,L8,0)) -> #NUM! | M16: =IF(M$5<5*12,$F6-M12,IF(M$5=5*12,M8,0)) -> #NUM! | N16: =IF(N$5<5*12,$F6-N12,IF(N$5=5*12,N8,0)) -> #NUM! | O16: =IF(O$5<5*12,$F6-O12,IF(O$5=5*12,O8,0)) -> #NUM! | P16: =IF(P$5<5*12,$F6-P12,IF(P$5=5*12,P8,0)) -> #NUM! | ... EJ16: =IF(EJ$5<5*12,$F6-EJ12,IF(EJ$5=5*12,EJ8,0)) -> 0
H17: 10yr | I17: =IF(I$5<10*12,$F7-I13,IF(I$5=10*12,I9,0)) -> #NUM! | J17: =IF(J$5<10*12,$F7-J13,IF(J$5=10*12,J9,0)) -> #NUM! | K17: =IF(K$5<10*12,$F7-K13,IF(K$5=10*12,K9,0)) -> #NUM! | L17: =IF(L$5<10*12,$F7-L13,IF(L$5=10*12,L9,0)) -> #NUM! | M17: =IF(M$5<10*12,$F7-M13,IF(M$5=10*12,M9,0)) -> #NUM! | N17: =IF(N$5<10*12,$F7-N13,IF(N$5=10*12,N9,0)) -> #NUM! | O17: =IF(O$5<10*12,$F7-O13,IF(O$5=10*12,O9,0)) -> #NUM! | P17: =IF(P$5<10*12,$F7-P13,IF(P$5=10*12,P9,0)) -> #NUM! | ... EJ17: =IF(EJ$5<10*12,$F7-EJ13,IF(EJ$5=10*12,EJ9,0)) -> 0
H19: Total CF
H20: 5yr | I20: =IFERROR(I16+I12,"") | J20: =IFERROR(J16+J12,"") | K20: =IFERROR(K16+K12,"") | L20: =IFERROR(L16+L12,"") | M20: =IFERROR(M16+M12,"") | N20: =IFERROR(N16+N12,"") | O20: =IFERROR(O16+O12,"") | P20: =IFERROR(P16+P12,"") | ... EJ20: =IFERROR(EJ16+EJ12,"")
H21: 10yr | I21: =IFERROR(I17+I13,"") | J21: =IFERROR(J17+J13,"") | K21: =IFERROR(K17+K13,"") | L21: =IFERROR(L17+L13,"") | M21: =IFERROR(M17+M13,"") | N21: =IFERROR(N17+N13,"") | O21: =IFERROR(O17+O13,"") | P21: =IFERROR(P17+P13,"") | ... EJ21: =IFERROR(EJ17+EJ13,"")

Sheet ControlBackEnd
C2: <Region> | G2: Min Loan | H2: Servicing
C3: ON | G3: 0 | H3: =10*1.13 -> 11.3
C4: BC | G4: 2000000 | H4: =7*1.13 -> 7.91
C5: QC | G5: 5000000 | H5: =5*1.13 -> 5.65
C6: Atlantic | G6: 25000000 | H6: =4*1.13 -> 4.52
C7: Prairies & Territories | G7: 35000000 | H7: =3*1.13 -> 3.39
G8: 100000000 | H8: =2*1.13 -> 2.26
C9: <Housing Type>
C10: Standard Rental Housing
C11: Student
C12: SRO
C13: Retirement
C15: <Program>
C16: MLI Market
C17: MLI Select
C19: <EGI Test Met>
C20: Yes
C21: No
C23: <Select Frame>
... C91: <Term>
C92: 5
C93: 10
C95: <Premium Used>
C96: Pre-July 14, 2025
C97: Effective July 14, 2025

Sheet PremiumBackEnd
I1: Select vs Market Scenarios | L1: Select vs Market Scenarios | T1: Premium Credit
A2: Housing Type | B2: Program | C2: EGI Met | D2: Min LTV | E2: Max LTV | F2: Indicator | G2: Premium | I2: 5yr Market | L2: 10yr Market | P2: Increase | Q2: Pre June 19, 2023 Premiums | T2: Years since Previous Transaction | U2: Credit (% of Original Premium)
A3: Standard Rental Housing | B3: MLI Market | C3: Yes | D3: 0 | E3: 0.65 | F3: =IF(AND(Economics!$F$203=PremiumBackEnd!A3,Economics!$F$204=PremiumBackEnd!B3,Economics!$F$205=C3,$B$70<=PremiumBackEnd!E3,$B$70>=PremiumBackEnd!D3),"X","") -> #DIV/0! | G3: 0.026 | I3: =IF(AND(Economics!$F$203=PremiumBackEnd!A3,Economics!$AU$57=PremiumBackEnd!B3,Economics!$F$205=C3,Economics!$AU$74<=E3,Economics!$AU$74>=D3),"X","") | J3: =+PremiumBackEnd!G3 -> 0.026 | L3: =IF(AND(Economics!$F$203=PremiumBackEnd!A3,Economics!$AV$57=PremiumBackEnd!B3,Economics!$F$205=PremiumBackEnd!C3,Economics!$AV$74<=PremiumBackEnd!E3,Economics!$AV$74>=PremiumBackEnd!D3),"X","") | M3: =+PremiumBackEnd!G3 -> 0.026 | P3: =+G3-Q3 -> 0.0085 | Q3: 0.0175 | T3: 1 | U3: 0.75
A4: Standard Rental Housing | B4: MLI Market | C4: Yes | D4: =+E3+0.00001 -> 0.65001 | E4: 0.7 | F4: =IF(AND(Economics!$F$203=PremiumBackEnd!A4,Economics!$F$204=PremiumBackEnd!B4,Economics!$F$205=C4,$B$70<=PremiumBackEnd!E4,$B$70>=PremiumBackEnd!D4),"X","") -> #DIV/0! | G4: 0.0285 | I4: =IF(AND(Economics!$F$203=PremiumBackEnd!A4,Economics!$AU$57=PremiumBackEnd!B4,Economics!$F$205=PremiumBackEnd!C4,Economics!$AU$74<=PremiumBackEnd!E4,Economics!$AU$74>=PremiumBackEnd!D4),"X","") | J4: =+PremiumBackEnd!G4 -> 0.0285 | L4: =IF(AND(Economics!$F$203=PremiumBackEnd!A4,Economics!$AV$57=PremiumBackEnd!B4,Economics!$F$205=PremiumBackEnd!C4,Economics!$AV$74<=PremiumBackEnd!E4,Economics!$AV$74>=PremiumBackEnd!D4),"X","") | M4: =+PremiumBackEnd!G4 -> 0.0285 | P4: =+G4-Q4 -> 0.0085 | Q4: 0.02 | T4: 2 | U4: 0.7
A5: Standard Rental Housing | B5: MLI Market | C5: Yes | D5: =+E4+0.00001 -> 0.70001 | E5: 0.75 | F5: =IF(AND(Economics!$F$203=PremiumBackEnd!A5,Economics!$F$204=PremiumBackEnd!B5,Economics!$F$205=C5,$B$70<=PremiumBackEnd!E5,$B$70>=PremiumBackEnd!D5),"X","") -> #DIV/0! | G5: 0.0335 | I5: =IF(AND(Economics!$F$203=PremiumBackEnd!A5,Economics!$AU$57=PremiumBackEnd!B5,Economics!$F$205=PremiumBackEnd!C5,Economics!$AU$74<=PremiumBackEnd!E5,Economics!$AU$74>=PremiumBackEnd!D5),"X","") | J5: =+PremiumBackEnd!G5 -> 0.0335 | L5: =IF(AND(Economics!$F$203=PremiumBackEnd!A5,Economics!$AV$57=PremiumBackEnd!B5,Economics!$F$205=PremiumBackEnd!C5,Economics!$AV$74<=PremiumBackEnd!E5,Economics!$AV$74>=PremiumBackEnd!D5),"X","") | M5: =+PremiumBackEnd!G5 -> 0.0335 | P5: =+G5-Q5 -> 0.0085 | Q5: 0.025 | T5: 3 | U5: 0.6
A6: Standard Rental Housing | B6: MLI Market | C6: Yes | D6: =+E5+0.00001 -> 0.75001 | E6: 0.8 | F6: =IF(AND(Economics!$F$203=PremiumBackEnd!A6,Economics!$F$204=PremiumBackEnd!B6,Economics!$F$205=C6,$B$70<=PremiumBackEnd!E6,$B$70>=PremiumBackEnd!D6),"X","") -> #DIV/0! | G6: 0.0435 | I6: =IF(AND(Economics!$F$203=PremiumBackEnd!A6,Economics!$AU$57=PremiumBackEnd!B6,Economics!$F$205=PremiumBackEnd!C6,Economics!$AU$74<=PremiumBackEnd!E6,Economics!$AU$74>=PremiumBackEnd!D6),"X","") | J6: =+PremiumBackEnd!G6 -> 0.0435 | L6: =IF(AND(Economics!$F$203=PremiumBackEnd!A6,Economics!$AV$57=PremiumBackEnd!B6,Economics!$F$205=PremiumBackEnd!C6,Economics!$AV$74<=PremiumBackEnd!E6,Economics!$AV$74>=PremiumBackEnd!D6),"X","") | M6: =+PremiumBackEnd!G6 -> 0.0435 | P6: =+G6-Q6 -> 0.0085 | Q6: 0.035 | T6: 4 | U6: 0.5
A7: Standard Rental Housing | B7: MLI Market | C7: Yes | D7: =+E6+0.00001 -> 0.80001 | E7: 0.85 | F7: =IF(AND(Economics!$F$203=PremiumBackEnd!A7,Economics!$F$204=PremiumBackEnd!B7,Economics!$F$205=C7,$B$70<=PremiumBackEnd!E7,$B$70>=PremiumBackEnd!D7),"X","") -> #DIV/0! | G7: 0.0535 | I7: =IF(AND(Economics!$F$203=PremiumBackEnd!A7,Economics!$AU$57=PremiumBackEnd!B7,Economics!$F$205=PremiumBackEnd!C7,Economics!$AU$74<=PremiumBackEnd!E7,Economics!$AU$74>=PremiumBackEnd!D7),"X","") | J7: =+PremiumBackEnd!G7 -> 0.0535 | L7: =IF(AND(Economics!$F$203=PremiumBackEnd!A7,Economics!$AV$57=PremiumBackEnd!B7,Economics!$F$205=PremiumBackEnd!C7,Economics!$AV$74<=PremiumBackEnd!E7,Economics!$AV$74>=PremiumBackEnd!D7),"X","") | M7: =+PremiumBackEnd!G7 -> 0.0535 | P7: =+G7-Q7 -> 0.0085 | Q7: 0.045 | T7: 5 | U7: 0.4
T8: 6 | U8: 0.3
A9: Student | B9: MLI Market | C9: Yes | D9: 0 | E9: 0.65 | F9: =IF(AND(Economics!$F$203=PremiumBackEnd!A9,Economics!$F$204=PremiumBackEnd!B9,Economics!$F$205=C9,$B$70<=PremiumBackEnd!E9,$B$70>=PremiumBackEnd!D9),"X","") -> #DIV/0! | G9: 0.0335 | I9: =IF(AND(Economics!$F$203=PremiumBackEnd!A9,Economics!$AU$57=PremiumBackEnd!B9,Economics!$F$205=PremiumBackEnd!C9,Economics!$AU$74<=PremiumBackEnd!E9,Economics!$AU$74>=PremiumBackEnd!D9),"X","") | J9: =+PremiumBackEnd!G9 -> 0.0335 | L9: =IF(AND(Economics!$F$203=PremiumBackEnd!A9,Economics!$AV$57=PremiumBackEnd!B9,Economics!$F$205=PremiumBackEnd!C9,Economics!$AV$74<=PremiumBackEnd!E9,Economics!$AV$74>=PremiumBackEnd!D9),"X","") | M9: =+PremiumBackEnd!G9 -> 0.0335 | P9: =+G9-Q9 -> 0.0085 | Q9: 0.025 | T9: 7 | U9: 0.2
A10: Student | B10: MLI Market | C10: Yes | D10: =+E9+0.00001 -> 0.65001 | E10: 0.7 | F10: =IF(AND(Economics!$F$203=PremiumBackEnd!A10,Economics!$F$204=PremiumBackEnd!B10,Economics!$F$205=C10,$B$70<=PremiumBackEnd!E10,$B$70>=PremiumBackEnd!D10),"X","") -> #DIV/0! | G10: 0.0385 | I10: =IF(AND(Economics!$F$203=PremiumBackEnd!A10,Economics!$AU$57=PremiumBackEnd!B10,Economics!$F$205=PremiumBackEnd!C10,Economics!$AU$74<=PremiumBackEnd!E10,Economics!$AU$74>=PremiumBackEnd!D10),"X","") | J10: =+PremiumBackEnd!G10 -> 0.0385 | L10: =IF(AND(Economics!$F$203=PremiumBackEnd!A10,Economics!$AV$57=PremiumBackEnd!B10,Economics!$F$205=PremiumBackEnd!C10,Economics!$AV$74<=PremiumBackEnd!E10,Economics!$AV$74>=PremiumBackEnd!D10),"X","") | M10: =+PremiumBackEnd!G10 -> 0.0385 | P10: =+G10-Q10 -> 0.0085 | Q10: 0.03
A11: Student | B11: MLI Market | C11: Yes | D11: =+E10+0.00001 -> 0.70001 | E11: 0.75 | F11: =IF(AND(Economics!$F$203=PremiumBackEnd!A11,Economics!$F$204=PremiumBackEnd!B11,Economics!$F$205=C11,$B$70<=PremiumBackEnd!E11,$B$70>=PremiumBackEnd!D11),"X","") -> #DIV/0! | G11: 0.0435 | I11: =IF(AND(Economics!$F$203=PremiumBackEnd!A11,Economics!$AU$57=PremiumBackEnd!B11,Economics!$F$205=PremiumBackEnd!C11,Economics!$AU$74<=PremiumBackEnd!E11,Economics!$AU$74>=PremiumBackEnd!D11),"X","") | J11: =+PremiumBackEnd!G11 -> 0.0435 | L11: =IF(AND(Economics!$F$203=PremiumBackEnd!A11,Economics!$AV$57=PremiumBackEnd!B11,Economics!$F$205=PremiumBackEnd!C11,Economics!$AV$74<=PremiumBackEnd!E11,Economics!$AV$74>=PremiumBackEnd!D11),"X","") | M11: =+PremiumBackEnd!G11 -> 0.0435 | P11: =+G11-Q11 -> 0.0085 | Q11: 0.035
A12: Student | B12: MLI Market | C12: Yes | D12: =+E11+0.00001 -> 0.75001 | E12: 0.8 | F12: =IF(AND(Economics!$F$203=PremiumBackEnd!A12,Economics!$F$204=PremiumBackEnd!B12,Economics!$F$205=C12,$B$70<=PremiumBackEnd!E12,$B$70>=PremiumBackEnd!D12),"X","") -> #DIV/0! | G12: 0.051 | I12: =IF(AND(Economics!$F$203=PremiumBackEnd!A12,Economics!$AU$57=PremiumBackEnd!B12,Economics!$F$205=PremiumBackEnd!C12,Economics!$AU$74<=PremiumBackEnd!E12,Economics!$AU$74>=PremiumBackEnd!D12),"X","") | J12: =+PremiumBackEnd!G12 -> 0.051 | L12: =IF(AND(Economics!$F$203=PremiumBackEnd!A12,Economics!$AV$57=PremiumBackEnd!B12,Economics!$F$205=PremiumBackEnd!C12,Economics!$AV$74<=PremiumBackEnd!E12,Economics!$AV$74>=PremiumBackEnd!D12),"X","") | M12: =+PremiumBackEnd!G12 -> 0.051 | P12: =+G12-Q12 -> 0.0085 | Q12: 0.0425
A13: Student | B13: MLI Market | C13: Yes | D13: =+E12+0.00001 -> 0.80001 | E13: 0.85 | F13: =IF(AND(Economics!$F$203=PremiumBackEnd!A13,Economics!$F$204=PremiumBackEnd!B13,Economics!$F$205=C13,$B$70<=PremiumBackEnd!E13,$B$70>=PremiumBackEnd!D13),"X","") -> #DIV/0! | G13: 0.061 | I13: =IF(AND(Economics!$F$203=PremiumBackEnd!A13,Economics!$AU$57=PremiumBackEnd!B13,Economics!$F$205=PremiumBackEnd!C13,Economics!$AU$74<=PremiumBackEnd!E13,Economics!$AU$74>=PremiumBackEnd!D13),"X","") | J13: =+PremiumBackEnd!G13 -> 0.061 | L13: =IF(AND(Economics!$F$203=PremiumBackEnd!A13,Economics!$AV$57=PremiumBackEnd!B13,Economics!$F$205=PremiumBackEnd!C13,Economics!$AV$74<=PremiumBackEnd!E13,Economics!$AV$74>=PremiumBackEnd!D13),"X","") | M13: =+PremiumBackEnd!G13 -> 0.061 | P13: =+G13-Q13 -> 0.0085 | Q13: 0.0525
A15: SRO | B15: MLI Market | C15: Yes | D15: 0 | E15: 0.65 | F15: =IF(AND(Economics!$F$203=PremiumBackEnd!A15,Economics!$F$204=PremiumBackEnd!B15,Economics!$F$205=C15,$B$70<=PremiumBackEnd!E15,$B$70>=PremiumBackEnd!D15),"X","") -> #DIV/0! | G15: 0.0335 | I15: =IF(AND(Economics!$F$203=PremiumBackEnd!A15,Economics!$AU$57=PremiumBackEnd!B15,Economics!$F$205=PremiumBackEnd!C15,Economics!$AU$74<=PremiumBackEnd!E15,Economics!$AU$74>=PremiumBackEnd!D15),"X","") | J15: =+PremiumBackEnd!G15 -> 0.0335 | L15: =IF(AND(Economics!$F$203=PremiumBackEnd!A15,Economics!$AV$57=PremiumBackEnd!B15,Economics!$F$205=PremiumBackEnd!C15,Economics!$AV$74<=PremiumBackEnd!E15,Economics!$AV$74>=PremiumBackEnd!D15),"X","") | M15: =+PremiumBackEnd!G15 -> 0.0335 | P15: =+G15-Q15 -> 0.0085 | Q15: 0.025
A16: SRO | B16: MLI Market | C16: Yes | D16: =+E15+0.00001 -> 0.65001 | E16: 0.7 | F16: =IF(AND(Economics!$F$203=PremiumBackEnd!A16,Economics!$F$204=PremiumBackEnd!B16,Economics!$F$205=C16,$B$70<=PremiumBackEnd!E16,$B$70>=PremiumBackEnd!D16),"X","") -> #DIV/0! | G16: 0.0385 | I16: =IF(AND(Economics!$F$203=PremiumBackEnd!A16,Economics!$AU$57=PremiumBackEnd!B16,Economics!$F$205=PremiumBackEnd!C16,Economics!$AU$74<=PremiumBackEnd!E16,Economics!$AU$74>=PremiumBackEnd!D16),"X","") | J16: =+PremiumBackEnd!G16 -> 0.0385 | L16: =IF(AND(Economics!$F$203=PremiumBackEnd!A16,Economics!$AV$57=PremiumBackEnd!B16,Economics!$F$205=PremiumBackEnd!C16,Economics!$AV$74<=PremiumBackEnd!E16,Economics!$AV$74>=PremiumBackEnd!D16),"X","") | M16: =+PremiumBackEnd!G16 -> 0.0385 | P16: =+G16-Q16 -> 0.0085 | Q16: 0.03
A17: SRO | B17: MLI Market | C17: Yes | D17: =+E16+0.00001 -> 0.70001 | E17: 0.75 | F17: =IF(AND(Economics!$F$203=PremiumBackEnd!A17,Economics!$F$204=PremiumBackEnd!B17,Economics!$F$205=C17,$B$70<=PremiumBackEnd!E17,$B$70>=PremiumBackEnd!D17),"X","") -> #DIV/0! | G17: 0.0435 | I17: =IF(AND(Economics!$F$203=PremiumBackEnd!A17,Economics!$AU$57=PremiumBackEnd!B17,Economics!$F$205=PremiumBackEnd!C17,Economics!$AU$74<=PremiumBackEnd!E17,Economics!$AU$74>=PremiumBackEnd!D17),"X","") | J17: =+PremiumBackEnd!G17 -> 0.0435 | L17: =IF(AND(Economics!$F$203=PremiumBackEnd!A17,Economics!$AV$57=PremiumBackEnd!B17,Economics!$F$205=PremiumBackEnd!C17,Economics!$AV$74<=PremiumBackEnd!E17,Economics!$AV$74>=PremiumBackEnd!D17),"X","") | M17: =+PremiumBackEnd!G17 -> 0.0435 | P17: =+G17-Q17 -> 0.0085 | Q17: 0.035
A18: SRO | B18: MLI Market | C18: Yes | D18: =+E17+0.00001 -> 0.75001 | E18: 0.8 | F18: =IF(AND(Economics!$F$203=PremiumBackEnd!A18,Economics!$F$204=PremiumBackEnd!B18,Economics!$F$205=C18,$B$70<=PremiumBackEnd!E18,$B$70>=PremiumBackEnd!D18),"X","") -> #DIV/0! | G18: 0.051 | I18: =IF(AND(Economics!$F$203=PremiumBackEnd!A18,Economics!$AU$57=PremiumBackEnd!B18,Economics!$F$205=PremiumBackEnd!C18,Economics!$AU$74<=PremiumBackEnd!E18,Economics!$AU$74>=PremiumBackEnd!D18),"X","") | J18: =+PremiumBackEnd!G18 -> 0.051 | L18: =IF(AND(Economics!$F$203=PremiumBackEnd!A18,Economics!$AV$57=PremiumBackEnd!B18,Economics!$F$205=PremiumBackEnd!C18,Economics!$AV$74<=PremiumBackEnd!E18,Economics!$AV$74>=PremiumBackEnd!D18),"X","") | M18: =+PremiumBackEnd!G18 -> 0.051 | P18: =+G18-Q18 -> 0.0085 | Q18: 0.0425
A19: SRO | B19: MLI Market | C19: Yes | D19: =+E18+0.00001 -> 0.80001 | E19: 0.85 | F19: =IF(AND(Economics!$F$203=PremiumBackEnd!A19,Economics!$F$204=PremiumBackEnd!B19,Economics!$F$205=C19,$B$70<=PremiumBackEnd!E19,$B$70>=PremiumBackEnd!D19),"X","") -> #DIV/0! | G19: 0.061 | I19: =IF(AND(Economics!$F$203=PremiumBackEnd!A19,Economics!$AU$57=PremiumBackEnd!B19,Economics!$F$205=PremiumBackEnd!C19,Economics!$AU$74<=PremiumBackEnd!E19,Economics!$AU$74>=PremiumBackEnd!D19),"X","") | J19: =+PremiumBackEnd!G19 -> 0.061 | L19: =IF(AND(Economics!$F$203=PremiumBackEnd!A19,Economics!$AV$57=PremiumBackEnd!B19,Economics!$F$205=PremiumBackEnd!C19,Economics!$AV$74<=PremiumBackEnd!E19,Economics!$AV$74>=PremiumBackEnd!D19),"X","") | M19: =+PremiumBackEnd!G19 -> 0.061 | P19: =+G19-Q19 -> 0.0085 | Q19: 0.0525
A21: Retirement | B21: MLI Market | C21: Yes | D21: 0 | E21: 0.65 | F21: =IF(AND(Economics!$F$203=PremiumBackEnd!A21,Economics!$F$204=PremiumBackEnd!B21,Economics!$F$205=C21,$B$70<=PremiumBackEnd!E21,$B$70>=PremiumBackEnd!D21),"X","") -> #DIV/0! | G21: 0.041 | I21: =IF(AND(Economics!$F$203=PremiumBackEnd!A21,Economics!$AU$57=PremiumBackEnd!B21,Economics!$F$205=PremiumBackEnd!C21,Economics!$AU$74<=PremiumBackEnd!E21,Economics!$AU$74>=PremiumBackEnd!D21),"X","") | J21: =+PremiumBackEnd!G21 -> 0.041 | L21: =IF(AND(Economics!$F$203=PremiumBackEnd!A21,Economics!$AV$57=PremiumBackEnd!B21,Economics!$F$205=PremiumBackEnd!C21,Economics!$AV$74<=PremiumBackEnd!E21,Economics!$AV$74>=PremiumBackEnd!D21),"X","") | M21: =+PremiumBackEnd!G21 -> 0.041 | P21: =+G21-Q21 -> 0.0085 | Q21: 0.0325
A22: Retirement | B22: MLI Market | C22: Yes | D22: =+E21+0.00001 -> 0.65001 | E22: 0.7 | F22: =IF(AND(Economics!$F$203=PremiumBackEnd!A22,Economics!$F$204=PremiumBackEnd!B22,Economics!$F$205=C22,$B$70<=PremiumBackEnd!E22,$B$70>=PremiumBackEnd!D22),"X","") -> #DIV/0! | G22: 0.046 | I22: =IF(AND(Economics!$F$203=PremiumBackEnd!A22,Economics!$AU$57=PremiumBackEnd!B22,Economics!$F$205=PremiumBackEnd!C22,Economics!$AU$74<=PremiumBackEnd!E22,Economics!$AU$74>=PremiumBackEnd!D22),"X","") | J22: =+PremiumBackEnd!G22 -> 0.046 | L22: =IF(AND(Economics!$F$203=PremiumBackEnd!A22,Economics!$AV$57=PremiumBackEnd!B22,Economics!$F$205=PremiumBackEnd!C22,Economics!$AV$74<=PremiumBackEnd!E22,Economics!$AV$74>=PremiumBackEnd!D22),"X","") | M22: =+PremiumBackEnd!G22 -> 0.046 | P22: =+G22-Q22 -> 0.0085 | Q22: 0.0375
A23: Retirement | B23: MLI Market | C23: Yes | D23: =+E22+0.00001 -> 0.70001 | E23: 0.75 | F23: =IF(AND(Economics!$F$203=PremiumBackEnd!A23,Economics!$F$204=PremiumBackEnd!B23,Economics!$F$205=C23,$B$70<=PremiumBackEnd!E23,$B$70>=PremiumBackEnd!D23),"X","") -> #DIV/0! | G23: 0.051 | I23: =IF(AND(Economics!$F$203=PremiumBackEnd!A23,Economics!$AU$57=PremiumBackEnd!B23,Economics!$F$205=PremiumBackEnd!C23,Economics!$AU$74<=PremiumBackEnd!E23,Economics!$AU$74>=PremiumBackEnd!D23),"X","") | J23: =+PremiumBackEnd!G23 -> 0.051 | L23: =IF(AND(Economics!$F$203=PremiumBackEnd!A23,Economics!$AV$57=PremiumBackEnd!B23,Economics!$F$205=PremiumBackEnd!C23,Economics!$AV$74<=PremiumBackEnd!E23,Economics!$AV$74>=PremiumBackEnd!D23),"X","") | M23: =+PremiumBackEnd!G23 -> 0.051 | P23: =+G23-Q23 -> 0.0085 | Q23: 0.0425
A24: Retirement | B24: MLI Market | C24: Yes | D24: =+E23+0.00001 -> 0.75001 | E24: 0.8 | F24: =IF(AND(Economics!$F$203=PremiumBackEnd!A24,Economics!$F$204=PremiumBackEnd!B24,Economics!$F$205=C24,$B$70<=PremiumBackEnd!E24,$B$70>=PremiumBackEnd!D24),"X","") -> #DIV/0! | G24: 0.0585 | I24: =IF(AND(Economics!$F$203=PremiumBackEnd!A24,Economics!$AU$57=PremiumBackEnd!B24,Economics!$F$205=PremiumBackEnd!C24,Economics!$AU$74<=PremiumBackEnd!E24,Economics!$AU$74>=PremiumBackEnd!D24),"X","") | J24: =+PremiumBackEnd!G24 -> 0.0585 | L24: =IF(AND(Economics!$F$203=PremiumBackEnd!A24,Economics!$AV$57=PremiumBackEnd!B24,Economics!$F$205=PremiumBackEnd!C24,Economics!$AV$74<=PremiumBackEnd!E24,Economics!$AV$74>=PremiumBackEnd!D24),"X","") | M24: =+PremiumBackEnd!G24 -> 0.0585 | P24: =+G24-Q24 -> 0.0085 | Q24: 0.05
A25: Retirement | B25: MLI Market | C25: Yes | D25: =+E24+0.00001 -> 0.80001 | E25: 0.85 | F25: =IF(AND(Economics!$F$203=PremiumBackEnd!A25,Economics!$F$204=PremiumBackEnd!B25,Economics!$F$205=C25,$B$70<=PremiumBackEnd!E25,$B$70>=PremiumBackEnd!D25),"X","") -> #DIV/0! | G25: 0.066 | I25: =IF(AND(Economics!$F$203=PremiumBackEnd!A25,Economics!$AU$57=PremiumBackEnd!B25,Economics!$F$205=PremiumBackEnd!C25,Economics!$AU$74<=PremiumBackEnd!E25,Economics!$AU$74>=PremiumBackEnd!D25),"X","") | J25: =+PremiumBackEnd!G25 -> 0.066 | L25: =IF(AND(Economics!$F$203=PremiumBackEnd!A25,Economics!$AV$57=PremiumBackEnd!B25,Economics!$F$205=PremiumBackEnd!C25,Economics!$AV$74<=PremiumBackEnd!E25,Economics!$AV$74>=PremiumBackEnd!D25),"X","") | M25: =+PremiumBackEnd!G25 -> 0.066 | P25: =+G25-Q25 -> 0.0085 | Q25: 0.0575
A27: Standard Rental Housing | B27: MLI Market | C27: No | D27: 0 | E27: 0.65 | F27: =IF(AND(Economics!$F$203=PremiumBackEnd!A27,Economics!$F$204=PremiumBackEnd!B27,Economics!$F$205=C27,$B$70<=PremiumBackEnd!E27,$B$70>=PremiumBackEnd!D27),"X","") -> #DIV/0! | G27: 0.0325 | I27: =IF(AND(Economics!$F$203=PremiumBackEnd!A27,Economics!$AU$57=PremiumBackEnd!B27,Economics!$F$205=PremiumBackEnd!C27,Economics!$AU$74<=PremiumBackEnd!E27,Economics!$AU$74>=PremiumBackEnd!D27),"X","") | J27: =+PremiumBackEnd!G27 -> 0.0325 | L27: =IF(AND(Economics!$F$203=PremiumBackEnd!A27,Economics!$AV$57=PremiumBackEnd!B27,Economics!$F$205=PremiumBackEnd!C27,Economics!$AV$74<=PremiumBackEnd!E27,Economics!$AV$74>=PremiumBackEnd!D27),"X","") | M27: =+PremiumBackEnd!G27 -> 0.0325 | P27: =+G27-Q27 -> 0.0075 | Q27: 0.025
A28: Standard Rental Housing | B28: MLI Market | C28: No | D28: =+E27+0.00001 -> 0.65001 | E28: 0.7 | F28: =IF(AND(Economics!$F$203=PremiumBackEnd!A28,Economics!$F$204=PremiumBackEnd!B28,Economics!$F$205=C28,$B$70<=PremiumBackEnd!E28,$B$70>=PremiumBackEnd!D28),"X","") -> #DIV/0! | G28: 0.0375 | I28: =IF(AND(Economics!$F$203=PremiumBackEnd!A28,Economics!$AU$57=PremiumBackEnd!B28,Economics!$F$205=PremiumBackEnd!C28,Economics!$AU$74<=PremiumBackEnd!E28,Economics!$AU$74>=PremiumBackEnd!D28),"X","") | J28: =+PremiumBackEnd!G28 -> 0.0375 | L28: =IF(AND(Economics!$F$203=PremiumBackEnd!A28,Economics!$AV$57=PremiumBackEnd!B28,Economics!$F$205=PremiumBackEnd!C28,Economics!$AV$74<=PremiumBackEnd!E28,Economics!$AV$74>=PremiumBackEnd!D28),"X","") | M28: =+PremiumBackEnd!G28 -> 0.0375 | P28: =+G28-Q28 -> 0.0075 | Q28: 0.03
A29: Standard Rental Housing | B29: MLI Market | C29: No | D29: =+E28+0.00001 -> 0.70001 | E29: 0.75 | F29: =IF(AND(Economics!$F$203=PremiumBackEnd!A29,Economics!$F$204=PremiumBackEnd!B29,Economics!$F$205=C29,$B$70<=PremiumBackEnd!E29,$B$70>=PremiumBackEnd!D29),"X","") -> #DIV/0! | G29: 0.0425 | I29: =IF(AND(Economics!$F$203=PremiumBackEnd!A29,Economics!$AU$57=PremiumBackEnd!B29,Economics!$F$205=PremiumBackEnd!C29,Economics!$AU$74<=PremiumBackEnd!E29,Economics!$AU$74>=PremiumBackEnd!D29),"X","") | J29: =+PremiumBackEnd!G29 -> 0.0425 | L29: =IF(AND(Economics!$F$203=PremiumBackEnd!A29,Economics!$AV$57=PremiumBackEnd!B29,Economics!$F$205=PremiumBackEnd!C29,Economics!$AV$74<=PremiumBackEnd!E29,Economics!$AV$74>=PremiumBackEnd!D29),"X","") | M29: =+PremiumBackEnd!G29 -> 0.0425 | P29: =+G29-Q29 -> 0.0075 | Q29: 0.035
A30: Standard Rental Housing | B30: MLI Market | C30: No | D30: =+E29+0.00001 -> 0.75001 | E30: 0.8 | F30: =IF(AND(Economics!$F$203=PremiumBackEnd!A30,Economics!$F$204=PremiumBackEnd!B30,Economics!$F$205=C30,$B$70<=PremiumBackEnd!E30,$B$70>=PremiumBackEnd!D30),"X","") -> #DIV/0! | G30: 0.05 | I30: =IF(AND(Economics!$F$203=PremiumBackEnd!A30,Economics!$AU$57=PremiumBackEnd!B30,Economics!$F$205=PremiumBackEnd!C30,Economics!$AU$74<=PremiumBackEnd!E30,Economics!$AU$74>=PremiumBackEnd!D30),"X","") | J30: =+PremiumBackEnd!G30 -> 0.05 | L30: =IF(AND(Economics!$F$203=PremiumBackEnd!A30,Economics!$AV$57=PremiumBackEnd!B30,Economics!$F$205=PremiumBackEnd!C30,Economics!$AV$74<=PremiumBackEnd!E30,Economics!$AV$74>=PremiumBackEnd!D30),"X","") | M30: =+PremiumBackEnd!G30 -> 0.05 | P30: =+G30-Q30 -> 0.0075 | Q30: 0.0425
A31: Standard Rental Housing | B31: MLI Market | C31: No | D31: =+E30+0.00001 -> 0.80001 | E31: 0.85 | F31: =IF(AND(Economics!$F$203=PremiumBackEnd!A31,Economics!$F$204=PremiumBackEnd!B31,Economics!$F$205=C31,$B$70<=PremiumBackEnd!E31,$B$70>=PremiumBackEnd!D31),"X","") -> #DIV/0! | G31: 0.06 | I31: =IF(AND(Economics!$F$203=PremiumBackEnd!A31,Economics!$AU$57=PremiumBackEnd!B31,Economics!$F$205=PremiumBackEnd!C31,Economics!$AU$74<=PremiumBackEnd!E31,Economics!$AU$74>=PremiumBackEnd!D31),"X","") | J31: =+PremiumBackEnd!G31 -> 0.06 | L31: =IF(AND(Economics!$F$203=PremiumBackEnd!A31,Economics!$AV$57=PremiumBackEnd!B31,Economics!$F$205=PremiumBackEnd!C31,Economics!$AV$74<=PremiumBackEnd!E31,Economics!$AV$74>=PremiumBackEnd!D31),"X","") | M31: =+PremiumBackEnd!G31 -> 0.06 | P31: =+G31-Q31 -> 0.0075 | Q31: 0.0525
A33: Student | B33: MLI Market | C33: No | D33: 0 | E33: 0.65 | F33: =IF(AND(Economics!$F$203=PremiumBackEnd!A33,Economics!$F$204=PremiumBackEnd!B33,Economics!$F$205=C33,$B$70<=PremiumBackEnd!E33,$B$70>=PremiumBackEnd!D33),"X","") -> #DIV/0! | G33: 0.04 | I33: =IF(AND(Economics!$F$203=PremiumBackEnd!A33,Economics!$AU$57=PremiumBackEnd!B33,Economics!$F$205=PremiumBackEnd!C33,Economics!$AU$74<=PremiumBackEnd!E33,Economics!$AU$74>=PremiumBackEnd!D33),"X","") | J33: =+PremiumBackEnd!G33 -> 0.04 | L33: =IF(AND(Economics!$F$203=PremiumBackEnd!A33,Economics!$AV$57=PremiumBackEnd!B33,Economics!$F$205=PremiumBackEnd!C33,Economics!$AV$74<=PremiumBackEnd!E33,Economics!$AV$74>=PremiumBackEnd!D33),"X","") | M33: =+PremiumBackEnd!G33 -> 0.04 | P33: =+G33-Q33 -> 0.0075 | Q33: 0.0325
A34: Student | B34: MLI Market | C34: No | D34: =+E33+0.00001 -> 0.65001 | E34: 0.7 | F34: =IF(AND(Economics!$F$203=PremiumBackEnd!A34,Economics!$F$204=PremiumBackEnd!B34,Economics!$F$205=C34,$B$70<=PremiumBackEnd!E34,$B$70>=PremiumBackEnd!D34),"X","") -> #DIV/0! | G34: 0.045 | I34: =IF(AND(Economics!$F$203=PremiumBackEnd!A34,Economics!$AU$57=PremiumBackEnd!B34,Economics!$F$205=PremiumBackEnd!C34,Economics!$AU$74<=PremiumBackEnd!E34,Economics!$AU$74>=PremiumBackEnd!D34),"X","") | J34: =+PremiumBackEnd!G34 -> 0.045 | L34: =IF(AND(Economics!$F$203=PremiumBackEnd!A34,Economics!$AV$57=PremiumBackEnd!B34,Economics!$F$205=PremiumBackEnd!C34,Economics!$AV$74<=PremiumBackEnd!E34,Economics!$AV$74>=PremiumBackEnd!D34),"X","") | M34: =+PremiumBackEnd!G34 -> 0.045 | P34: =+G34-Q34 -> 0.0075 | Q34: 0.0375
A35: Student | B35: MLI Market | C35: No | D35: =+E34+0.00001 -> 0.70001 | E35: 0.75 | F35: =IF(AND(Economics!$F$203=PremiumBackEnd!A35,Economics!$F$204=PremiumBackEnd!B35,Economics!$F$205=C35,$B$70<=PremiumBackEnd!E35,$B$70>=PremiumBackEnd!D35),"X","") -> #DIV/0! | G35: 0.05 | I35: =IF(AND(Economics!$F$203=PremiumBackEnd!A35,Economics!$AU$57=PremiumBackEnd!B35,Economics!$F$205=PremiumBackEnd!C35,Economics!$AU$74<=PremiumBackEnd!E35,Economics!$AU$74>=PremiumBackEnd!D35),"X","") | J35: =+PremiumBackEnd!G35 -> 0.05 | L35: =IF(AND(Economics!$F$203=PremiumBackEnd!A35,Economics!$AV$57=PremiumBackEnd!B35,Economics!$F$205=PremiumBackEnd!C35,Economics!$AV$74<=PremiumBackEnd!E35,Economics!$AV$74>=PremiumBackEnd!D35),"X","") | M35: =+PremiumBackEnd!G35 -> 0.05 | P35: =+G35-Q35 -> 0.0075 | Q35: 0.0425
A36: Student | B36: MLI Market | C36: No | D36: =+E35+0.00001 -> 0.75001 | E36: 0.8 | F36: =IF(AND(Economics!$F$203=PremiumBackEnd!A36,Economics!$F$204=PremiumBackEnd!B36,Economics!$F$205=C36,$B$70<=PremiumBackEnd!E36,$B$70>=PremiumBackEnd!D36),"X","") -> #DIV/0! | G36: 0.0575 | I36: =IF(AND(Economics!$F$203=PremiumBackEnd!A36,Economics!$AU$57=PremiumBackEnd!B36,Economics!$F$205=PremiumBackEnd!C36,Economics!$AU$74<=PremiumBackEnd!E36,Economics!$AU$74>=PremiumBackEnd!D36),"X","") | J36: =+PremiumBackEnd!G36 -> 0.0575 | L36: =IF(AND(Economics!$F$203=PremiumBackEnd!A36,Economics!$AV$57=PremiumBackEnd!B36,Economics!$F$205=PremiumBackEnd!C36,Economics!$AV$74<=PremiumBackEnd!E36,Economics!$AV$74>=PremiumBackEnd!D36),"X","") | M36: =+PremiumBackEnd!G36 -> 0.0575 | P36: =+G36-Q36 -> 0.0075 | Q36: 0.05
A37: Student | B37: MLI Market | C37: No | D37: =+E36+0.00001 -> 0.80001 | E37: 0.85 | F37: =IF(AND(Economics!$F$203=PremiumBackEnd!A37,Economics!$F$204=PremiumBackEnd!B37,Economics!$F$205=C37,$B$70<=PremiumBackEnd!E37,$B$70>=PremiumBackEnd!D37),"X","") -> #DIV/0! | G37: 0.065 | I37: =IF(AND(Economics!$F$203=PremiumBackEnd!A37,Economics!$AU$57=PremiumBackEnd!B37,Economics!$F$205=PremiumBackEnd!C37,Economics!$AU$74<=PremiumBackEnd!E37,Economics!$AU$74>=PremiumBackEnd!D37),"X","") | J37: =+PremiumBackEnd!G37 -> 0.065 | L37: =IF(AND(Economics!$F$203=PremiumBackEnd!A37,Economics!$AV$57=PremiumBackEnd!B37,Economics!$F$205=PremiumBackEnd!C37,Economics!$AV$74<=PremiumBackEnd!E37,Economics!$AV$74>=PremiumBackEnd!D37),"X","") | M37: =+PremiumBackEnd!G37 -> 0.065 | P37: =+G37-Q37 -> 0.0075 | Q37: 0.0575
A39: SRO | B39: MLI Market | C39: No | D39: 0 | E39: 0.65 | F39: =IF(AND(Economics!$F$203=PremiumBackEnd!A39,Economics!$F$204=PremiumBackEnd!B39,Economics!$F$205=C39,$B$70<=PremiumBackEnd!E39,$B$70>=PremiumBackEnd!D39),"X","") -> #DIV/0! | G39: 0.04 | I39: =IF(AND(Economics!$F$203=PremiumBackEnd!A39,Economics!$AU$57=PremiumBackEnd!B39,Economics!$F$205=PremiumBackEnd!C39,Economics!$AU$74<=PremiumBackEnd!E39,Economics!$AU$74>=PremiumBackEnd!D39),"X","") | J39: =+PremiumBackEnd!G39 -> 0.04 | L39: =IF(AND(Economics!$F$203=PremiumBackEnd!A39,Economics!$AV$57=PremiumBackEnd!B39,Economics!$F$205=PremiumBackEnd!C39,Economics!$AV$74<=PremiumBackEnd!E39,Economics!$AV$74>=PremiumBackEnd!D39),"X","") | M39: =+PremiumBackEnd!G39 -> 0.04 | P39: =+G39-Q39 -> 0.0075 | Q39: 0.0325
A40: SRO | B40: MLI Market | C40: No | D40: =+E39+0.00001 -> 0.65001 | E40: 0.7 | F40: =IF(AND(Economics!$F$203=PremiumBackEnd!A40,Economics!$F$204=PremiumBackEnd!B40,Economics!$F$205=C40,$B$70<=PremiumBackEnd!E40,$B$70>=PremiumBackEnd!D40),"X","") -> #DIV/0! | G40: 0.045 | I40: =IF(AND(Economics!$F$203=PremiumBackEnd!A40,Economics!$AU$57=PremiumBackEnd!B40,Economics!$F$205=PremiumBackEnd!C40,Economics!$AU$74<=PremiumBackEnd!E40,Economics!$AU$74>=PremiumBackEnd!D40),"X","") | J40: =+PremiumBackEnd!G40 -> 0.045 | L40: =IF(AND(Economics!$F$203=PremiumBackEnd!A40,Economics!$AV$57=PremiumBackEnd!B40,Economics!$F$205=PremiumBackEnd!C40,Economics!$AV$74<=PremiumBackEnd!E40,Economics!$AV$74>=PremiumBackEnd!D40),"X","") | M40: =+PremiumBackEnd!G40 -> 0.045 | P40: =+G40-Q40 -> 0.0075 | Q40: 0.0375
A41: SRO | B41: MLI Market | C41: No | D41: =+E40+0.00001 -> 0.70001 | E41: 0.75 | F41: =IF(AND(Economics!$F$203=PremiumBackEnd!A41,Economics!$F$204=PremiumBackEnd!B41,Economics!$F$205=C41,$B$70<=PremiumBackEnd!E41,$B$70>=PremiumBackEnd!D41),"X","") -> #DIV/0! | G41: 0.05 | I41: =IF(AND(Economics!$F$203=PremiumBackEnd!A41,Economics!$AU$57=PremiumBackEnd!B41,Economics!$F$205=PremiumBackEnd!C41,Economics!$AU$74<=PremiumBackEnd!E41,Economics!$AU$74>=PremiumBackEnd!D41),"X","") | J41: =+PremiumBackEnd!G41 -> 0.05 | L41: =IF(AND(Economics!$F$203=PremiumBackEnd!A41,Economics!$AV$57=PremiumBackEnd!B41,Economics!$F$205=PremiumBackEnd!C41,Economics!$AV$74<=PremiumBackEnd!E41,Economics!$AV$74>=PremiumBackEnd!D41),"X","") | M41: =+PremiumBackEnd!G41 -> 0.05 | P41: =+G41-Q41 -> 0.0075 | Q41: 0.0425
A42: SRO | B42: MLI Market | C42: No | D42: =+E41+0.00001 -> 0.75001 | E42: 0.8 | F42: =IF(AND(Economics!$F$203=PremiumBackEnd!A42,Economics!$F$204=PremiumBackEnd!B42,Economics!$F$205=C42,$B$70<=PremiumBackEnd!E42,$B$70>=PremiumBackEnd!D42),"X","") -> #DIV/0! | G42: 0.0575 | I42: =IF(AND(Economics!$F$203=PremiumBackEnd!A42,Economics!$AU$57=PremiumBackEnd!B42,Economics!$F$205=PremiumBackEnd!C42,Economics!$AU$74<=PremiumBackEnd!E42,Economics!$AU$74>=PremiumBackEnd!D42),"X","") | J42: =+PremiumBackEnd!G42 -> 0.0575 | L42: =IF(AND(Economics!$F$203=PremiumBackEnd!A42,Economics!$AV$57=PremiumBackEnd!B42,Economics!$F$205=PremiumBackEnd!C42,Economics!$AV$74<=PremiumBackEnd!E42,Economics!$AV$74>=PremiumBackEnd!D42),"X","") | M42: =+PremiumBackEnd!G42 -> 0.0575 | P42: =+G42-Q42 -> 0.0075 | Q42: 0.05
A43: SRO | B43: MLI Market | C43: No | D43: =+E42+0.00001 -> 0.80001 | E43: 0.85 | F43: =IF(AND(Economics!$F$203=PremiumBackEnd!A43,Economics!$F$204=PremiumBackEnd!B43,Economics!$F$205=C43,$B$70<=PremiumBackEnd!E43,$B$70>=PremiumBackEnd!D43),"X","") -> #DIV/0! | G43: 0.065 | I43: =IF(AND(Economics!$F$203=PremiumBackEnd!A43,Economics!$AU$57=PremiumBackEnd!B43,Economics!$F$205=PremiumBackEnd!C43,Economics!$AU$74<=PremiumBackEnd!E43,Economics!$AU$74>=PremiumBackEnd!D43),"X","") | J43: =+PremiumBackEnd!G43 -> 0.065 | L43: =IF(AND(Economics!$F$203=PremiumBackEnd!A43,Economics!$AV$57=PremiumBackEnd!B43,Economics!$F$205=PremiumBackEnd!C43,Economics!$AV$74<=PremiumBackEnd!E43,Economics!$AV$74>=PremiumBackEnd!D43),"X","") | M43: =+PremiumBackEnd!G43 -> 0.065 | P43: =+G43-Q43 -> 0.0075 | Q43: 0.0575
A45: Retirement | B45: MLI Market | C45: No | D45: 0 | E45: 0.65 | F45: =IF(AND(Economics!$F$203=PremiumBackEnd!A45,Economics!$F$204=PremiumBackEnd!B45,Economics!$F$205=C45,$B$70<=PremiumBackEnd!E45,$B$70>=PremiumBackEnd!D45),"X","") -> #DIV/0! | G45: 0.0475 | I45: =IF(AND(Economics!$F$203=PremiumBackEnd!A45,Economics!$AU$57=PremiumBackEnd!B45,Economics!$F$205=PremiumBackEnd!C45,Economics!$AU$74<=PremiumBackEnd!E45,Economics!$AU$74>=PremiumBackEnd!D45),"X","") | J45: =+PremiumBackEnd!G45 -> 0.0475 | L45: =IF(AND(Economics!$F$203=PremiumBackEnd!A45,Economics!$AV$57=PremiumBackEnd!B45,Economics!$F$205=PremiumBackEnd!C45,Economics!$AV$74<=PremiumBackEnd!E45,Economics!$AV$74>=PremiumBackEnd!D45),"X","") | M45: =+PremiumBackEnd!G45 -> 0.0475 | P45: =+G45-Q45 -> 0.0075 | Q45: 0.04
A46: Retirement | B46: MLI Market | C46: No | D46: =+E45+0.00001 -> 0.65001 | E46: 0.7 | F46: =IF(AND(Economics!$F$203=PremiumBackEnd!A46,Economics!$F$204=PremiumBackEnd!B46,Economics!$F$205=C46,$B$70<=PremiumBackEnd!E46,$B$70>=PremiumBackEnd!D46),"X","") -> #DIV/0! | G46: 0.0525 | I46: =IF(AND(Economics!$F$203=PremiumBackEnd!A46,Economics!$AU$57=PremiumBackEnd!B46,Economics!$F$205=PremiumBackEnd!C46,Economics!$AU$74<=PremiumBackEnd!E46,Economics!$AU$74>=PremiumBackEnd!D46),"X","") | J46: =+PremiumBackEnd!G46 -> 0.0525 | L46: =IF(AND(Economics!$F$203=PremiumBackEnd!A46,Economics!$AV$57=PremiumBackEnd!B46,Economics!$F$205=PremiumBackEnd!C46,Economics!$AV$74<=PremiumBackEnd!E46,Economics!$AV$74>=PremiumBackEnd!D46),"X","") | M46: =+PremiumBackEnd!G46 -> 0.0525 | P46: =+G46-Q46 -> 0.0075 | Q46: 0.045
A47: Retirement | B47: MLI Market | C47: No | D47: =+E46+0.00001 -> 0.70001 | E47: 0.75 | F47: =IF(AND(Economics!$F$203=PremiumBackEnd!A47,Economics!$F$204=PremiumBackEnd!B47,Economics!$F$205=C47,$B$70<=PremiumBackEnd!E47,$B$70>=PremiumBackEnd!D47),"X","") -> #DIV/0! | G47: 0.0575 | I47: =IF(AND(Economics!$F$203=PremiumBackEnd!A47,Economics!$AU$57=PremiumBackEnd!B47,Economics!$F$205=PremiumBackEnd!C47,Economics!$AU$74<=PremiumBackEnd!E47,Economics!$AU$74>=PremiumBackEnd!D47),"X","") | J47: =+PremiumBackEnd!G47 -> 0.0575 | L47: =IF(AND(Economics!$F$203=PremiumBackEnd!A47,Economics!$AV$57=PremiumBackEnd!B47,Economics!$F$205=PremiumBackEnd!C47,Economics!$AV$74<=PremiumBackEnd!E47,Economics!$AV$74>=PremiumBackEnd!D47),"X","") | M47: =+PremiumBackEnd!G47 -> 0.0575 | P47: =+G47-Q47 -> 0.0075 | Q47: 0.05
A48: Retirement | B48: MLI Market | C48: No | D48: =+E47+0.00001 -> 0.75001 | E48: 0.8 | F48: =IF(AND(Economics!$F$203=PremiumBackEnd!A48,Economics!$F$204=PremiumBackEnd!B48,Economics!$F$205=C48,$B$70<=PremiumBackEnd!E48,$B$70>=PremiumBackEnd!D48),"X","") -> #DIV/0! | G48: 0.0625 | I48: =IF(AND(Economics!$F$203=PremiumBackEnd!A48,Economics!$AU$57=PremiumBackEnd!B48,Economics!$F$205=PremiumBackEnd!C48,Economics!$AU$74<=PremiumBackEnd!E48,Economics!$AU$74>=PremiumBackEnd!D48),"X","") | J48: =+PremiumBackEnd!G48 -> 0.0625 | L48: =IF(AND(Economics!$F$203=PremiumBackEnd!A48,Economics!$AV$57=PremiumBackEnd!B48,Economics!$F$205=PremiumBackEnd!C48,Economics!$AV$74<=PremiumBackEnd!E48,Economics!$AV$74>=PremiumBackEnd!D48),"X","") | M48: =+PremiumBackEnd!G48 -> 0.0625 | P48: =+G48-Q48 -> 0.0075 | Q48: 0.055
A49: Retirement | B49: MLI Market | C49: No | D49: =+E48+0.00001 -> 0.80001 | E49: 0.85 | F49: =IF(AND(Economics!$F$203=PremiumBackEnd!A49,Economics!$F$204=PremiumBackEnd!B49,Economics!$F$205=C49,$B$70<=PremiumBackEnd!E49,$B$70>=PremiumBackEnd!D49),"X","") -> #DIV/0! | G49: 0.07 | I49: =IF(AND(Economics!$F$203=PremiumBackEnd!A49,Economics!$AU$57=PremiumBackEnd!B49,Economics!$F$205=PremiumBackEnd!C49,Economics!$AU$74<=PremiumBackEnd!E49,Economics!$AU$74>=PremiumBackEnd!D49),"X","") | J49: =+PremiumBackEnd!G49 -> 0.07 | L49: =IF(AND(Economics!$F$203=PremiumBackEnd!A49,Economics!$AV$57=PremiumBackEnd!B49,Economics!$F$205=PremiumBackEnd!C49,Economics!$AV$74<=PremiumBackEnd!E49,Economics!$AV$74>=PremiumBackEnd!D49),"X","") | M49: =+PremiumBackEnd!G49 -> 0.07 | P49: =+G49-Q49 -> 0.0075 | Q49: 0.0625
B51: MLI Select | C51: Yes | D51: 50 | E51: 69.9999 | F51: =IF(AND(Economics!$F$204=PremiumBackEnd!B51,Economics!$F$205=C51,$B$72<=PremiumBackEnd!E51,$B$72>=PremiumBackEnd!D51),"X","") | G51: 0.038 | I51: =IF(AND(Economics!$AU$57=PremiumBackEnd!B51,Economics!$F$205=PremiumBackEnd!C51,PremiumBackEnd!$B$72<=PremiumBackEnd!E51,PremiumBackEnd!$B$72>=PremiumBackEnd!D51),"X","") | J51: =+PremiumBackEnd!G51 -> 0.038 | L51: =IF(AND(Economics!$AV$57=PremiumBackEnd!B51,Economics!$F$205=PremiumBackEnd!C51,PremiumBackEnd!$B$72<=PremiumBackEnd!E51,PremiumBackEnd!$B$72>=PremiumBackEnd!D51),"X","") | M51: =+PremiumBackEnd!G51 -> 0.038 | P51: =+G51-Q51 -> 0.0155 | Q51: 0.0225
B52: MLI Select | C52: Yes | D52: 70 | E52: 99.9999 | F52: =IF(AND(Economics!$F$204=PremiumBackEnd!B52,Economics!$F$205=C52,$B$72<=PremiumBackEnd!E52,$B$72>=PremiumBackEnd!D52),"X","") | G52: 0.033 | I52: =IF(AND(Economics!$AU$57=PremiumBackEnd!B52,Economics!$F$205=PremiumBackEnd!C52,PremiumBackEnd!$B$72<=PremiumBackEnd!E52,PremiumBackEnd!$B$72>=PremiumBackEnd!D52),"X","") | J52: =+PremiumBackEnd!G52 -> 0.033 | L52: =IF(AND(Economics!$AV$57=PremiumBackEnd!B52,Economics!$F$205=PremiumBackEnd!C52,PremiumBackEnd!$B$72<=PremiumBackEnd!E52,PremiumBackEnd!$B$72>=PremiumBackEnd!D52),"X","") | M52: =+PremiumBackEnd!G52 -> 0.033 | P52: =+G52-Q52 -> 0.0155 | Q52: 0.0175
B53: MLI Select | C53: Yes | D53: 100 | E53: 99999 | F53: =IF(AND(Economics!$F$204=PremiumBackEnd!B53,Economics!$F$205=C53,$B$72<=PremiumBackEnd!E53,$B$72>=PremiumBackEnd!D53),"X","") | G53: 0.0255 | I53: =IF(AND(Economics!$AU$57=PremiumBackEnd!B53,Economics!$F$205=PremiumBackEnd!C53,PremiumBackEnd!$B$72<=PremiumBackEnd!E53,PremiumBackEnd!$B$72>=PremiumBackEnd!D53),"X","") | J53: =+PremiumBackEnd!G53 -> 0.0255 | L53: =IF(AND(Economics!$AV$57=PremiumBackEnd!B53,Economics!$F$205=PremiumBackEnd!C53,PremiumBackEnd!$B$72<=PremiumBackEnd!E53,PremiumBackEnd!$B$72>=PremiumBackEnd!D53),"X","") | M53: =+PremiumBackEnd!G53 -> 0.0255 | P53: =+G53-Q53 -> 0.0155 | Q53: 0.01
B55: MLI Select | C55: No | D55: 50 | E55: 69.9999 | F55: =IF(AND(Economics!$F$204=PremiumBackEnd!B55,Economics!$F$205=C55,$B$72<=PremiumBackEnd!E55,$B$72>=PremiumBackEnd!D55),"X","") | G55: 0.0405 | I55: =IF(AND(Economics!$AU$57=PremiumBackEnd!B55,Economics!$F$205=PremiumBackEnd!C55,PremiumBackEnd!$B$72<=PremiumBackEnd!E55,PremiumBackEnd!$B$72>=PremiumBackEnd!D55),"X","") | J55: =+PremiumBackEnd!G55 -> 0.0405 | L55: =IF(AND(Economics!$AV$57=PremiumBackEnd!B55,Economics!$F$205=PremiumBackEnd!C55,PremiumBackEnd!$B$72<=PremiumBackEnd!E55,PremiumBackEnd!$B$72>=PremiumBackEnd!D55),"X","") | M55: =+PremiumBackEnd!G55 -> 0.0405 | P55: =+G55-Q55 -> 0.0155 | Q55: 0.025
B56: MLI Select | C56: No | D56: 70 | E56: 99.9999 | F56: =IF(AND(Economics!$F$204=PremiumBackEnd!B56,Economics!$F$205=C56,$B$72<=PremiumBackEnd!E56,$B$72>=PremiumBackEnd!D56),"X","") | G56: 0.0355 | I56: =IF(AND(Economics!$AU$57=PremiumBackEnd!B56,Economics!$F$205=PremiumBackEnd!C56,PremiumBackEnd!$B$72<=PremiumBackEnd!E56,PremiumBackEnd!$B$72>=PremiumBackEnd!D56),"X","") | J56: =+PremiumBackEnd!G56 -> 0.0355 | L56: =IF(AND(Economics!$AV$57=PremiumBackEnd!B56,Economics!$F$205=PremiumBackEnd!C56,PremiumBackEnd!$B$72<=PremiumBackEnd!E56,PremiumBackEnd!$B$72>=PremiumBackEnd!D56),"X","") | M56: =+PremiumBackEnd!G56 -> 0.0355 | P56: =+G56-Q56 -> 0.0155 | Q56: 0.02
B57: MLI Select | C57: No | D57: 100 | E57: 99999 | F57: =IF(AND(Economics!$F$204=PremiumBackEnd!B57,Economics!$F$205=C57,$B$72<=PremiumBackEnd!E57,$B$72>=PremiumBackEnd!D57),"X","") | G57: 0.028 | I57: =IF(AND(Economics!$AU$57=PremiumBackEnd!B57,Economics!$F$205=PremiumBackEnd!C57,PremiumBackEnd!$B$72<=PremiumBackEnd!E57,PremiumBackEnd!$B$72>=PremiumBackEnd!D57),"X","") | J57: =+PremiumBackEnd!G57 -> 0.028 | L57: =IF(AND(Economics!$AV$57=PremiumBackEnd!B57,Economics!$F$205=PremiumBackEnd!C57,PremiumBackEnd!$B$72<=PremiumBackEnd!E57,PremiumBackEnd!$B$72>=PremiumBackEnd!D57),"X","") | M57: =+PremiumBackEnd!G57 -> 0.028 | P57: =+G57-Q57 -> 0.0155 | Q57: 0.0125
D59: 5-yr Resi DSC | E59: 10-yr Resi DSC | F59: 5-yr Comm DSC | G59: 10-yr Comm DSC
A60: =B60&C60 -> Standard Rental HousingMLI Market | B60: Standard Rental Housing | C60: MLI Market | D60: 1.3 | E60: 1.2 | F60: 1.5 | G60: 1.4
A61: =B61&C61 -> Standard Rental HousingMLI Select | B61: Standard Rental Housing | C61: MLI Select | D61: 1.1 | E61: 1.1 | F61: 1.4 | G61: 1.4
A62: =B62&C62 -> StudentMLI Market | B62: Student | C62: MLI Market | D62: 1.4 | E62: 1.3 | F62: 1.5 | G62: 1.4
A63: =B63&C63 -> StudentMLI Select | B63: Student | C63: MLI Select | D63: 1.2 | E63: 1.2 | F63: 1.4 | G63: 1.4
A64: =B64&C64 -> SROMLI Market | B64: SRO | C64: MLI Market | D64: 1.3 | E64: 1.2 | F64: 1.5 | G64: 1.4
A65: =B65&C65 -> SROMLI Select | B65: SRO | C65: MLI Select | D65: 1.2 | E65: 1.2 | F65: 1.4 | G65: 1.4
A66: =B66&C66 -> RetirementMLI Market | B66: Retirement | C66: MLI Market | D66: 1.5 | E66: 1.4 | F66: 1.5 | G66: 1.4
A67: =B67&C67 -> RetirementMLI Select | B67: Retirement | C67: MLI Select | D67: 1.2 | E67: 1.2 | F67: 1.4 | G67: 1.4
A70: LTV | B70: =+IF(AND(Economics!J251<>0,ISNUMBER(Economics!J251)),Economics!J251,IF(AND(Economics!H169=0,Economics!I155=0),Economics!H80,SUM(Economics!H158,Economics!I155)/Economics!H54)) -> #DIV/0!
A71: LTV Range | B71: =IF(B70>0.8,"80%-85%",IF(B70>0.75,"75%-80%",IF(B70>0.7,"70%-75%",IF(B70>0.65,"65%-70%","<65%")))) -> #DIV/0!
A72: MLI Select Points | B72: =SUM(Economics!F217:F219) -> 0

Sheet Premium&DSCBackEndNEW
B2: CMHC Premiums (In Effect Starting July 14, 2025)
B4: Insurance Premiums Table | G4: Select vs Market Scenarios | N4: Summary
B5: Financing Type | C5: Housing Type | D5: Min LTV | E5: Max LTV | F5: Indicator | G5: Select - 50pts | H5: Select - 70pts | I5: Select - 100pts | J5: 5 yr Market | K5: 10yr Market | L5: New Base Premium | N5: Key Metric | P5: Result
B6: Construction Financing | C6: Standard Rental Housing | D6: 0 | E6: 0.65 | F6: =IF(AND($P$6=$B6,$P$7=$C6,$P$8>=$D6,$P$8<=$E6),"X","") -> #DIV/0! | G6: =IF(AND(Economics!$F$200=$B6,Economics!$F$203=$C6,Economics!$AJ$75>=$D6,Economics!$AJ$75<=$E6),"X","") -> #N/A | H6: =IF(AND(Economics!$F$200=$B6,Economics!$F$203=$C6,Economics!$AK$75>=$D6,Economics!$AK$75<=$E6),"X","") -> #N/A | I6: =IF(AND(Economics!$F$200=$B6,Economics!$F$203=$C6,Economics!$AL$75>=$D6,Economics!$AL$75<=$E6),"X","") -> #N/A | J6: =IF(AND(Economics!$F$200=$B6,Economics!$F$203=$C6,Economics!$AM$75>=$D6,Economics!$AM$75<=$E6),"X","") -> #N/A | K6: =IF(AND(Economics!$F$200=$B6,Economics!$F$203=$C6,Economics!$AN$75>=$D6,Economics!$AN$75<=$E6),"X","") -> #N/A | L6: 0.0325 | N6: Loan Type | P6: =Economics!$F$200 -> <Loan Type>
B7: Construction Financing | C7: Standard Rental Housing | D7: =E6+0.001% -> 0.65001 | E7: 0.7 | F7: =IF(AND($P$6=$B7,$P$7=$C7,$P$8>=$D7,$P$8<=$E7),"X","") -> #DIV/0! | G7: =IF(AND(Economics!$F$200=$B7,Economics!$F$203=$C7,Economics!$AJ$75>=$D7,Economics!$AJ$75<=$E7),"X","") -> #N/A | H7: =IF(AND(Economics!$F$200=$B7,Economics!$F$203=$C7,Economics!$AK$75>=$D7,Economics!$AK$75<=$E7),"X","") -> #N/A | I7: =IF(AND(Economics!$F$200=$B7,Economics!$F$203=$C7,Economics!$AL$75>=$D7,Economics!$AL$75<=$E7),"X","") -> #N/A | J7: =IF(AND(Economics!$F$200=$B7,Economics!$F$203=$C7,Economics!$AM$75>=$D7,Economics!$AM$75<=$E7),"X","") -> #N/A | K7: =IF(AND(Economics!$F$200=$B7,Economics!$F$203=$C7,Economics!$AN$75>=$D7,Economics!$AN$75<=$E7),"X","") -> #N/A | L7: 0.0375 | N7: Housing Type | P7: =Economics!$F$203 -> <Housing Type>
B8: Construction Financing | C8: Standard Rental Housing | D8: =E7+0.001% -> 0.70001 | E8: 0.75 | F8: =IF(AND($P$6=$B8,$P$7=$C8,$P$8>=$D8,$P$8<=$E8),"X","") -> #DIV/0! | G8: =IF(AND(Economics!$F$200=$B8,Economics!$F$203=$C8,Economics!$AJ$75>=$D8,Economics!$AJ$75<=$E8),"X","") -> #N/A | H8: =IF(AND(Economics!$F$200=$B8,Economics!$F$203=$C8,Economics!$AK$75>=$D8,Economics!$AK$75<=$E8),"X","") -> #N/A | I8: =IF(AND(Economics!$F$200=$B8,Economics!$F$203=$C8,Economics!$AL$75>=$D8,Economics!$AL$75<=$E8),"X","") -> #N/A | J8: =IF(AND(Economics!$F$200=$B8,Economics!$F$203=$C8,Economics!$AM$75>=$D8,Economics!$AM$75<=$E8),"X","") -> #N/A | K8: =IF(AND(Economics!$F$200=$B8,Economics!$F$203=$C8,Economics!$AN$75>=$D8,Economics!$AN$75<=$E8),"X","") -> #N/A | L8: 0.0425 | N8: LTV | P8: =+IF(AND(Economics!J251<>0,ISNUMBER(Economics!J251)),Economics!J251,IF(AND(Economics!H169=0,Economics!I155=0),Economics!H80,SUM(Economics!H158,Economics!I155)/Economics!H54)) -> #DIV/0!
B9: Construction Financing | C9: Standard Rental Housing | D9: =E8+0.001% -> 0.75001 | E9: 0.8 | F9: =IF(AND($P$6=$B9,$P$7=$C9,$P$8>=$D9,$P$8<=$E9),"X","") -> #DIV/0! | G9: =IF(AND(Economics!$F$200=$B9,Economics!$F$203=$C9,Economics!$AJ$75>=$D9,Economics!$AJ$75<=$E9),"X","") -> #N/A | H9: =IF(AND(Economics!$F$200=$B9,Economics!$F$203=$C9,Economics!$AK$75>=$D9,Economics!$AK$75<=$E9),"X","") -> #N/A | I9: =IF(AND(Economics!$F$200=$B9,Economics!$F$203=$C9,Economics!$AL$75>=$D9,Economics!$AL$75<=$E9),"X","") -> #N/A | J9: =IF(AND(Economics!$F$200=$B9,Economics!$F$203=$C9,Economics!$AM$75>=$D9,Economics!$AM$75<=$E9),"X","") -> #N/A | K9: =IF(AND(Economics!$F$200=$B9,Economics!$F$203=$C9,Economics!$AN$75>=$D9,Economics!$AN$75<=$E9),"X","") -> #N/A | L9: 0.05 | N9: LTV Range | P9: =IF(P8>0.9,">90%",IF(P8>0.85,"85%-90%",IF(P8>0.8,"80%-85%",IF(P8>0.75,"75%-80%",IF(P8>0.7,"70%-75%",IF(P8>0.65,"65%-70%","<65%")))))) -> #DIV/0!
B10: Construction Financing | C10: Standard Rental Housing | D10: =E9+0.001% -> 0.80001 | E10: 0.85 | F10: =IF(AND($P$6=$B10,$P$7=$C10,$P$8>=$D10,$P$8<=$E10),"X","") -> #DIV/0! | G10: =IF(AND(Economics!$F$200=$B10,Economics!$F$203=$C10,Economics!$AJ$75>=$D10,Economics!$AJ$75<=$E10),"X","") -> #N/A | H10: =IF(AND(Economics!$F$200=$B10,Economics!$F$203=$C10,Economics!$AK$75>=$D10,Economics!$AK$75<=$E10),"X","") -> #N/A | I10: =IF(AND(Economics!$F$200=$B10,Economics!$F$203=$C10,Economics!$AL$75>=$D10,Economics!$AL$75<=$E10),"X","") -> #N/A | J10: =IF(AND(Economics!$F$200=$B10,Economics!$F$203=$C10,Economics!$AM$75>=$D10,Economics!$AM$75<=$E10),"X","") -> #N/A | K10: =IF(AND(Economics!$F$200=$B10,Economics!$F$203=$C10,Economics!$AN$75>=$D10,Economics!$AN$75<=$E10),"X","") -> #N/A | L10: 0.06 | N10: MLI Select Points | P10: =SUM(Economics!F217:F219) -> 0
B11: Construction Financing | C11: Standard Rental Housing | D11: =E10+0.001% -> 0.85001 | E11: 0.9 | F11: =IF(AND($P$6=$B11,$P$7=$C11,$P$8>=$D11,$P$8<=$E11),"X","") -> #DIV/0! | G11: =IF(AND(Economics!$F$200=$B11,Economics!$F$203=$C11,Economics!$AJ$75>=$D11,Economics!$AJ$75<=$E11),"X","") -> #N/A | H11: =IF(AND(Economics!$F$200=$B11,Economics!$F$203=$C11,Economics!$AK$75>=$D11,Economics!$AK$75<=$E11),"X","") -> #N/A | I11: =IF(AND(Economics!$F$200=$B11,Economics!$F$203=$C11,Economics!$AL$75>=$D11,Economics!$AL$75<=$E11),"X","") -> #N/A | J11: =IF(AND(Economics!$F$200=$B11,Economics!$F$203=$C11,Economics!$AM$75>=$D11,Economics!$AM$75<=$E11),"X","") -> #N/A | K11: =IF(AND(Economics!$F$200=$B11,Economics!$F$203=$C11,Economics!$AN$75>=$D11,Economics!$AN$75<=$E11),"X","") -> #N/A | L11: 0.0675 | N11: EGI Test Met? | P11: =Economics!F205 -> <EGI Test Met>
B12: Construction Financing | C12: Standard Rental Housing | D12: =E11+0.001% -> 0.90001 | E12: 1 | F12: =IF(AND($P$6=$B12,$P$7=$C12,$P$8>=$D12,$P$8<=$E12),"X","") -> #DIV/0! | G12: =IF(AND(Economics!$F$200=$B12,Economics!$F$203=$C12,Economics!$AJ$75>=$D12,Economics!$AJ$75<=$E12),"X","") -> #N/A | H12: =IF(AND(Economics!$F$200=$B12,Economics!$F$203=$C12,Economics!$AK$75>=$D12,Economics!$AK$75<=$E12),"X","") -> #N/A | I12: =IF(AND(Economics!$F$200=$B12,Economics!$F$203=$C12,Economics!$AL$75>=$D12,Economics!$AL$75<=$E12),"X","") -> #N/A | J12: =IF(AND(Economics!$F$200=$B12,Economics!$F$203=$C12,Economics!$AM$75>=$D12,Economics!$AM$75<=$E12),"X","") -> #N/A | K12: =IF(AND(Economics!$F$200=$B12,Economics!$F$203=$C12,Economics!$AN$75>=$D12,Economics!$AN$75<=$E12),"X","") -> #N/A | L12: 0.07 | N12: Loan Type | P12: =Economics!F200 -> <Loan Type>
N13: Unit Count | P13: =Economics!$F$211 -> Populate Rent Roll
B14: Construction Financing | C14: Student | D14: 0 | E14: 0.65 | F14: =IF(AND($P$6=$B14,$P$7=$C14,$P$8>=$D14,$P$8<=$E14),"X","") -> #DIV/0! | G14: =IF(AND(Economics!$F$200=$B14,Economics!$F$203=$C14,Economics!$AJ$75>=$D14,Economics!$AJ$75<=$E14),"X","") -> #N/A | H14: =IF(AND(Economics!$F$200=$B14,Economics!$F$203=$C14,Economics!$AK$75>=$D14,Economics!$AK$75<=$E14),"X","") -> #N/A | I14: =IF(AND(Economics!$F$200=$B14,Economics!$F$203=$C14,Economics!$AL$75>=$D14,Economics!$AL$75<=$E14),"X","") -> #N/A | J14: =IF(AND(Economics!$F$200=$B14,Economics!$F$203=$C14,Economics!$AM$75>=$D14,Economics!$AM$75<=$E14),"X","") -> #N/A | K14: =IF(AND(Economics!$F$200=$B14,Economics!$F$203=$C14,Economics!$AN$75>=$D14,Economics!$AN$75<=$E14),"X","") -> #N/A | L14: 0.0655 | N14: Key Results for "Economics" Tab
B15: Construction Financing | C15: Student | D15: =E14+0.001% -> 0.65001 | E15: 0.7 | F15: =IF(AND($P$6=$B15,$P$7=$C15,$P$8>=$D15,$P$8<=$E15),"X","") -> #DIV/0! | G15: =IF(AND(Economics!$F$200=$B15,Economics!$F$203=$C15,Economics!$AJ$75>=$D15,Economics!$AJ$75<=$E15),"X","") -> #N/A | H15: =IF(AND(Economics!$F$200=$B15,Economics!$F$203=$C15,Economics!$AK$75>=$D15,Economics!$AK$75<=$E15),"X","") -> #N/A | I15: =IF(AND(Economics!$F$200=$B15,Economics!$F$203=$C15,Economics!$AL$75>=$D15,Economics!$AL$75<=$E15),"X","") -> #N/A | J15: =IF(AND(Economics!$F$200=$B15,Economics!$F$203=$C15,Economics!$AM$75>=$D15,Economics!$AM$75<=$E15),"X","") -> #N/A | K15: =IF(AND(Economics!$F$200=$B15,Economics!$F$203=$C15,Economics!$AN$75>=$D15,Economics!$AN$75<=$E15),"X","") -> #N/A | L15: 0.0685 | N15: Base Premium | P15: =INDEX(L6:L68,MATCH("X",F6:F68,0)) -> #N/A
B16: Construction Financing | C16: Student | D16: =E15+0.001% -> 0.70001 | E16: 0.75 | F16: =IF(AND($P$6=$B16,$P$7=$C16,$P$8>=$D16,$P$8<=$E16),"X","") -> #DIV/0! | G16: =IF(AND(Economics!$F$200=$B16,Economics!$F$203=$C16,Economics!$AJ$75>=$D16,Economics!$AJ$75<=$E16),"X","") -> #N/A | H16: =IF(AND(Economics!$F$200=$B16,Economics!$F$203=$C16,Economics!$AK$75>=$D16,Economics!$AK$75<=$E16),"X","") -> #N/A | I16: =IF(AND(Economics!$F$200=$B16,Economics!$F$203=$C16,Economics!$AL$75>=$D16,Economics!$AL$75<=$E16),"X","") -> #N/A | J16: =IF(AND(Economics!$F$200=$B16,Economics!$F$203=$C16,Economics!$AM$75>=$D16,Economics!$AM$75<=$E16),"X","") -> #N/A | K16: =IF(AND(Economics!$F$200=$B16,Economics!$F$203=$C16,Economics!$AN$75>=$D16,Economics!$AN$75<=$E16),"X","") -> #N/A | L16: 0.0715 | N16: MLI Select Discount | P16: =IF(P10<N21,0,IF(AND(P10>=N21,P10<=O21),P21,IF(AND(P10>=N22,P10<=O22),P22,IF(AND(P10>=N23,P10<=O23),P23)))) -> 0
B17: Construction Financing | C17: Student | D17: =E16+0.001% -> 0.75001 | E17: 0.8 | F17: =IF(AND($P$6=$B17,$P$7=$C17,$P$8>=$D17,$P$8<=$E17),"X","") -> #DIV/0! | G17: =IF(AND(Economics!$F$200=$B17,Economics!$F$203=$C17,Economics!$AJ$75>=$D17,Economics!$AJ$75<=$E17),"X","") -> #N/A | H17: =IF(AND(Economics!$F$200=$B17,Economics!$F$203=$C17,Economics!$AK$75>=$D17,Economics!$AK$75<=$E17),"X","") -> #N/A | I17: =IF(AND(Economics!$F$200=$B17,Economics!$F$203=$C17,Economics!$AL$75>=$D17,Economics!$AL$75<=$E17),"X","") -> #N/A | J17: =IF(AND(Economics!$F$200=$B17,Economics!$F$203=$C17,Economics!$AM$75>=$D17,Economics!$AM$75<=$E17),"X","") -> #N/A | K17: =IF(AND(Economics!$F$200=$B17,Economics!$F$203=$C17,Economics!$AN$75>=$D17,Economics!$AN$75<=$E17),"X","") -> #N/A | L17: 0.073 | N17: EGI Test Surcharge | P17: =IF(P12="Construction Financing", 0, IF(P11="Yes",P27,IF(P11="No",P28,"Populate EGI Test Field"))) -> Populate EGI Test Field
B18: Construction Financing | C18: Student | D18: =E17+0.001% -> 0.80001 | E18: 0.85 | F18: =IF(AND($P$6=$B18,$P$7=$C18,$P$8>=$D18,$P$8<=$E18),"X","") -> #DIV/0! | G18: =IF(AND(Economics!$F$200=$B18,Economics!$F$203=$C18,Economics!$AJ$75>=$D18,Economics!$AJ$75<=$E18),"X","") -> #N/A | H18: =IF(AND(Economics!$F$200=$B18,Economics!$F$203=$C18,Economics!$AK$75>=$D18,Economics!$AK$75<=$E18),"X","") -> #N/A | I18: =IF(AND(Economics!$F$200=$B18,Economics!$F$203=$C18,Economics!$AL$75>=$D18,Economics!$AL$75<=$E18),"X","") -> #N/A | J18: =IF(AND(Economics!$F$200=$B18,Economics!$F$203=$C18,Economics!$AM$75>=$D18,Economics!$AM$75<=$E18),"X","") -> #N/A | K18: =IF(AND(Economics!$F$200=$B18,Economics!$F$203=$C18,Economics!$AN$75>=$D18,Economics!$AN$75<=$E18),"X","") -> #N/A | L18: 0.08 | R18: Premium Credit Table
B19: Construction Financing | C19: Student | D19: =E18+0.001% -> 0.85001 | E19: 0.9 | F19: =IF(AND($P$6=$B19,$P$7=$C19,$P$8>=$D19,$P$8<=$E19),"X","") -> #DIV/0! | G19: =IF(AND(Economics!$F$200=$B19,Economics!$F$203=$C19,Economics!$AJ$75>=$D19,Economics!$AJ$75<=$E19),"X","") -> #N/A | H19: =IF(AND(Economics!$F$200=$B19,Economics!$F$203=$C19,Economics!$AK$75>=$D19,Economics!$AK$75<=$E19),"X","") -> #N/A | I19: =IF(AND(Economics!$F$200=$B19,Economics!$F$203=$C19,Economics!$AL$75>=$D19,Economics!$AL$75<=$E19),"X","") -> #N/A | J19: =IF(AND(Economics!$F$200=$B19,Economics!$F$203=$C19,Economics!$AM$75>=$D19,Economics!$AM$75<=$E19),"X","") -> #N/A | K19: =IF(AND(Economics!$F$200=$B19,Economics!$F$203=$C19,Economics!$AN$75>=$D19,Economics!$AN$75<=$E19),"X","") -> #N/A | L19: 0.0825 | N19: MLI Select Discount Table | R19: Years since | S19: Credit (% of
B20: Construction Financing | C20: Student | D20: =E19+0.001% -> 0.90001 | E20: 1 | F20: =IF(AND($P$6=$B20,$P$7=$C20,$P$8>=$D20,$P$8<=$E20),"X","") -> #DIV/0! | G20: =IF(AND(Economics!$F$200=$B20,Economics!$F$203=$C20,Economics!$AJ$75>=$D20,Economics!$AJ$75<=$E20),"X","") -> #N/A | H20: =IF(AND(Economics!$F$200=$B20,Economics!$F$203=$C20,Economics!$AK$75>=$D20,Economics!$AK$75<=$E20),"X","") -> #N/A | I20: =IF(AND(Economics!$F$200=$B20,Economics!$F$203=$C20,Economics!$AL$75>=$D20,Economics!$AL$75<=$E20),"X","") -> #N/A | J20: =IF(AND(Economics!$F$200=$B20,Economics!$F$203=$C20,Economics!$AM$75>=$D20,Economics!$AM$75<=$E20),"X","") -> #N/A | K20: =IF(AND(Economics!$F$200=$B20,Economics!$F$203=$C20,Economics!$AN$75>=$D20,Economics!$AN$75<=$E20),"X","") -> #N/A | L20: 0.09 | N20: Min Points | O20: Max Points | P20: Discount | R20: Previous Transaction | S20: Original Premium)
N21: 50 | O21: 69.9999 | P21: 0.1 | R21: 1 | S21: 0.75
B22: Construction Financing | C22: SRO | D22: 0 | E22: 0.65 | F22: =IF(AND($P$6=$B22,$P$7=$C22,$P$8>=$D22,$P$8<=$E22),"X","") -> #DIV/0! | G22: =IF(AND(Economics!$F$200=$B22,Economics!$F$203=$C22,Economics!$AJ$75>=$D22,Economics!$AJ$75<=$E22),"X","") -> #N/A | H22: =IF(AND(Economics!$F$200=$B22,Economics!$F$203=$C22,Economics!$AK$75>=$D22,Economics!$AK$75<=$E22),"X","") -> #N/A | I22: =IF(AND(Economics!$F$200=$B22,Economics!$F$203=$C22,Economics!$AL$75>=$D22,Economics!$AL$75<=$E22),"X","") -> #N/A | J22: =IF(AND(Economics!$F$200=$B22,Economics!$F$203=$C22,Economics!$AM$75>=$D22,Economics!$AM$75<=$E22),"X","") -> #N/A | K22: =IF(AND(Economics!$F$200=$B22,Economics!$F$203=$C22,Economics!$AN$75>=$D22,Economics!$AN$75<=$E22),"X","") -> #N/A | L22: 0.0655 | N22: 70 | O22: 99.9999 | P22: 0.2 | R22: 2 | S22: 0.7
B23: Construction Financing | C23: SRO | D23: =E22+0.001% -> 0.65001 | E23: 0.7 | F23: =IF(AND($P$6=$B23,$P$7=$C23,$P$8>=$D23,$P$8<=$E23),"X","") -> #DIV/0! | G23: =IF(AND(Economics!$F$200=$B23,Economics!$F$203=$C23,Economics!$AJ$75>=$D23,Economics!$AJ$75<=$E23),"X","") -> #N/A | H23: =IF(AND(Economics!$F$200=$B23,Economics!$F$203=$C23,Economics!$AK$75>=$D23,Economics!$AK$75<=$E23),"X","") -> #N/A | I23: =IF(AND(Economics!$F$200=$B23,Economics!$F$203=$C23,Economics!$AL$75>=$D23,Economics!$AL$75<=$E23),"X","") -> #N/A | J23: =IF(AND(Economics!$F$200=$B23,Economics!$F$203=$C23,Economics!$AM$75>=$D23,Economics!$AM$75<=$E23),"X","") -> #N/A | K23: =IF(AND(Economics!$F$200=$B23,Economics!$F$203=$C23,Economics!$AN$75>=$D23,Economics!$AN$75<=$E23),"X","") -> #N/A | L23: 0.0685 | N23: 100 | O23: 9999 | P23: 0.3 | R23: 3 | S23: 0.6
B24: Construction Financing | C24: SRO | D24: =E23+0.001% -> 0.70001 | E24: 0.75 | F24: =IF(AND($P$6=$B24,$P$7=$C24,$P$8>=$D24,$P$8<=$E24),"X","") -> #DIV/0! | G24: =IF(AND(Economics!$F$200=$B24,Economics!$F$203=$C24,Economics!$AJ$75>=$D24,Economics!$AJ$75<=$E24),"X","") -> #N/A | H24: =IF(AND(Economics!$F$200=$B24,Economics!$F$203=$C24,Economics!$AK$75>=$D24,Economics!$AK$75<=$E24),"X","") -> #N/A | I24: =IF(AND(Economics!$F$200=$B24,Economics!$F$203=$C24,Economics!$AL$75>=$D24,Economics!$AL$75<=$E24),"X","") -> #N/A | J24: =IF(AND(Economics!$F$200=$B24,Economics!$F$203=$C24,Economics!$AM$75>=$D24,Economics!$AM$75<=$E24),"X","") -> #N/A | K24: =IF(AND(Economics!$F$200=$B24,Economics!$F$203=$C24,Economics!$AN$75>=$D24,Economics!$AN$75<=$E24),"X","") -> #N/A | L24: 0.0715 | R24: 4 | S24: 0.5
B25: Construction Financing | C25: SRO | D25: =E24+0.001% -> 0.75001 | E25: 0.8 | F25: =IF(AND($P$6=$B25,$P$7=$C25,$P$8>=$D25,$P$8<=$E25),"X","") -> #DIV/0! | G25: =IF(AND(Economics!$F$200=$B25,Economics!$F$203=$C25,Economics!$AJ$75>=$D25,Economics!$AJ$75<=$E25),"X","") -> #N/A | H25: =IF(AND(Economics!$F$200=$B25,Economics!$F$203=$C25,Economics!$AK$75>=$D25,Economics!$AK$75<=$E25),"X","") -> #N/A | I25: =IF(AND(Economics!$F$200=$B25,Economics!$F$203=$C25,Economics!$AL$75>=$D25,Economics!$AL$75<=$E25),"X","") -> #N/A | J25: =IF(AND(Economics!$F$200=$B25,Economics!$F$203=$C25,Economics!$AM$75>=$D25,Economics!$AM$75<=$E25),"X","") -> #N/A | K25: =IF(AND(Economics!$F$200=$B25,Economics!$F$203=$C25,Economics!$AN$75>=$D25,Economics!$AN$75<=$E25),"X","") -> #N/A | L25: 0.073 | N25: EGI Test Surcharge Application | R25: 5 | S25: 0.4
B26: Construction Financing | C26: SRO | D26: =E25+0.001% -> 0.80001 | E26: 0.85 | F26: =IF(AND($P$6=$B26,$P$7=$C26,$P$8>=$D26,$P$8<=$E26),"X","") -> #DIV/0! | G26: =IF(AND(Economics!$F$200=$B26,Economics!$F$203=$C26,Economics!$AJ$75>=$D26,Economics!$AJ$75<=$E26),"X","") -> #N/A | H26: =IF(AND(Economics!$F$200=$B26,Economics!$F$203=$C26,Economics!$AK$75>=$D26,Economics!$AK$75<=$E26),"X","") -> #N/A | I26: =IF(AND(Economics!$F$200=$B26,Economics!$F$203=$C26,Economics!$AL$75>=$D26,Economics!$AL$75<=$E26),"X","") -> #N/A | J26: =IF(AND(Economics!$F$200=$B26,Economics!$F$203=$C26,Economics!$AM$75>=$D26,Economics!$AM$75<=$E26),"X","") -> #N/A | K26: =IF(AND(Economics!$F$200=$B26,Economics!$F$203=$C26,Economics!$AN$75>=$D26,Economics!$AN$75<=$E26),"X","") -> #N/A | L26: 0.08 | N26: EGI Test Met? | P26: Surcharge | R26: 6 | S26: 0.3
B27: Construction Financing | C27: SRO | D27: =E26+0.001% -> 0.85001 | E27: 0.9 | F27: =IF(AND($P$6=$B27,$P$7=$C27,$P$8>=$D27,$P$8<=$E27),"X","") -> #DIV/0! | G27: =IF(AND(Economics!$F$200=$B27,Economics!$F$203=$C27,Economics!$AJ$75>=$D27,Economics!$AJ$75<=$E27),"X","") -> #N/A | H27: =IF(AND(Economics!$F$200=$B27,Economics!$F$203=$C27,Economics!$AK$75>=$D27,Economics!$AK$75<=$E27),"X","") -> #N/A | I27: =IF(AND(Economics!$F$200=$B27,Economics!$F$203=$C27,Economics!$AL$75>=$D27,Economics!$AL$75<=$E27),"X","") -> #N/A | J27: =IF(AND(Economics!$F$200=$B27,Economics!$F$203=$C27,Economics!$AM$75>=$D27,Economics!$AM$75<=$E27),"X","") -> #N/A | K27: =IF(AND(Economics!$F$200=$B27,Economics!$F$203=$C27,Economics!$AN$75>=$D27,Economics!$AN$75<=$E27),"X","") -> #N/A | L27: 0.0825 | N27: Yes | P27: 0 | R27: 7 | S27: 0.2
B28: Construction Financing | C28: SRO | D28: =E27+0.001% -> 0.90001 | E28: 1 | F28: =IF(AND($P$6=$B28,$P$7=$C28,$P$8>=$D28,$P$8<=$E28),"X","") -> #DIV/0! | G28: =IF(AND(Economics!$F$200=$B28,Economics!$F$203=$C28,Economics!$AJ$75>=$D28,Economics!$AJ$75<=$E28),"X","") -> #N/A | H28: =IF(AND(Economics!$F$200=$B28,Economics!$F$203=$C28,Economics!$AK$75>=$D28,Economics!$AK$75<=$E28),"X","") -> #N/A | I28: =IF(AND(Economics!$F$200=$B28,Economics!$F$203=$C28,Economics!$AL$75>=$D28,Economics!$AL$75<=$E28),"X","") -> #N/A | J28: =IF(AND(Economics!$F$200=$B28,Economics!$F$203=$C28,Economics!$AM$75>=$D28,Economics!$AM$75<=$E28),"X","") -> #N/A | K28: =IF(AND(Economics!$F$200=$B28,Economics!$F$203=$C28,Economics!$AN$75>=$D28,Economics!$AN$75<=$E28),"X","") -> #N/A | L28: 0.09 | N28: No | P28: 0.0025
B30: Construction Financing | C30: Retirement | D30: 0 | E30: 0.65 | F30: =IF(AND($P$6=$B30,$P$7=$C30,$P$8>=$D30,$P$8<=$E30),"X","") -> #DIV/0! | G30: =IF(AND(Economics!$F$200=$B30,Economics!$F$203=$C30,Economics!$AJ$75>=$D30,Economics!$AJ$75<=$E30),"X","") -> #N/A | H30: =IF(AND(Economics!$F$200=$B30,Economics!$F$203=$C30,Economics!$AK$75>=$D30,Economics!$AK$75<=$E30),"X","") -> #N/A | I30: =IF(AND(Economics!$F$200=$B30,Economics!$F$203=$C30,Economics!$AL$75>=$D30,Economics!$AL$75<=$E30),"X","") -> #N/A | J30: =IF(AND(Economics!$F$200=$B30,Economics!$F$203=$C30,Economics!$AM$75>=$D30,Economics!$AM$75<=$E30),"X","") -> #N/A | K30: =IF(AND(Economics!$F$200=$B30,Economics!$F$203=$C30,Economics!$AN$75>=$D30,Economics!$AN$75<=$E30),"X","") -> #N/A | L30: 0.0655
B31: Construction Financing | C31: Retirement | D31: =E30+0.001% -> 0.65001 | E31: 0.7 | F31: =IF(AND($P$6=$B31,$P$7=$C31,$P$8>=$D31,$P$8<=$E31),"X","") -> #DIV/0! | G31: =IF(AND(Economics!$F$200=$B31,Economics!$F$203=$C31,Economics!$AJ$75>=$D31,Economics!$AJ$75<=$E31),"X","") -> #N/A | H31: =IF(AND(Economics!$F$200=$B31,Economics!$F$203=$C31,Economics!$AK$75>=$D31,Economics!$AK$75<=$E31),"X","") -> #N/A | I31: =IF(AND(Economics!$F$200=$B31,Economics!$F$203=$C31,Economics!$AL$75>=$D31,Economics!$AL$75<=$E31),"X","") -> #N/A | J31: =IF(AND(Economics!$F$200=$B31,Economics!$F$203=$C31,Economics!$AM$75>=$D31,Economics!$AM$75<=$E31),"X","") -> #N/A | K31: =IF(AND(Economics!$F$200=$B31,Economics!$F$203=$C31,Economics!$AN$75>=$D31,Economics!$AN$75<=$E31),"X","") -> #N/A | L31: 0.0685
B32: Construction Financing | C32: Retirement | D32: =E31+0.001% -> 0.70001 | E32: 0.75 | F32: =IF(AND($P$6=$B32,$P$7=$C32,$P$8>=$D32,$P$8<=$E32),"X","") -> #DIV/0! | G32: =IF(AND(Economics!$F$200=$B32,Economics!$F$203=$C32,Economics!$AJ$75>=$D32,Economics!$AJ$75<=$E32),"X","") -> #N/A | H32: =IF(AND(Economics!$F$200=$B32,Economics!$F$203=$C32,Economics!$AK$75>=$D32,Economics!$AK$75<=$E32),"X","") -> #N/A | I32: =IF(AND(Economics!$F$200=$B32,Economics!$F$203=$C32,Economics!$AL$75>=$D32,Economics!$AL$75<=$E32),"X","") -> #N/A | J32: =IF(AND(Economics!$F$200=$B32,Economics!$F$203=$C32,Economics!$AM$75>=$D32,Economics!$AM$75<=$E32),"X","") -> #N/A | K32: =IF(AND(Economics!$F$200=$B32,Economics!$F$203=$C32,Economics!$AN$75>=$D32,Economics!$AN$75<=$E32),"X","") -> #N/A | L32: 0.0715
B33: Construction Financing | C33: Retirement | D33: =E32+0.001% -> 0.75001 | E33: 0.8 | F33: =IF(AND($P$6=$B33,$P$7=$C33,$P$8>=$D33,$P$8<=$E33),"X","") -> #DIV/0! | G33: =IF(AND(Economics!$F$200=$B33,Economics!$F$203=$C33,Economics!$AJ$75>=$D33,Economics!$AJ$75<=$E33),"X","") -> #N/A | H33: =IF(AND(Economics!$F$200=$B33,Economics!$F$203=$C33,Economics!$AK$75>=$D33,Economics!$AK$75<=$E33),"X","") -> #N/A | I33: =IF(AND(Economics!$F$200=$B33,Economics!$F$203=$C33,Economics!$AL$75>=$D33,Economics!$AL$75<=$E33),"X","") -> #N/A | J33: =IF(AND(Economics!$F$200=$B33,Economics!$F$203=$C33,Economics!$AM$75>=$D33,Economics!$AM$75<=$E33),"X","") -> #N/A | K33: =IF(AND(Economics!$F$200=$B33,Economics!$F$203=$C33,Economics!$AN$75>=$D33,Economics!$AN$75<=$E33),"X","") -> #N/A | L33: 0.073
B34: Construction Financing | C34: Retirement | D34: =E33+0.001% -> 0.80001 | E34: 0.85 | F34: =IF(AND($P$6=$B34,$P$7=$C34,$P$8>=$D34,$P$8<=$E34),"X","") -> #DIV/0! | G34: =IF(AND(Economics!$F$200=$B34,Economics!$F$203=$C34,Economics!$AJ$75>=$D34,Economics!$AJ$75<=$E34),"X","") -> #N/A | H34: =IF(AND(Economics!$F$200=$B34,Economics!$F$203=$C34,Economics!$AK$75>=$D34,Economics!$AK$75<=$E34),"X","") -> #N/A | I34: =IF(AND(Economics!$F$200=$B34,Economics!$F$203=$C34,Economics!$AL$75>=$D34,Economics!$AL$75<=$E34),"X","") -> #N/A | J34: =IF(AND(Economics!$F$200=$B34,Economics!$F$203=$C34,Economics!$AM$75>=$D34,Economics!$AM$75<=$E34),"X","") -> #N/A | K34: =IF(AND(Economics!$F$200=$B34,Economics!$F$203=$C34,Economics!$AN$75>=$D34,Economics!$AN$75<=$E34),"X","") -> #N/A | L34: 0.08
B35: Construction Financing | C35: Retirement | D35: =E34+0.001% -> 0.85001 | E35: 0.9 | F35: =IF(AND($P$6=$B35,$P$7=$C35,$P$8>=$D35,$P$8<=$E35),"X","") -> #DIV/0! | G35: =IF(AND(Economics!$F$200=$B35,Economics!$F$203=$C35,Economics!$AJ$75>=$D35,Economics!$AJ$75<=$E35),"X","") -> #N/A | H35: =IF(AND(Economics!$F$200=$B35,Economics!$F$203=$C35,Economics!$AK$75>=$D35,Economics!$AK$75<=$E35),"X","") -> #N/A | I35: =IF(AND(Economics!$F$200=$B35,Economics!$F$203=$C35,Economics!$AL$75>=$D35,Economics!$AL$75<=$E35),"X","") -> #N/A | J35: =IF(AND(Economics!$F$200=$B35,Economics!$F$203=$C35,Economics!$AM$75>=$D35,Economics!$AM$75<=$E35),"X","") -> #N/A | K35: =IF(AND(Economics!$F$200=$B35,Economics!$F$203=$C35,Economics!$AN$75>=$D35,Economics!$AN$75<=$E35),"X","") -> #N/A | L35: 0.0825
B36: Construction Financing | C36: Retirement | D36: =E35+0.001% -> 0.90001 | E36: 1 | F36: =IF(AND($P$6=$B36,$P$7=$C36,$P$8>=$D36,$P$8<=$E36),"X","") -> #DIV/0! | G36: =IF(AND(Economics!$F$200=$B36,Economics!$F$203=$C36,Economics!$AJ$75>=$D36,Economics!$AJ$75<=$E36),"X","") -> #N/A | H36: =IF(AND(Economics!$F$200=$B36,Economics!$F$203=$C36,Economics!$AK$75>=$D36,Economics!$AK$75<=$E36),"X","") -> #N/A | I36: =IF(AND(Economics!$F$200=$B36,Economics!$F$203=$C36,Economics!$AL$75>=$D36,Economics!$AL$75<=$E36),"X","") -> #N/A | J36: =IF(AND(Economics!$F$200=$B36,Economics!$F$203=$C36,Economics!$AM$75>=$D36,Economics!$AM$75<=$E36),"X","") -> #N/A | K36: =IF(AND(Economics!$F$200=$B36,Economics!$F$203=$C36,Economics!$AN$75>=$D36,Economics!$AN$75<=$E36),"X","") -> #N/A | L36: 0.09
B38: All Other Loan Purposes | C38: Standard Rental Housing | D38: 0 | E38: 0.65 | F38: =IF(AND($P$6=$B38,$P$7=$C38,$P$8>=$D38,$P$8<=$E38),"X","") -> #DIV/0! | G38: =IF(AND(Economics!$F$200=$B38,Economics!$F$203=$C38,Economics!$AJ$75>=$D38,Economics!$AJ$75<=$E38),"X","") -> #N/A | H38: =IF(AND(Economics!$F$200=$B38,Economics!$F$203=$C38,Economics!$AK$75>=$D38,Economics!$AK$75<=$E38),"X","") -> #N/A | I38: =IF(AND(Economics!$F$200=$B38,Economics!$F$203=$C38,Economics!$AL$75>=$D38,Economics!$AL$75<=$E38),"X","") -> #N/A | J38: =IF(AND(Economics!$F$200=$B38,Economics!$F$203=$C38,Economics!$AM$75>=$D38,Economics!$AM$75<=$E38),"X","") -> #N/A | K38: =IF(AND(Economics!$F$200=$B38,Economics!$F$203=$C38,Economics!$AN$75>=$D38,Economics!$AN$75<=$E38),"X","") -> #N/A | L38: 0.026
B39: All Other Loan Purposes | C39: Standard Rental Housing | D39: =E38+0.001% -> 0.65001 | E39: 0.7 | F39: =IF(AND($P$6=$B39,$P$7=$C39,$P$8>=$D39,$P$8<=$E39),"X","") -> #DIV/0! | G39: =IF(AND(Economics!$F$200=$B39,Economics!$F$203=$C39,Economics!$AJ$75>=$D39,Economics!$AJ$75<=$E39),"X","") -> #N/A | H39: =IF(AND(Economics!$F$200=$B39,Economics!$F$203=$C39,Economics!$AK$75>=$D39,Economics!$AK$75<=$E39),"X","") -> #N/A | I39: =IF(AND(Economics!$F$200=$B39,Economics!$F$203=$C39,Economics!$AL$75>=$D39,Economics!$AL$75<=$E39),"X","") -> #N/A | J39: =IF(AND(Economics!$F$200=$B39,Economics!$F$203=$C39,Economics!$AM$75>=$D39,Economics!$AM$75<=$E39),"X","") -> #N/A | K39: =IF(AND(Economics!$F$200=$B39,Economics!$F$203=$C39,Economics!$AN$75>=$D39,Economics!$AN$75<=$E39),"X","") -> #N/A | L39: 0.0285
B40: All Other Loan Purposes | C40: Standard Rental Housing | D40: =E39+0.001% -> 0.70001 | E40: 0.75 | F40: =IF(AND($P$6=$B40,$P$7=$C40,$P$8>=$D40,$P$8<=$E40),"X","") -> #DIV/0! | G40: =IF(AND(Economics!$F$200=$B40,Economics!$F$203=$C40,Economics!$AJ$75>=$D40,Economics!$AJ$75<=$E40),"X","") -> #N/A | H40: =IF(AND(Economics!$F$200=$B40,Economics!$F$203=$C40,Economics!$AK$75>=$D40,Economics!$AK$75<=$E40),"X","") -> #N/A | I40: =IF(AND(Economics!$F$200=$B40,Economics!$F$203=$C40,Economics!$AL$75>=$D40,Economics!$AL$75<=$E40),"X","") -> #N/A | J40: =IF(AND(Economics!$F$200=$B40,Economics!$F$203=$C40,Economics!$AM$75>=$D40,Economics!$AM$75<=$E40),"X","") -> #N/A | K40: =IF(AND(Economics!$F$200=$B40,Economics!$F$203=$C40,Economics!$AN$75>=$D40,Economics!$AN$75<=$E40),"X","") -> #N/A | L40: 0.0335
B41: All Other Loan Purposes | C41: Standard Rental Housing | D41: =E40+0.001% -> 0.75001 | E41: 0.8 | F41: =IF(AND($P$6=$B41,$P$7=$C41,$P$8>=$D41,$P$8<=$E41),"X","") -> #DIV/0! | G41: =IF(AND(Economics!$F$200=$B41,Economics!$F$203=$C41,Economics!$AJ$75>=$D41,Economics!$AJ$75<=$E41),"X","") -> #N/A | H41: =IF(AND(Economics!$F$200=$B41,Economics!$F$203=$C41,Economics!$AK$75>=$D41,Economics!$AK$75<=$E41),"X","") -> #N/A | I41: =IF(AND(Economics!$F$200=$B41,Economics!$F$203=$C41,Economics!$AL$75>=$D41,Economics!$AL$75<=$E41),"X","") -> #N/A | J41: =IF(AND(Economics!$F$200=$B41,Economics!$F$203=$C41,Economics!$AM$75>=$D41,Economics!$AM$75<=$E41),"X","") -> #N/A | K41: =IF(AND(Economics!$F$200=$B41,Economics!$F$203=$C41,Economics!$AN$75>=$D41,Economics!$AN$75<=$E41),"X","") -> #N/A | L41: 0.0435
B42: All Other Loan Purposes | C42: Standard Rental Housing | D42: =E41+0.001% -> 0.80001 | E42: 0.85 | F42: =IF(AND($P$6=$B42,$P$7=$C42,$P$8>=$D42,$P$8<=$E42),"X","") -> #DIV/0! | G42: =IF(AND(Economics!$F$200=$B42,Economics!$F$203=$C42,Economics!$AJ$75>=$D42,Economics!$AJ$75<=$E42),"X","") -> #N/A | H42: =IF(AND(Economics!$F$200=$B42,Economics!$F$203=$C42,Economics!$AK$75>=$D42,Economics!$AK$75<=$E42),"X","") -> #N/A | I42: =IF(AND(Economics!$F$200=$B42,Economics!$F$203=$C42,Economics!$AL$75>=$D42,Economics!$AL$75<=$E42),"X","") -> #N/A | J42: =IF(AND(Economics!$F$200=$B42,Economics!$F$203=$C42,Economics!$AM$75>=$D42,Economics!$AM$75<=$E42),"X","") -> #N/A | K42: =IF(AND(Economics!$F$200=$B42,Economics!$F$203=$C42,Economics!$AN$75>=$D42,Economics!$AN$75<=$E42),"X","") -> #N/A | L42: 0.0535
B43: All Other Loan Purposes | C43: Standard Rental Housing | D43: =E42+0.001% -> 0.85001 | E43: 0.9 | F43: =IF(AND($P$6=$B43,$P$7=$C43,$P$8>=$D43,$P$8<=$E43),"X","") -> #DIV/0! | G43: =IF(AND(Economics!$F$200=$B43,Economics!$F$203=$C43,Economics!$AJ$75>=$D43,Economics!$AJ$75<=$E43),"X","") -> #N/A | H43: =IF(AND(Economics!$F$200=$B43,Economics!$F$203=$C43,Economics!$AK$75>=$D43,Economics!$AK$75<=$E43),"X","") -> #N/A | I43: =IF(AND(Economics!$F$200=$B43,Economics!$F$203=$C43,Economics!$AL$75>=$D43,Economics!$AL$75<=$E43),"X","") -> #N/A | J43: =IF(AND(Economics!$F$200=$B43,Economics!$F$203=$C43,Economics!$AM$75>=$D43,Economics!$AM$75<=$E43),"X","") -> #N/A | K43: =IF(AND(Economics!$F$200=$B43,Economics!$F$203=$C43,Economics!$AN$75>=$D43,Economics!$AN$75<=$E43),"X","") -> #N/A | L43: 0.059
B44: All Other Loan Purposes | C44: Standard Rental Housing | D44: =E43+0.001% -> 0.90001 | E44: 1 | F44: =IF(AND($P$6=$B44,$P$7=$C44,$P$8>=$D44,$P$8<=$E44),"X","") -> #DIV/0! | G44: =IF(AND(Economics!$F$200=$B44,Economics!$F$203=$C44,Economics!$AJ$75>=$D44,Economics!$AJ$75<=$E44),"X","") -> #N/A | H44: =IF(AND(Economics!$F$200=$B44,Economics!$F$203=$C44,Economics!$AK$75>=$D44,Economics!$AK$75<=$E44),"X","") -> #N/A | I44: =IF(AND(Economics!$F$200=$B44,Economics!$F$203=$C44,Economics!$AL$75>=$D44,Economics!$AL$75<=$E44),"X","") -> #N/A | J44: =IF(AND(Economics!$F$200=$B44,Economics!$F$203=$C44,Economics!$AM$75>=$D44,Economics!$AM$75<=$E44),"X","") -> #N/A | K44: =IF(AND(Economics!$F$200=$B44,Economics!$F$203=$C44,Economics!$AN$75>=$D44,Economics!$AN$75<=$E44),"X","") -> #N/A | L44: 0.0615
B46: All Other Loan Purposes | C46: Student | D46: 0 | E46: 0.65 | F46: =IF(AND($P$6=$B46,$P$7=$C46,$P$8>=$D46,$P$8<=$E46),"X","") -> #DIV/0! | G46: =IF(AND(Economics!$F$200=$B46,Economics!$F$203=$C46,Economics!$AJ$75>=$D46,Economics!$AJ$75<=$E46),"X","") -> #N/A | H46: =IF(AND(Economics!$F$200=$B46,Economics!$F$203=$C46,Economics!$AK$75>=$D46,Economics!$AK$75<=$E46),"X","") -> #N/A | I46: =IF(AND(Economics!$F$200=$B46,Economics!$F$203=$C46,Economics!$AL$75>=$D46,Economics!$AL$75<=$E46),"X","") -> #N/A | J46: =IF(AND(Economics!$F$200=$B46,Economics!$F$203=$C46,Economics!$AM$75>=$D46,Economics!$AM$75<=$E46),"X","") -> #N/A | K46: =IF(AND(Economics!$F$200=$B46,Economics!$F$203=$C46,Economics!$AN$75>=$D46,Economics!$AN$75<=$E46),"X","") -> #N/A | L46: 0.063
B47: All Other Loan Purposes | C47: Student | D47: =E46+0.001% -> 0.65001 | E47: 0.7 | F47: =IF(AND($P$6=$B47,$P$7=$C47,$P$8>=$D47,$P$8<=$E47),"X","") -> #DIV/0! | G47: =IF(AND(Economics!$F$200=$B47,Economics!$F$203=$C47,Economics!$AJ$75>=$D47,Economics!$AJ$75<=$E47),"X","") -> #N/A | H47: =IF(AND(Economics!$F$200=$B47,Economics!$F$203=$C47,Economics!$AK$75>=$D47,Economics!$AK$75<=$E47),"X","") -> #N/A | I47: =IF(AND(Economics!$F$200=$B47,Economics!$F$203=$C47,Economics!$AL$75>=$D47,Economics!$AL$75<=$E47),"X","") -> #N/A | J47: =IF(AND(Economics!$F$200=$B47,Economics!$F$203=$C47,Economics!$AM$75>=$D47,Economics!$AM$75<=$E47),"X","") -> #N/A | K47: =IF(AND(Economics!$F$200=$B47,Economics!$F$203=$C47,Economics!$AN$75>=$D47,Economics!$AN$75<=$E47),"X","") -> #N/A | L47: 0.066
B48: All Other Loan Purposes | C48: Student | D48: =E47+0.001% -> 0.70001 | E48: 0.75 | F48: =IF(AND($P$6=$B48,$P$7=$C48,$P$8>=$D48,$P$8<=$E48),"X","") -> #DIV/0! | G48: =IF(AND(Economics!$F$200=$B48,Economics!$F$203=$C48,Economics!$AJ$75>=$D48,Economics!$AJ$75<=$E48),"X","") -> #N/A | H48: =IF(AND(Economics!$F$200=$B48,Economics!$F$203=$C48,Economics!$AK$75>=$D48,Economics!$AK$75<=$E48),"X","") -> #N/A | I48: =IF(AND(Economics!$F$200=$B48,Economics!$F$203=$C48,Economics!$AL$75>=$D48,Economics!$AL$75<=$E48),"X","") -> #N/A | J48: =IF(AND(Economics!$F$200=$B48,Economics!$F$203=$C48,Economics!$AM$75>=$D48,Economics!$AM$75<=$E48),"X","") -> #N/A | K48: =IF(AND(Economics!$F$200=$B48,Economics!$F$203=$C48,Economics!$AN$75>=$D48,Economics!$AN$75<=$E48),"X","") -> #N/A | L48: 0.069
B49: All Other Loan Purposes | C49: Student | D49: =E48+0.001% -> 0.75001 | E49: 0.8 | F49: =IF(AND($P$6=$B49,$P$7=$C49,$P$8>=$D49,$P$8<=$E49),"X","") -> #DIV/0! | G49: =IF(AND(Economics!$F$200=$B49,Economics!$F$203=$C49,Economics!$AJ$75>=$D49,Economics!$AJ$75<=$E49),"X","") -> #N/A | H49: =IF(AND(Economics!$F$200=$B49,Economics!$F$203=$C49,Economics!$AK$75>=$D49,Economics!$AK$75<=$E49),"X","") -> #N/A | I49: =IF(AND(Economics!$F$200=$B49,Economics!$F$203=$C49,Economics!$AL$75>=$D49,Economics!$AL$75<=$E49),"X","") -> #N/A | J49: =IF(AND(Economics!$F$200=$B49,Economics!$F$203=$C49,Economics!$AM$75>=$D49,Economics!$AM$75<=$E49),"X","") -> #N/A | K49: =IF(AND(Economics!$F$200=$B49,Economics!$F$203=$C49,Economics!$AN$75>=$D49,Economics!$AN$75<=$E49),"X","") -> #N/A | L49: 0.0705
B50: All Other Loan Purposes | C50: Student | D50: =E49+0.001% -> 0.80001 | E50: 0.85 | F50: =IF(AND($P$6=$B50,$P$7=$C50,$P$8>=$D50,$P$8<=$E50),"X","") -> #DIV/0! | G50: =IF(AND(Economics!$F$200=$B50,Economics!$F$203=$C50,Economics!$AJ$75>=$D50,Economics!$AJ$75<=$E50),"X","") -> #N/A | H50: =IF(AND(Economics!$F$200=$B50,Economics!$F$203=$C50,Economics!$AK$75>=$D50,Economics!$AK$75<=$E50),"X","") -> #N/A | I50: =IF(AND(Economics!$F$200=$B50,Economics!$F$203=$C50,Economics!$AL$75>=$D50,Economics!$AL$75<=$E50),"X","") -> #N/A | J50: =IF(AND(Economics!$F$200=$B50,Economics!$F$203=$C50,Economics!$AM$75>=$D50,Economics!$AM$75<=$E50),"X","") -> #N/A | K50: =IF(AND(Economics!$F$200=$B50,Economics!$F$203=$C50,Economics!$AN$75>=$D50,Economics!$AN$75<=$E50),"X","") -> #N/A | L50: 0.0775
B51: All Other Loan Purposes | C51: Student | D51: =E50+0.001% -> 0.85001 | E51: 0.9 | F51: =IF(AND($P$6=$B51,$P$7=$C51,$P$8>=$D51,$P$8<=$E51),"X","") -> #DIV/0! | G51: =IF(AND(Economics!$F$200=$B51,Economics!$F$203=$C51,Economics!$AJ$75>=$D51,Economics!$AJ$75<=$E51),"X","") -> #N/A | H51: =IF(AND(Economics!$F$200=$B51,Economics!$F$203=$C51,Economics!$AK$75>=$D51,Economics!$AK$75<=$E51),"X","") -> #N/A | I51: =IF(AND(Economics!$F$200=$B51,Economics!$F$203=$C51,Economics!$AL$75>=$D51,Economics!$AL$75<=$E51),"X","") -> #N/A | J51: =IF(AND(Economics!$F$200=$B51,Economics!$F$203=$C51,Economics!$AM$75>=$D51,Economics!$AM$75<=$E51),"X","") -> #N/A | K51: =IF(AND(Economics!$F$200=$B51,Economics!$F$203=$C51,Economics!$AN$75>=$D51,Economics!$AN$75<=$E51),"X","") -> #N/A | L51: 0.08
B52: All Other Loan Purposes | C52: Student | D52: =E51+0.001% -> 0.90001 | E52: 1 | F52: =IF(AND($P$6=$B52,$P$7=$C52,$P$8>=$D52,$P$8<=$E52),"X","") -> #DIV/0! | G52: =IF(AND(Economics!$F$200=$B52,Economics!$F$203=$C52,Economics!$AJ$75>=$D52,Economics!$AJ$75<=$E52),"X","") -> #N/A | H52: =IF(AND(Economics!$F$200=$B52,Economics!$F$203=$C52,Economics!$AK$75>=$D52,Economics!$AK$75<=$E52),"X","") -> #N/A | I52: =IF(AND(Economics!$F$200=$B52,Economics!$F$203=$C52,Economics!$AL$75>=$D52,Economics!$AL$75<=$E52),"X","") -> #N/A | J52: =IF(AND(Economics!$F$200=$B52,Economics!$F$203=$C52,Economics!$AM$75>=$D52,Economics!$AM$75<=$E52),"X","") -> #N/A | K52: =IF(AND(Economics!$F$200=$B52,Economics!$F$203=$C52,Economics!$AN$75>=$D52,Economics!$AN$75<=$E52),"X","") -> #N/A | L52: 0.0875
B54: All Other Loan Purposes | C54: SRO | D54: 0 | E54: 0.65 | F54: =IF(AND($P$6=$B54,$P$7=$C54,$P$8>=$D54,$P$8<=$E54),"X","") -> #DIV/0! | G54: =IF(AND(Economics!$F$200=$B54,Economics!$F$203=$C54,Economics!$AJ$75>=$D54,Economics!$AJ$75<=$E54),"X","") -> #N/A | H54: =IF(AND(Economics!$F$200=$B54,Economics!$F$203=$C54,Economics!$AK$75>=$D54,Economics!$AK$75<=$E54),"X","") -> #N/A | I54: =IF(AND(Economics!$F$200=$B54,Economics!$F$203=$C54,Economics!$AL$75>=$D54,Economics!$AL$75<=$E54),"X","") -> #N/A | J54: =IF(AND(Economics!$F$200=$B54,Economics!$F$203=$C54,Economics!$AM$75>=$D54,Economics!$AM$75<=$E54),"X","") -> #N/A | K54: =IF(AND(Economics!$F$200=$B54,Economics!$F$203=$C54,Economics!$AN$75>=$D54,Economics!$AN$75<=$E54),"X","") -> #N/A | L54: 0.063
B55: All Other Loan Purposes | C55: SRO | D55: =E54+0.001% -> 0.65001 | E55: 0.7 | F55: =IF(AND($P$6=$B55,$P$7=$C55,$P$8>=$D55,$P$8<=$E55),"X","") -> #DIV/0! | G55: =IF(AND(Economics!$F$200=$B55,Economics!$F$203=$C55,Economics!$AJ$75>=$D55,Economics!$AJ$75<=$E55),"X","") -> #N/A | H55: =IF(AND(Economics!$F$200=$B55,Economics!$F$203=$C55,Economics!$AK$75>=$D55,Economics!$AK$75<=$E55),"X","") -> #N/A | I55: =IF(AND(Economics!$F$200=$B55,Economics!$F$203=$C55,Economics!$AL$75>=$D55,Economics!$AL$75<=$E55),"X","") -> #N/A | J55: =IF(AND(Economics!$F$200=$B55,Economics!$F$203=$C55,Economics!$AM$75>=$D55,Economics!$AM$75<=$E55),"X","") -> #N/A | K55: =IF(AND(Economics!$F$200=$B55,Economics!$F$203=$C55,Economics!$AN$75>=$D55,Economics!$AN$75<=$E55),"X","") -> #N/A | L55: 0.066
B56: All Other Loan Purposes | C56: SRO | D56: =E55+0.001% -> 0.70001 | E56: 0.75 | F56: =IF(AND($P$6=$B56,$P$7=$C56,$P$8>=$D56,$P$8<=$E56),"X","") -> #DIV/0! | G56: =IF(AND(Economics!$F$200=$B56,Economics!$F$203=$C56,Economics!$AJ$75>=$D56,Economics!$AJ$75<=$E56),"X","") -> #N/A | H56: =IF(AND(Economics!$F$200=$B56,Economics!$F$203=$C56,Economics!$AK$75>=$D56,Economics!$AK$75<=$E56),"X","") -> #N/A | I56: =IF(AND(Economics!$F$200=$B56,Economics!$F$203=$C56,Economics!$AL$75>=$D56,Economics!$AL$75<=$E56),"X","") -> #N/A | J56: =IF(AND(Economics!$F$200=$B56,Economics!$F$203=$C56,Economics!$AM$75>=$D56,Economics!$AM$75<=$E56),"X","") -> #N/A | K56: =IF(AND(Economics!$F$200=$B56,Economics!$F$203=$C56,Economics!$AN$75>=$D56,Economics!$AN$75<=$E56),"X","") -> #N/A | L56: 0.069
B57: All Other Loan Purposes | C57: SRO | D57: =E56+0.001% -> 0.75001 | E57: 0.8 | F57: =IF(AND($P$6=$B57,$P$7=$C57,$P$8>=$D57,$P$8<=$E57),"X","") -> #DIV/0! | G57: =IF(AND(Economics!$F$200=$B57,Economics!$F$203=$C57,Economics!$AJ$75>=$D57,Economics!$AJ$75<=$E57),"X","") -> #N/A | H57: =IF(AND(Economics!$F$200=$B57,Economics!$F$203=$C57,Economics!$AK$75>=$D57,Economics!$AK$75<=$E57),"X","") -> #N/A | I57: =IF(AND(Economics!$F$200=$B57,Economics!$F$203=$C57,Economics!$AL$75>=$D57,Economics!$AL$75<=$E57),"X","") -> #N/A | J57: =IF(AND(Economics!$F$200=$B57,Economics!$F$203=$C57,Economics!$AM$75>=$D57,Economics!$AM$75<=$E57),"X","") -> #N/A | K57: =IF(AND(Economics!$F$200=$B57,Economics!$F$203=$C57,Economics!$AN$75>=$D57,Economics!$AN$75<=$E57),"X","") -> #N/A | L57: 0.0705
B58: All Other Loan Purposes | C58: SRO | D58: =E57+0.001% -> 0.80001 | E58: 0.85 | F58: =IF(AND($P$6=$B58,$P$7=$C58,$P$8>=$D58,$P$8<=$E58),"X","") -> #DIV/0! | G58: =IF(AND(Economics!$F$200=$B58,Economics!$F$203=$C58,Economics!$AJ$75>=$D58,Economics!$AJ$75<=$E58),"X","") -> #N/A | H58: =IF(AND(Economics!$F$200=$B58,Economics!$F$203=$C58,Economics!$AK$75>=$D58,Economics!$AK$75<=$E58),"X","") -> #N/A | I58: =IF(AND(Economics!$F$200=$B58,Economics!$F$203=$C58,Economics!$AL$75>=$D58,Economics!$AL$75<=$E58),"X","") -> #N/A | J58: =IF(AND(Economics!$F$200=$B58,Economics!$F$203=$C58,Economics!$AM$75>=$D58,Economics!$AM$75<=$E58),"X","") -> #N/A | K58: =IF(AND(Economics!$F$200=$B58,Economics!$F$203=$C58,Economics!$AN$75>=$D58,Economics!$AN$75<=$E58),"X","") -> #N/A | L58: 0.0775
B59: All Other Loan Purposes | C59: SRO | D59: =E58+0.001% -> 0.85001 | E59: 0.9 | F59: =IF(AND($P$6=$B59,$P$7=$C59,$P$8>=$D59,$P$8<=$E59),"X","") -> #DIV/0! | G59: =IF(AND(Economics!$F$200=$B59,Economics!$F$203=$C59,Economics!$AJ$75>=$D59,Economics!$AJ$75<=$E59),"X","") -> #N/A | H59: =IF(AND(Economics!$F$200=$B59,Economics!$F$203=$C59,Economics!$AK$75>=$D59,Economics!$AK$75<=$E59),"X","") -> #N/A | I59: =IF(AND(Economics!$F$200=$B59,Economics!$F$203=$C59,Economics!$AL$75>=$D59,Economics!$AL$75<=$E59),"X","") -> #N/A | J59: =IF(AND(Economics!$F$200=$B59,Economics!$F$203=$C59,Economics!$AM$75>=$D59,Economics!$AM$75<=$E59),"X","") -> #N/A | K59: =IF(AND(Economics!$F$200=$B59,Economics!$F$203=$C59,Economics!$AN$75>=$D59,Economics!$AN$75<=$E59),"X","") -> #N/A | L59: 0.08
B60: All Other Loan Purposes | C60: SRO | D60: =E59+0.001% -> 0.90001 | E60: 1 | F60: =IF(AND($P$6=$B60,$P$7=$C60,$P$8>=$D60,$P$8<=$E60),"X","") -> #DIV/0! | G60: =IF(AND(Economics!$F$200=$B60,Economics!$F$203=$C60,Economics!$AJ$75>=$D60,Economics!$AJ$75<=$E60),"X","") -> #N/A | H60: =IF(AND(Economics!$F$200=$B60,Economics!$F$203=$C60,Economics!$AK$75>=$D60,Economics!$AK$75<=$E60),"X","") -> #N/A | I60: =IF(AND(Economics!$F$200=$B60,Economics!$F$203=$C60,Economics!$AL$75>=$D60,Economics!$AL$75<=$E60),"X","") -> #N/A | J60: =IF(AND(Economics!$F$200=$B60,Economics!$F$203=$C60,Economics!$AM$75>=$D60,Economics!$AM$75<=$E60),"X","") -> #N/A | K60: =IF(AND(Economics!$F$200=$B60,Economics!$F$203=$C60,Economics!$AN$75>=$D60,Economics!$AN$75<=$E60),"X","") -> #N/A | L60: 0.0875
B62: All Other Loan Purposes | C62: Retirement | D62: 0 | E62: 0.65 | F62: =IF(AND($P$6=$B62,$P$7=$C62,$P$8>=$D62,$P$8<=$E62),"X","") -> #DIV/0! | G62: =IF(AND(Economics!$F$200=$B62,Economics!$F$203=$C62,Economics!$AJ$75>=$D62,Economics!$AJ$75<=$E62),"X","") -> #N/A | H62: =IF(AND(Economics!$F$200=$B62,Economics!$F$203=$C62,Economics!$AK$75>=$D62,Economics!$AK$75<=$E62),"X","") -> #N/A | I62: =IF(AND(Economics!$F$200=$B62,Economics!$F$203=$C62,Economics!$AL$75>=$D62,Economics!$AL$75<=$E62),"X","") -> #N/A | J62: =IF(AND(Economics!$F$200=$B62,Economics!$F$203=$C62,Economics!$AM$75>=$D62,Economics!$AM$75<=$E62),"X","") -> #N/A | K62: =IF(AND(Economics!$F$200=$B62,Economics!$F$203=$C62,Economics!$AN$75>=$D62,Economics!$AN$75<=$E62),"X","") -> #N/A | L62: 0.063
B63: All Other Loan Purposes | C63: Retirement | D63: =E62+0.001% -> 0.65001 | E63: 0.7 | F63: =IF(AND($P$6=$B63,$P$7=$C63,$P$8>=$D63,$P$8<=$E63),"X","") -> #DIV/0! | G63: =IF(AND(Economics!$F$200=$B63,Economics!$F$203=$C63,Economics!$AJ$75>=$D63,Economics!$AJ$75<=$E63),"X","") -> #N/A | H63: =IF(AND(Economics!$F$200=$B63,Economics!$F$203=$C63,Economics!$AK$75>=$D63,Economics!$AK$75<=$E63),"X","") -> #N/A | I63: =IF(AND(Economics!$F$200=$B63,Economics!$F$203=$C63,Economics!$AL$75>=$D63,Economics!$AL$75<=$E63),"X","") -> #N/A | J63: =IF(AND(Economics!$F$200=$B63,Economics!$F$203=$C63,Economics!$AM$75>=$D63,Economics!$AM$75<=$E63),"X","") -> #N/A | K63: =IF(AND(Economics!$F$200=$B63,Economics!$F$203=$C63,Economics!$AN$75>=$D63,Economics!$AN$75<=$E63),"X","") -> #N/A | L63: 0.066
B64: All Other Loan Purposes | C64: Retirement | D64: =E63+0.001% -> 0.70001 | E64: 0.75 | F64: =IF(AND($P$6=$B64,$P$7=$C64,$P$8>=$D64,$P$8<=$E64),"X","") -> #DIV/0! | G64: =IF(AND(Economics!$F$200=$B64,Economics!$F$203=$C64,Economics!$AJ$75>=$D64,Economics!$AJ$75<=$E64),"X","") -> #N/A | H64: =IF(AND(Economics!$F$200=$B64,Economics!$F$203=$C64,Economics!$AK$75>=$D64,Economics!$AK$75<=$E64),"X","") -> #N/A | I64: =IF(AND(Economics!$F$200=$B64,Economics!$F$203=$C64,Economics!$AL$75>=$D64,Economics!$AL$75<=$E64),"X","") -> #N/A | J64: =IF(AND(Economics!$F$200=$B64,Economics!$F$203=$C64,Economics!$AM$75>=$D64,Economics!$AM$75<=$E64),"X","") -> #N/A | K64: =IF(AND(Economics!$F$200=$B64,Economics!$F$203=$C64,Economics!$AN$75>=$D64,Economics!$AN$75<=$E64),"X","") -> #N/A | L64: 0.069
B65: All Other Loan Purposes | C65: Retirement | D65: =E64+0.001% -> 0.75001 | E65: 0.8 | F65: =IF(AND($P$6=$B65,$P$7=$C65,$P$8>=$D65,$P$8<=$E65),"X","") -> #DIV/0! | G65: =IF(AND(Economics!$F$200=$B65,Economics!$F$203=$C65,Economics!$AJ$75>=$D65,Economics!$AJ$75<=$E65),"X","") -> #N/A | H65: =IF(AND(Economics!$F$200=$B65,Economics!$F$203=$C65,Economics!$AK$75>=$D65,Economics!$AK$75<=$E65),"X","") -> #N/A | I65: =IF(AND(Economics!$F$200=$B65,Economics!$F$203=$C65,Economics!$AL$75>=$D65,Economics!$AL$75<=$E65),"X","") -> #N/A | J65: =IF(AND(Economics!$F$200=$B65,Economics!$F$203=$C65,Economics!$AM$75>=$D65,Economics!$AM$75<=$E65),"X","") -> #N/A | K65: =IF(AND(Economics!$F$200=$B65,Economics!$F$203=$C65,Economics!$AN$75>=$D65,Economics!$AN$75<=$E65),"X","") -> #N/A | L65: 0.0705
B66: All Other Loan Purposes | C66: Retirement | D66: =E65+0.001% -> 0.80001 | E66: 0.85 | F66: =IF(AND($P$6=$B66,$P$7=$C66,$P$8>=$D66,$P$8<=$E66),"X","") -> #DIV/0! | G66: =IF(AND(Economics!$F$200=$B66,Economics!$F$203=$C66,Economics!$AJ$75>=$D66,Economics!$AJ$75<=$E66),"X","") -> #N/A | H66: =IF(AND(Economics!$F$200=$B66,Economics!$F$203=$C66,Economics!$AK$75>=$D66,Economics!$AK$75<=$E66),"X","") -> #N/A | I66: =IF(AND(Economics!$F$200=$B66,Economics!$F$203=$C66,Economics!$AL$75>=$D66,Economics!$AL$75<=$E66),"X","") -> #N/A | J66: =IF(AND(Economics!$F$200=$B66,Economics!$F$203=$C66,Economics!$AM$75>=$D66,Economics!$AM$75<=$E66),"X","") -> #N/A | K66: =IF(AND(Economics!$F$200=$B66,Economics!$F$203=$C66,Economics!$AN$75>=$D66,Economics!$AN$75<=$E66),"X","") -> #N/A | L66: 0.0775
B67: All Other Loan Purposes | C67: Retirement | D67: =E66+0.001% -> 0.85001 | E67: 0.9 | F67: =IF(AND($P$6=$B67,$P$7=$C67,$P$8>=$D67,$P$8<=$E67),"X","") -> #DIV/0! | G67: =IF(AND(Economics!$F$200=$B67,Economics!$F$203=$C67,Economics!$AJ$75>=$D67,Economics!$AJ$75<=$E67),"X","") -> #N/A | H67: =IF(AND(Economics!$F$200=$B67,Economics!$F$203=$C67,Economics!$AK$75>=$D67,Economics!$AK$75<=$E67),"X","") -> #N/A | I67: =IF(AND(Economics!$F$200=$B67,Economics!$F$203=$C67,Economics!$AL$75>=$D67,Economics!$AL$75<=$E67),"X","") -> #N/A | J67: =IF(AND(Economics!$F$200=$B67,Economics!$F$203=$C67,Economics!$AM$75>=$D67,Economics!$AM$75<=$E67),"X","") -> #N/A | K67: =IF(AND(Economics!$F$200=$B67,Economics!$F$203=$C67,Economics!$AN$75>=$D67,Economics!$AN$75<=$E67),"X","") -> #N/A | L67: 0.08
B68: All Other Loan Purposes | C68: Retirement | D68: =E67+0.001% -> 0.90001 | E68: 1 | F68: =IF(AND($P$6=$B68,$P$7=$C68,$P$8>=$D68,$P$8<=$E68),"X","") -> #DIV/0! | G68: =IF(AND(Economics!$F$200=$B68,Economics!$F$203=$C68,Economics!$AJ$75>=$D68,Economics!$AJ$75<=$E68),"X","") -> #N/A | H68: =IF(AND(Economics!$F$200=$B68,Economics!$F$203=$C68,Economics!$AK$75>=$D68,Economics!$AK$75<=$E68),"X","") -> #N/A | I68: =IF(AND(Economics!$F$200=$B68,Economics!$F$203=$C68,Economics!$AL$75>=$D68,Economics!$AL$75<=$E68),"X","") -> #N/A | J68: =IF(AND(Economics!$F$200=$B68,Economics!$F$203=$C68,Economics!$AM$75>=$D68,Economics!$AM$75<=$E68),"X","") -> #N/A | K68: =IF(AND(Economics!$F$200=$B68,Economics!$F$203=$C68,Economics!$AN$75>=$D68,Economics!$AN$75<=$E68),"X","") -> #N/A | L68: 0.0875
B72: DSC Ratios Table
B73: Search Term | C73: Housing Type | D73: Program Type | E73: Units | F73: 5-yr Resi DSC | G73: 10-yr Resi DSC | H73: 5-yr Comm DSC | I73: 10-yr Comm DSC
B74: =C74&D74&E74 -> Standard Rental HousingMLI MarketPopulate Rent Roll | C74: Standard Rental Housing | D74: MLI Market | E74: =$P$13 -> Populate Rent Roll | F74: 1.3 | G74: 1.2 | H74: 1.5 | I74: 1.4
B75: =C75&D75&E75 -> Standard Rental HousingMLI SelectPopulate Rent Roll | C75: Standard Rental Housing | D75: MLI Select | E75: =$P$13 -> Populate Rent Roll | F75: 1.1 | G75: 1.1 | H75: 1.4 | I75: 1.4
B76: =C76&D76&E76 -> StudentMLI Market7+ units | C76: Student | D76: MLI Market | E76: 7+ units | F76: 1.4 | G76: 1.3 | H76: 1.5 | I76: 1.4
B77: =C77&D77&E77 -> StudentMLI Market5 or 6 units | C77: Student | D77: MLI Market | E77: 5 or 6 units | F77: 1.2 | G77: 1.2 | H77: 1.5 | I77: 1.4
B78: =C78&D78&E78 -> StudentMLI SelectPopulate Rent Roll | C78: Student | D78: MLI Select | E78: =$P$13 -> Populate Rent Roll | F78: 1.2 | G78: 1.2 | H78: 1.4 | I78: 1.4
B79: =C79&D79&E79 -> SROMLI Market7+ units | C79: SRO | D79: MLI Market | E79: 7+ units | F79: 1.3 | G79: 1.2 | H79: 1.5 | I79: 1.4
B80: =C80&D80&E80 -> SROMLI Market5 or 6 units | C80: SRO | D80: MLI Market | E80: 5 or 6 units | F80: 1.2 | G80: 1.2 | H80: 1.5 | I80: 1.4
B81: =C81&D81&E81 -> SROMLI SelectPopulate Rent Roll | C81: SRO | D81: MLI Select | E81: =$P$13 -> Populate Rent Roll | F81: 1.2 | G81: 1.2 | H81: 1.4 | I81: 1.4
B82: =C82&D82&E82 -> RetirementMLI Market7+ units | C82: Retirement | D82: MLI Market | E82: 7+ units | F82: 1.5 | G82: 1.4 | H82: 1.5 | I82: 1.4
B83: =C83&D83&E83 -> RetirementMLI Market5 or 6 units | C83: Retirement | D83: MLI Market | E83: 5 or 6 units | F83: 1.2 | G83: 1.2 | H83: 1.5 | I83: 1.4
B84: =C84&D84&E84 -> RetirementMLI SelectPopulate Rent Roll | C84: Retirement | D84: MLI Select | E84: =$P$13 -> Populate Rent Roll | F84: 1.2 | G84: 1.2 | H84: 1.4 | I84: 1.4

Sheet BenchmarkBackEnd
D2: Expense Assumptions | E2: Ontario Region - Wood Frame | S2: Pre June 19 Benchmarks
A3: Region | B3: Frame | D3: Category | E3: $/Unit | F3: % EGI | G3: Comments | S3: Per Unit | T3: % EGI
A4: ON | B4: Wood Frame | C4: <N/A> | D4: (-) Property Taxes | E4: 0 | G4: Previous Benchmark $1,803 per unit or 14.4% of EGI | S4: 1968 | T4: 0.13
A5: ON | B5: Wood Frame | C5: <N/A> | D5: (-) Insurance | E5: 0 | G5: Previous Benchmart $265 per uint or 2.1% of EGI | S5: 300 | T5: 0.02
A6: ON | B6: Wood Frame | C6: <N/A> | D6: (-) Utilities | E6: 0 | S6: 1500 | T6: 0.099
A7: ON | B7: Wood Frame | C7: <N/A> | D7: (-) Repairs and Maintenance | E7: 830 | G7: Previous Benchmark $650-750 per unit | S7: 750 | T7: 0.051
A8: ON | B8: Wood Frame | C8: <N/A> | D8: (-) Payroll & Administration | E8: 555 | G8: Called "Salaries" on CMHC Benchmark Report | S8: 500 | T8: 0.033
A9: ON | B9: Wood Frame | C9: <N/A> | D9: (-) Marketing | G9: Included in Other Costs in CMHC Benchmark Report | S9: 0 | T9: 0
A10: ON | B10: Wood Frame | C10: <N/A> | D10: (-) Other | F10: 0.01 | G10: "Other Costs" incl. advertising, permits, garbage, snow, security etc. | S10: 151 | T10: 0.01
A11: ON | B11: Wood Frame | C11: <N/A> | D11: (-) Management Fee | F11: 0.0425 | G11: Benchmark based on EGI | S11: 605 | T11: 0.04
A12: ON | B12: Wood Frame | C12: <N/A> | D12: (-) Replacement Reserve | G12: Replacement reserve of $60 per appliance, $190 per AC unit, $300 per elevator per month | S12: 0 | T12: 0
A13: ON | B13: Wood Frame | C13: <N/A> | D13: Operating Expenses | G13: Previous Benchmark $4,821 per unit or 38.6% of EGI | S13: 5549 | T13: 0.367
D15: Expense Assumptions | E15: Ontario Region - Concrete | S15: Pre June 19 Benchmarks
D16: Category | E16: $/Unit | F16: % EGI | G16: Comments | S16: Per Unit | T16: % EGI
A17: ON | B17: Concrete Frame | C17: <N/A> | D17: (-) Property Taxes | E17: 0 | G17: Previous Benchmark $1,916 per unit or 13.3% of EGI | S17: 2105 | T17: 0.123
A18: ON | B18: Concrete Frame | C18: <N/A> | D18: (-) Insurance | E18: 0 | G18: Previous Benchmart $150 per uint or 1.0% of EGI | S18: 210 | T18: 0.012
A19: ON | B19: Concrete Frame | C19: <N/A> | D19: (-) Utilities | E19: 0 | S19: 1600 | T19: 0.093
A20: ON | B20: Concrete Frame | C20: <N/A> | D20: (-) Repairs and Maintenance | E20: 975 | G20: Previous Benchmark $850-950 per unit | S20: 900 | T20: 0.052
A21: ON | B21: Concrete Frame | C21: <N/A> | D21: (-) Payroll & Administration | E21: 700 | G21: Called "Salaries" on CMHC Benchmark Report | S21: 625 | T21: 0.036
A22: ON | B22: Concrete Frame | C22: <N/A> | D22: (-) Marketing | G22: Included in Other Costs in CMHC Benchmark Report | S22: 0 | T22: 0
A23: ON | B23: Concrete Frame | C23: <N/A> | D23: (-) Other | F23: 0.01 | G23: Called "Other Costs" incl. advertising, permits, garbage, snow, security etc. | S23: 171 | T23: 0.01
A24: ON | B24: Concrete Frame | C24: <N/A> | D24: (-) Management Fee | F24: 0.0425 | G24: Benchmark based on EGI | S24: 687 | T24: 0.04
A25: ON | B25: Concrete Frame | C25: <N/A> | D25: (-) Replacement Reserve | G25: Replacement reserve of $50 per appliance, $150 per AC unit | S25: 0 | T25: 0
A26: ON | B26: Concrete Frame | C26: <N/A> | D26: Operating Expenses | G26: Previous Benchmark $6,051 per unit or 35.5% of EGI | S26: 6098 | T26: 0.355
D28: Expense Assumptions | E28: BC Region - Wood Frame
D29: Category | E29: $/Unit | F29: % EGI | G29: Comments
A30: BC | B30: Wood Frame | C30: <N/A> | D30: (-) Property Taxes | E30: 0 | G30: Previous Benchmark $872 per unit or 6.4% of EGI | S30: 1095 | T30: 0.064
A31: BC | B31: Wood Frame | C31: <N/A> | D31: (-) Insurance | E31: 0 | G31: Previous Benchmart $340 per uint or 2.6% of EGI | S31: 425 | T31: 0.025
A32: BC | B32: Wood Frame | C32: <N/A> | D32: (-) Utilities | E32: 0 | S32: 915 | T32: 0.054
A33: BC | B33: Wood Frame | C33: <N/A> | D33: (-) Repairs and Maintenance | E33: 830 | G33: Previous Benchmark $650-750 per unit | S33: 750 | T33: 0.044
A34: BC | B34: Wood Frame | C34: <N/A> | D34: (-) Payroll & Administration | E34: 635 | G34: Called "Salaries" on CMHC Benchmark Report | S34: 575 | T34: 0.034
A35: BC | B35: Wood Frame | C35: <N/A> | D35: (-) Marketing | G35: Included in Other Costs in CMHC Benchmark Report | S35: 0 | T35: 0
A36: BC | B36: Wood Frame | C36: <N/A> | D36: (-) Other | F36: 0.017 | G36: Called "Other Costs" incl. advertising, permits, garbage, snow, security etc. | S36: 291 | T36: 0.017
A37: BC | B37: Wood Frame | C37: <N/A> | D37: (-) Management Fee | F37: 0.0425 | G37: Benchmark based on EGI | S37: 683 | T37: 0.04
A38: BC | B38: Wood Frame | C38: <N/A> | D38: (-) Replacement Reserve | G38: Replacement reserve of $50 per appliance, $150 per AC unit, $250 per elevator per month | S38: 0 | T38: 0
A39: BC | B39: Wood Frame | C39: <N/A> | D39: Operating Expenses | G39: Previous Benchmark $3,885 per unit or 30.3% of EGI | S39: 4734 | T39: 0.278
D41: Expense Assumptions | E41: BC Region - Concrete Frame
D42: Category | E42: $/Unit | F42: % EGI | G42: Comments
A43: BC | B43: Concrete Frame | C43: <N/A> | D43: (-) Property Taxes | E43: 0 | S43: 1465 | T43: 0.069
A44: BC | B44: Concrete Frame | C44: <N/A> | D44: (-) Insurance | E44: 0 | S44: 285 | T44: 0.013
A45: BC | B45: Concrete Frame | C45: <N/A> | D45: (-) Utilities | E45: 0 | S45: 1000 | T45: 0.047
A46: BC | B46: Concrete Frame | C46: <N/A> | D46: (-) Repairs and Maintenance | E46: 975 | S46: 900 | T46: 0.042
A47: BC | B47: Concrete Frame | C47: <N/A> | D47: (-) Payroll & Administration | E47: 700 | S47: 625 | T47: 0.029
A48: BC | B48: Concrete Frame | C48: <N/A> | D48: (-) Marketing | S48: 0 | T48: 0
A49: BC | B49: Concrete Frame | C49: <N/A> | D49: (-) Other | F49: 0.018 | S49: 382 | T49: 0.018
A50: BC | B50: Concrete Frame | C50: <N/A> | D50: (-) Management Fee | F50: 0.0425 | S50: 850 | T50: 0.04
A51: BC | B51: Concrete Frame | C51: <N/A> | D51: (-) Replacement Reserve | S51: 0 | T51: 0
A52: BC | B52: Concrete Frame | C52: <N/A> | D52: Operating Expenses | S52: 5507 | T52: 0.259
D54: Expense Assumptions | E54: Atlantic Region - Wood Frame
D55: Category | E55: $/Unit | F55: % EGI | G55: Comments
A56: Atlantic | B56: Wood Frame | C56: <N/A> | D56: (-) Property Taxes | E56: 0 | S56: 1278 | T56: 0.11
A57: Atlantic | B57: Wood Frame | C57: <N/A> | D57: (-) Insurance | E57: 0 | S57: 250 | T57: 0.021
A58: Atlantic | B58: Wood Frame | C58: <N/A> | D58: (-) Utilities | E58: 0 | S58: 1350 | T58: 0.116
A59: Atlantic | B59: Wood Frame | C59: <N/A> | D59: (-) Repairs and Maintenance | E59: 610 | S59: 550 | T59: 0.047
A60: Atlantic | B60: Wood Frame | C60: <N/A> | D60: (-) Payroll & Administration | E60: 420 | S60: 380 | T60: 0.033
A61: Atlantic | B61: Wood Frame | C61: <N/A> | D61: (-) Marketing | S61: 0 | T61: 0
A62: Atlantic | B62: Wood Frame | C62: <N/A> | D62: (-) Other | F62: 0.01 | S62: 117 | T62: 0.01
A63: Atlantic | B63: Wood Frame | C63: <N/A> | D63: (-) Management Fee | F63: 0.0425 | S63: 466 | T63: 0.04
A64: Atlantic | B64: Wood Frame | C64: <N/A> | D64: (-) Replacement Reserve | S64: 0 | T64: 0
A65: Atlantic | B65: Wood Frame | C65: <N/A> | D65: Operating Expenses | S65: 4391 | T65: 0.377
D67: Expense Assumptions | E67: Atlantic Region - Concrete Frame
D68: Category | E68: $/Unit | F68: % EGI | G68: Comments
A69: Atlantic | B69: Concrete Frame | C69: <N/A> | D69: (-) Property Taxes | E69: 0 | S69: 2283 | T69: 0.124
A70: Atlantic | B70: Concrete Frame | C70: <N/A> | D70: (-) Insurance | E70: 0 | S70: 175 | T70: 0.01
A71: Atlantic | B71: Concrete Frame | C71: <N/A> | D71: (-) Utilities | E71: 0 | S71: 1350 | T71: 0.073
A72: Atlantic | B72: Concrete Frame | C72: <N/A> | D72: (-) Repairs and Maintenance | E72: 825 | S72: 750 | T72: 0.04
A73: Atlantic | B73: Concrete Frame | C73: <N/A> | D73: (-) Payroll & Administration | E73: 610 | S73: 550 | T73: 0.029
A74: Atlantic | B74: Concrete Frame | C74: <N/A> | D74: (-) Marketing | S74: 0 | T74: 0
A75: Atlantic | B75: Concrete Frame | C75: <N/A> | D75: (-) Other | F75: 0.013 | S75: 239 | T75: 0.013
A76: Atlantic | B76: Concrete Frame | C76: <N/A> | D76: (-) Management Fee | F76: 0.0425 | S76: 737 | T76: 0.04
A77: Atlantic | B77: Concrete Frame | C77: <N/A> | D77: (-) Replacement Reserve | S77: 0 | T77: 0
A78: Atlantic | B78: Concrete Frame | C78: <N/A> | D78: Operating Expenses | S78: 6059 | T78: 0.329
D80: Expense Assumptions | E80: Prairie Region - Wood Frame
D81: Category | E81: $/Unit | F81: % EGI | G81: Comments
A82: Prairies & Territories | B82: Wood Frame | C82: <N/A> | D82: (-) Property Taxes | E82: 0 | S82: 1340 | T82: 0.083
A83: Prairies & Territories | B83: Wood Frame | C83: <N/A> | D83: (-) Insurance | E83: 0 | S83: 300 | T83: 0.019
A84: Prairies & Territories | B84: Wood Frame | C84: <N/A> | D84: (-) Utilities | E84: 0 | S84: 1250 | T84: 0.077
A85: Prairies & Territories | B85: Wood Frame | C85: <N/A> | D85: (-) Repairs and Maintenance | E85: 830 | S85: 750 | T85: 0.046
A86: Prairies & Territories | B86: Wood Frame | C86: <N/A> | D86: (-) Payroll & Administration | E86: 500 | S86: 450 | T86: 0.028
A87: Prairies & Territories | B87: Wood Frame | C87: <N/A> | D87: (-) Marketing | S87: 0 | T87: 0
A88: Prairies & Territories | B88: Wood Frame | C88: <N/A> | D88: (-) Other | F88: 0.02 | S88: 324 | T88: 0.02
A89: Prairies & Territories | B89: Wood Frame | C89: <N/A> | D89: (-) Management Fee | F89: 0.0425 | S89: 648 | T89: 0.04
A90: Prairies & Territories | B90: Wood Frame | C90: <N/A> | D90: (-) Replacement Reserve | S90: 0 | T90: 0
A91: Prairies & Territories | B91: Wood Frame | C91: <N/A> | D91: Operating Expenses | S91: 5062 | T91: 0.313
D93: Expense Assumptions | E93: Prairie Region - Concrete Frame
D94: Category | E94: $/Unit | F94: % EGI | G94: Comments
A95: Prairies & Territories | B95: Concrete Frame | C95: <N/A> | D95: (-) Property Taxes | E95: 0 | S95: 1675 | T95: 0.105
A96: Prairies & Territories | B96: Concrete Frame | C96: <N/A> | D96: (-) Insurance | E96: 0 | S96: 225 | T96: 0.014
A97: Prairies & Territories | B97: Concrete Frame | C97: <N/A> | D97: (-) Utilities | E97: 0 | S97: 1300 | T97: 0.056
A98: Prairies & Territories | B98: Concrete Frame | C98: <N/A> | D98: (-) Repairs and Maintenance | E98: 975 | S98: 900 | T98: 0.056
A99: Prairies & Territories | B99: Concrete Frame | C99: <N/A> | D99: (-) Payroll & Administration | E99: 665 | S99: 600 | T99: 0.038
A100: Prairies & Territories | B100: Concrete Frame | C100: <N/A> | D100: (-) Marketing | S100: 0 | T100: 0
A101: Prairies & Territories | B101: Concrete Frame | C101: <N/A> | D101: (-) Other | F101: 0.02 | S101: 319 | T101: 0.02
A102: Prairies & Territories | B102: Concrete Frame | C102: <N/A> | D102: (-) Management Fee | F102: 0.0425 | S102: 718 | T102: 0.045
A103: Prairies & Territories | B103: Concrete Frame | C103: <N/A> | D103: (-) Replacement Reserve | S103: 0 | T103: 0
A104: Prairies & Territories | B104: Concrete Frame | C104: <N/A> | D104: Operating Expenses | S104: 5737 | T104: 0.36
D106: Expense Assumptions | E106: Quebec Region - Wood Frame - 11 units and less
D107: Category | E107: $/Unit | F107: % EGI | G107: Comments
A108: QC | B108: Wood Frame | C108: 11 units and less | D108: (-) Property Taxes | E108: 0 | S108: 1125 | T108: 0.119
A109: QC | B109: Wood Frame | C109: 11 units and less | D109: (-) Insurance | E109: 0 | S109: 415 | T109: 0.049
...

Sheet Rent Roll
N1: Vacant | P1: Occupied (Market Units)
C2: In-Place / Proforma Rents for Term Loan | G2: Occupied | H2: Units | I2: Size | J2: Total | K2: Per Unit | L2: PSF | N2: Max | O2: Avg | P2: Max | Q2: Avg | S2: Unit Code | T2: Unit Type
C3: Bachelor | G3: =IFERROR(COUNTIFS($C$30:$C$984,$C3,$I$30:$I$984,"Yes",$E$30:$E$984,"No"),"-") -> 0 | H3: =IFERROR(COUNTIFS($C$30:$C$984,$C3,$I$30:$I$984,"Yes"),"-") -> 0 | I3: =IFERROR(AVERAGEIFS($H$30:$H$984,$C$30:$C$984,$C3,$I$30:$I$984,"Yes"),"-") -> - | J3: =IFERROR(SUMIFS($F$30:$F$984,$C$30:$C$984,$C3,$I$30:$I$984,"Yes")*12,0) -> 0 | K3: =IFERROR(+J3/H3/12,"-") -> - | L3: =IFERROR(+K3/I3,"-") -> - | N3: =_xlfn.MAXIFS($F$30:$F$1048576,$C$30:$C$1048576,C3,$E$30:$E$1048576,"=Yes",$I$30:$I$1048576,"=Yes") -> 0 | O3: =IFERROR(AVERAGEIFS($F$30:$F$1048576,$C$30:$C$1048576,C3,$E$30:$E$1048576,"=Yes",$I$30:$I$1048576,"=Yes"),0) -> 0 | P3: =_xlfn.MAXIFS($F$30:$F$1048576,$C$30:$C$1048576,C3,$E$30:$E$1048576,"=No",$I$30:$I$1048576,"=Yes") -> 0 | Q3: =IFERROR(AVERAGEIFS($F$30:$F$1048576,$C$30:$C$1048576,C3,$E$30:$E$1048576,"=No",$I$30:$I$1048576,"=Yes"),0) -> 0 | S3: 0 | T3: Bachelor
C4: 1 Bedroom | G4: =IFERROR(COUNTIFS($C$30:$C$984,$C4,$I$30:$I$984,"Yes",$E$30:$E$984,"No"),"-") -> 0 | H4: =IFERROR(COUNTIFS($C$30:$C$984,$C4,$I$30:$I$984,"Yes"),"-") -> 0 | I4: =IFERROR(AVERAGEIFS($H$30:$H$984,$C$30:$C$984,$C4,$I$30:$I$984,"Yes"),"-") -> - | J4: =IFERROR(SUMIFS($F$30:$F$984,$C$30:$C$984,$C4,$I$30:$I$984,"Yes")*12,0) -> 0 | K4: =IFERROR(+J4/H4/12,"-") -> - | L4: =IFERROR(+K4/I4,"-") -> - | N4: =_xlfn.MAXIFS($F$30:$F$1048576,$C$30:$C$1048576,C4,$E$30:$E$1048576,"=Yes",$I$30:$I$1048576,"=Yes") -> 0 | O4: =IFERROR(AVERAGEIFS($F$30:$F$1048576,$C$30:$C$1048576,C4,$E$30:$E$1048576,"=Yes",$I$30:$I$1048576,"=Yes"),0) -> 0 | P4: =_xlfn.MAXIFS($F$30:$F$1048576,$C$30:$C$1048576,C4,$E$30:$E$1048576,"=No",$I$30:$I$1048576,"=Yes") -> 0 | Q4: =IFERROR(AVERAGEIFS($F$30:$F$1048576,$C$30:$C$1048576,C4,$E$30:$E$1048576,"=No",$I$30:$I$1048576,"=Yes"),0) -> 0 | S4: 1 | T4: 1 Bedroom
C5: 2 Bedrooms | G5: =IFERROR(COUNTIFS($C$30:$C$984,$C5,$I$30:$I$984,"Yes",$E$30:$E$984,"No"),"-") -> 0 | H5: =IFERROR(COUNTIFS($C$30:$C$984,$C5,$I$30:$I$984,"Yes"),"-") -> 0 | I5: =IFERROR(AVERAGEIFS($H$30:$H$984,$C$30:$C$984,$C5,$I$30:$I$984,"Yes"),"-") -> - | J5: =IFERROR(SUMIFS($F$30:$F$984,$C$30:$C$984,$C5,$I$30:$I$984,"Yes")*12,0) -> 0 | K5: =IFERROR(+J5/H5/12,"-") -> - | L5: =IFERROR(+K5/I5,"-") -> - | N5: =_xlfn.MAXIFS($F$30:$F$1048576,$C$30:$C$1048576,C5,$E$30:$E$1048576,"=Yes",$I$30:$I$1048576,"=Yes") -> 0 | O5: =IFERROR(AVERAGEIFS($F$30:$F$1048576,$C$30:$C$1048576,C5,$E$30:$E$1048576,"=Yes",$I$30:$I$1048576,"=Yes"),0) -> 0 | P5: =_xlfn.MAXIFS($F$30:$F$1048576,$C$30:$C$1048576,C5,$E$30:$E$1048576,"=No",$I$30:$I$1048576,"=Yes") -> 0 | Q5: =IFERROR(AVERAGEIFS($F$30:$F$1048576,$C$30:$C$1048576,C5,$E$30:$E$1048576,"=No",$I$30:$I$1048576,"=Yes"),0) -> 0 | S5: 2 | T5: 2 Bedrooms
C6: 3 Bedrooms | G6: =IFERROR(COUNTIFS($C$30:$C$984,$C6,$I$30:$I$984,"Yes",$E$30:$E$984,"No"),"-") -> 0 | H6: =IFERROR(COUNTIFS($C$30:$C$984,$C6,$I$30:$I$984,"Yes"),"-") -> 0 | I6: =IFERROR(AVERAGEIFS($H$30:$H$984,$C$30:$C$984,$C6,$I$30:$I$984,"Yes"),"-") -> - | J6: =IFERROR(SUMIFS($F$30:$F$984,$C$30:$C$984,$C6,$I$30:$I$984,"Yes")*12,0) -> 0 | K6: =IFERROR(+J6/H6/12,"-") -> - | L6: =IFERROR(+K6/I6,"-") -> - | N6: =_xlfn.MAXIFS($F$30:$F$1048576,$C$30:$C$1048576,C6,$E$30:$E$1048576,"=Yes",$I$30:$I$1048576,"=Yes") -> 0 | O6: =IFERROR(AVERAGEIFS($F$30:$F$1048576,$C$30:$C$1048576,C6,$E$30:$E$1048576,"=Yes",$I$30:$I$1048576,"=Yes"),0) -> 0 | P6: =_xlfn.MAXIFS($F$30:$F$1048576,$C$30:$C$1048576,C6,$E$30:$E$1048576,"=No",$I$30:$I$1048576,"=Yes") -> 0 | Q6: =IFERROR(AVERAGEIFS($F$30:$F$1048576,$C$30:$C$1048576,C6,$E$30:$E$1048576,"=No",$I$30:$I$1048576,"=Yes"),0) -> 0 | S6: 3 | T6: 3 Bedrooms
C7: 4+ Bedrooms | G7: =IFERROR(COUNTIFS($C$30:$C$984,$C7,$I$30:$I$984,"Yes",$E$30:$E$984,"No"),"-") -> 0 | H7: =IFERROR(COUNTIFS($C$30:$C$984,$C7,$I$30:$I$984,"Yes"),"-") -> 0 | I7: =IFERROR(AVERAGEIFS($H$30:$H$984,$C$30:$C$984,$C7,$I$30:$I$984,"Yes"),"-") -> - | J7: =IFERROR(SUMIFS($F$30:$F$984,$C$30:$C$984,$C7,$I$30:$I$984,"Yes")*12,0) -> 0 | K7: =IFERROR(+J7/H7/12,"-") -> - | L7: =IFERROR(+K7/I7,"-") -> - | N7: =_xlfn.MAXIFS($F$30:$F$1048576,$C$30:$C$1048576,C7,$E$30:$E$1048576,"=Yes",$I$30:$I$1048576,"=Yes") -> 0 | O7: =IFERROR(AVERAGEIFS($F$30:$F$1048576,$C$30:$C$1048576,C7,$E$30:$E$1048576,"=Yes",$I$30:$I$1048576,"=Yes"),0) -> 0 | P7: =_xlfn.MAXIFS($F$30:$F$1048576,$C$30:$C$1048576,C7,$E$30:$E$1048576,"=No",$I$30:$I$1048576,"=Yes") -> 0 | Q7: =IFERROR(AVERAGEIFS($F$30:$F$1048576,$C$30:$C$1048576,C7,$E$30:$E$1048576,"=No",$I$30:$I$1048576,"=Yes"),0) -> 0 | S7: 4 | T7: 4+ Bedrooms
C8: Bachelor (Affordable) | G8: =IFERROR(COUNTIFS($C$30:$C$984,$C3,$I$30:$I$984,"No",$E$30:$E$984,"No"),"-") -> 0 | H8: =IFERROR(COUNTIFS($C$30:$C$984,$C3,$I$30:$I$984,"No"),"-") -> 0 | I8: =IFERROR(AVERAGEIFS($H$30:$H$984,$C$30:$C$984,$C3,$I$30:$I$984,"No"),"-") -> - | J8: =IFERROR(SUMIFS($F$30:$F$984,$C$30:$C$984,$C3,$I$30:$I$984,"No")*12,0) -> 0 | K8: =IFERROR(+J8/H8/12,"-") -> - | L8: =IFERROR(+K8/I8,"-") -> -
C9: 1 Bedroom (Affordable) | G9: =IFERROR(COUNTIFS($C$30:$C$984,$C4,$I$30:$I$984,"No",$E$30:$E$984,"No"),"-") -> 0 | H9: =IFERROR(COUNTIFS($C$30:$C$984,$C4,$I$30:$I$984,"No"),"-") -> 0 | I9: =IFERROR(AVERAGEIFS($H$30:$H$984,$C$30:$C$984,$C4,$I$30:$I$984,"No"),"-") -> - | J9: =IFERROR(SUMIFS($F$30:$F$984,$C$30:$C$984,$C4,$I$30:$I$984,"No")*12,0) -> 0 | K9: =IFERROR(+J9/H9/12,"-") -> - | L9: =IFERROR(+K9/I9,"-") -> -
C10: 2 Bedrooms (Affordable) | G10: =IFERROR(COUNTIFS($C$30:$C$984,$C5,$I$30:$I$984,"No",$E$30:$E$984,"No"),"-") -> 0 | H10: =IFERROR(COUNTIFS($C$30:$C$984,$C5,$I$30:$I$984,"No"),"-") -> 0 | I10: =IFERROR(AVERAGEIFS($H$30:$H$984,$C$30:$C$984,$C5,$I$30:$I$984,"No"),"-") -> - | J10: =IFERROR(SUMIFS($F$30:$F$984,$C$30:$C$984,$C5,$I$30:$I$984,"No")*12,0) -> 0 | K10: =IFERROR(+J10/H10/12,"-") -> - | L10: =IFERROR(+K10/I10,"-") -> -
C11: 3 Bedrooms (Affordable) | G11: =IFERROR(COUNTIFS($C$30:$C$984,$C6,$I$30:$I$984,"No",$E$30:$E$984,"No"),"-") -> 0 | H11: =IFERROR(COUNTIFS($C$30:$C$984,$C6,$I$30:$I$984,"No"),"-") -> 0 | I11: =IFERROR(AVERAGEIFS($H$30:$H$984,$C$30:$C$984,$C6,$I$30:$I$984,"No"),"-") -> - | J11: =IFERROR(SUMIFS($F$30:$F$984,$C$30:$C$984,$C6,$I$30:$I$984,"No")*12,0) -> 0 | K11: =IFERROR(+J11/H11/12,"-") -> - | L11: =IFERROR(+K11/I11,"-") -> -
C12: 4+ Bedrooms (Affordable) | G12: =IFERROR(COUNTIFS($C$30:$C$984,$C7,$I$30:$I$984,"No",$E$30:$E$984,"No"),"-") -> 0 | H12: =IFERROR(COUNTIFS($C$30:$C$984,$C7,$I$30:$I$984,"No"),"-") -> 0 | I12: =IFERROR(AVERAGEIFS($H$30:$H$984,$C$30:$C$984,$C7,$I$30:$I$984,"No"),"-") -> - | J12: =IFERROR(SUMIFS($F$30:$F$984,$C$30:$C$984,$C7,$I$30:$I$984,"No")*12,0) -> 0 | K12: =IFERROR(+J12/H12/12,"-") -> - | L12: =IFERROR(+K12/I12,"-") -> -
C13: Total Rental Income | G13: =SUM(G3:G12) -> 0 | H13: =SUM(H3:H12) -> 0 | I13: =IFERROR(SUMPRODUCT($I$3:$I$12,$H$3:$H$12)/H13,"-") -> - | J13: =SUM(J3:J12) -> 0 | K13: =IFERROR(J13/H13/12,"-") -> - | L13: =IFERROR(+K13/I13,"-") -> -
N14: Vacant
C15: Adjusted Rents for Construction Loan | G15: Occupied | H15: Units | I15: Size | J15: Total | K15: Per Unit | L15: PSF | N15: Max | O15: Avg | P15: Z
C16: Bachelor | G16: =IFERROR(COUNTIFS($C$30:$C$984,$C16,$I$30:$I$984,"Yes",$E$30:$E$984,"No"),"-") -> 0 | H16: =IFERROR(COUNTIFS($C$30:$C$984,$C16,$I$30:$I$984,"Yes"),"-") -> 0 | I16: =IFERROR(AVERAGEIFS($H$30:$H$984,$C$30:$C$984,$C16,$I$30:$I$984,"Yes"),"-") -> - | J16: =IFERROR(SUMIFS($G$30:$G$984,$C$30:$C$984,$C16,$I$30:$I$984,"Yes")*12,0) -> 0 | K16: =IFERROR(+J16/H16/12,"-") -> - | L16: =IFERROR(+K16/I16,"-") -> - | N16: =_xlfn.MAXIFS($G$30:$G$1048576,$C$30:$C$1048576,C16,$E$30:$E$1048576,"=Yes",$I$30:$I$1048576,"=Yes") -> 0 | O16: =IFERROR(AVERAGEIFS($G$30:$G$1048576,$C$30:$C$1048576,C16,$E$30:$E$1048576,"=Yes",$I$30:$I$1048576,"=Yes"),0) -> 0
C17: 1 Bedroom | G17: =IFERROR(COUNTIFS($C$30:$C$984,$C17,$I$30:$I$984,"Yes",$E$30:$E$984,"No"),"-") -> 0 | H17: =IFERROR(COUNTIFS($C$30:$C$984,$C17,$I$30:$I$984,"Yes"),"-") -> 0 | I17: =IFERROR(AVERAGEIFS($H$30:$H$984,$C$30:$C$984,$C17,$I$30:$I$984,"Yes"),"-") -> - | J17: =IFERROR(SUMIFS($G$30:$G$984,$C$30:$C$984,$C17,$I$30:$I$984,"Yes")*12,0) -> 0 | K17: =IFERROR(+J17/H17/12,"-") -> - | L17: =IFERROR(+K17/I17,"-") -> - | N17: =_xlfn.MAXIFS($G$30:$G$1048576,$C$30:$C$1048576,C17,$E$30:$E$1048576,"=Yes",$I$30:$I$1048576,"=Yes") -> 0 | O17: =IFERROR(AVERAGEIFS($G$30:$G$1048576,$C$30:$C$1048576,C17,$E$30:$E$1048576,"=Yes",$I$30:$I$1048576,"=Yes"),0) -> 0
C18: 2 Bedrooms | G18: =IFERROR(COUNTIFS($C$30:$C$984,$C18,$I$30:$I$984,"Yes",$E$30:$E$984,"No"),"-") -> 0 | H18: =IFERROR(COUNTIFS($C$30:$C$984,$C18,$I$30:$I$984,"Yes"),"-") -> 0 | I18: =IFERROR(AVERAGEIFS($H$30:$H$984,$C$30:$C$984,$C18,$I$30:$I$984,"Yes"),"-") -> - | J18: =IFERROR(SUMIFS($G$30:$G$984,$C$30:$C$984,$C18,$I$30:$I$984,"Yes")*12,0) -> 0 | K18: =IFERROR(+J18/H18/12,"-") -> - | L18: =IFERROR(+K18/I18,"-") -> - | N18: =_xlfn.MAXIFS($G$30:$G$1048576,$C$30:$C$1048576,C18,$E$30:$E$1048576,"=Yes",$I$30:$I$1048576,"=Yes") -> 0 | O18: =IFERROR(AVERAGEIFS($G$30:$G$1048576,$C$30:$C$1048576,C18,$E$30:$E$1048576,"=Yes",$I$30:$I$1048576,"=Yes"),0) -> 0
C19: 3 Bedrooms | G19: =IFERROR(COUNTIFS($C$30:$C$984,$C19,$I$30:$I$984,"Yes",$E$30:$E$984,"No"),"-") -> 0 | H19: =IFERROR(COUNTIFS($C$30:$C$984,$C19,$I$30:$I$984,"Yes"),"-") -> 0 | I19: =IFERROR(AVERAGEIFS($H$30:$H$984,$C$30:$C$984,$C19,$I$30:$I$984,"Yes"),"-") -> - | J19: =IFERROR(SUMIFS($G$30:$G$984,$C$30:$C$984,$C19,$I$30:$I$984,"Yes")*12,0) -> 0 | K19: =IFERROR(+J19/H19/12,"-") -> - | L19: =IFERROR(+K19/I19,"-") -> - | N19: =_xlfn.MAXIFS($G$30:$G$1048576,$C$30:$C$1048576,C19,$E$30:$E$1048576,"=Yes",$I$30:$I$1048576,"=Yes") -> 0 | O19: =IFERROR(AVERAGEIFS($G$30:$G$1048576,$C$30:$C$1048576,C19,$E$30:$E$1048576,"=Yes",$I$30:$I$1048576,"=Yes"),0) -> 0
C20: 4+ Bedrooms | G20: =IFERROR(COUNTIFS($C$30:$C$984,$C20,$I$30:$I$984,"Yes",$E$30:$E$984,"No"),"-") -> 0 | H20: =IFERROR(COUNTIFS($C$30:$C$984,$C20,$I$30:$I$984,"Yes"),"-") -> 0 | I20: =IFERROR(AVERAGEIFS($H$30:$H$984,$C$30:$C$984,$C20,$I$30:$I$984,"Yes"),"-") -> - | J20: =IFERROR(SUMIFS($G$30:$G$984,$C$30:$C$984,$C20,$I$30:$I$984,"Yes")*12,0) -> 0 | K20: =IFERROR(+J20/H20/12,"-") -> - | L20: =IFERROR(+K20/I20,"-") -> - | N20: =_xlfn.MAXIFS($G$30:$G$1048576,$C$30:$C$1048576,C20,$E$30:$E$1048576,"=Yes",$I$30:$I$1048576,"=Yes") -> 0 | O20: =IFERROR(AVERAGEIFS($G$30:$G$1048576,$C$30:$C$1048576,C20,$E$30:$E$1048576,"=Yes",$I$30:$I$1048576,"=Yes"),0) -> 0
C21: Bachelor (Affordable) | G21: =IFERROR(COUNTIFS($C$30:$C$984,$C16,$I$30:$I$984,"No",$E$30:$E$984,"No"),"-") -> 0 | H21: =IFERROR(COUNTIFS($C$30:$C$984,$C16,$I$30:$I$984,"No"),"-") -> 0 | I21: =IFERROR(AVERAGEIFS($H$30:$H$984,$C$30:$C$984,$C16,$I$30:$I$984,"No"),"-") -> - | J21: =IFERROR(SUMIFS($G$30:$G$984,$C$30:$C$984,$C16,$I$30:$I$984,"No")*12,0) -> 0 | K21: =IFERROR(+J21/H21/12,"-") -> - | L21: =IFERROR(+K21/I21,"-") -> -
C22: 1 Bedroom (Affordable) | G22: =IFERROR(COUNTIFS($C$30:$C$984,$C17,$I$30:$I$984,"No",$E$30:$E$984,"No"),"-") -> 0 | H22: =IFERROR(COUNTIFS($C$30:$C$984,$C17,$I$30:$I$984,"No"),"-") -> 0 | I22: =IFERROR(AVERAGEIFS($H$30:$H$984,$C$30:$C$984,$C17,$I$30:$I$984,"No"),"-") -> - | J22: =IFERROR(SUMIFS($G$30:$G$984,$C$30:$C$984,$C17,$I$30:$I$984,"No")*12,0) -> 0 | K22: =IFERROR(+J22/H22/12,"-") -> - | L22: =IFERROR(+K22/I22,"-") -> -
C23: 2 Bedrooms (Affordable) | G23: =IFERROR(COUNTIFS($C$30:$C$984,$C18,$I$30:$I$984,"No",$E$30:$E$984,"No"),"-") -> 0 | H23: =IFERROR(COUNTIFS($C$30:$C$984,$C18,$I$30:$I$984,"No"),"-") -> 0 | I23: =IFERROR(AVERAGEIFS($H$30:$H$984,$C$30:$C$984,$C18,$I$30:$I$984,"No"),"-") -> - | J23: =IFERROR(SUMIFS($G$30:$G$984,$C$30:$C$984,$C18,$I$30:$I$984,"No")*12,0) -> 0 | K23: =IFERROR(+J23/H23/12,"-") -> - | L23: =IFERROR(+K23/I23,"-") -> -
C24: 3 Bedrooms (Affordable) | G24: =IFERROR(COUNTIFS($C$30:$C$984,$C19,$I$30:$I$984,"No",$E$30:$E$984,"No"),"-") -> 0 | H24: =IFERROR(COUNTIFS($C$30:$C$984,$C19,$I$30:$I$984,"No"),"-") -> 0 | I24: =IFERROR(AVERAGEIFS($H$30:$H$984,$C$30:$C$984,$C19,$I$30:$I$984,"No"),"-") -> - | J24: =IFERROR(SUMIFS($G$30:$G$984,$C$30:$C$984,$C19,$I$30:$I$984,"No")*12,0) -> 0 | K24: =IFERROR(+J24/H24/12,"-") -> - | L24: =IFERROR(+K24/I24,"-") -> -
C25: 4+ Bedrooms (Affordable) | G25: =IFERROR(COUNTIFS($C$30:$C$984,$C20,$I$30:$I$984,"No",$E$30:$E$984,"No"),"-") -> 0 | H25: =IFERROR(COUNTIFS($C$30:$C$984,$C20,$I$30:$I$984,"No"),"-") -> 0 | I25: =IFERROR(AVERAGEIFS($H$30:$H$984,$C$30:$C$984,$C20,$I$30:$I$984,"No"),"-") -> - | J25: =IFERROR(SUMIFS($G$30:$G$984,$C$30:$C$984,$C20,$I$30:$I$984,"No")*12,0) -> 0 | K25: =IFERROR(+J25/H25/12,"-") -> - | L25: =IFERROR(+K25/I25,"-") -> -
C26: Total Rental Income | G26: =SUM(G16:G25) -> 0 | H26: =SUM(H16:H25) -> 0 | I26: =IFERROR(SUMPRODUCT($I$3:$I$12,$H$3:$H$12)/H26,"-") -> - | J26: =SUM(J16:J25) -> 0 | K26: =IFERROR(J26/H26/12,"-") -> - | L26: =IFERROR(+K26/I26,"-") -> -
C28: Unit Details (start with Unit #, Rental Rate or Unit Size) | I28: Unit Designations? | M28: What's included in the unit/rent?
B29: Unit Code | C29: Unit Type | D29: Unit # | E29: Vacant? | F29: Rent | G29: Adjusted Rent | H29: Unit Size (sq ft) | I29: Market Unit | J29: Affordable Unit | K29: Subsidized Unit | L29: Care Services? | M29: Bulk Lease Unit | N29: Den Included Unit | O29: Second Bathroom | P29: Heating | Q29: Electricity | R29: Water | S29: Washer/Dryer | T29: Stove/Fridge | U29: Dishwasher | V29: Parking | W29: Furniture | X29: Other
C30: =+IF(ISBLANK(B30),"",IFERROR(INDEX($T$3:$T$7,MATCH(B30,$S$3:$S$7,0)),"")) | G30: =+IF(ISBLANK(F30),"",IF(J30="Yes",F30,F30*(1+Economics!$AK$29))) | J30: =+IF(ISBLANK(I30),"",IF(ISNUMBER(FIND("Yes",I30)),"No","Yes"))
C31: =+IF(ISBLANK(B31),"",IFERROR(INDEX($T$3:$T$7,MATCH(B31,$S$3:$S$7,0)),"")) | G31: =+IF(ISBLANK(F31),"",IF(J31="Yes",F31,F31*(1+Economics!$AK$29))) | J31: =+IF(ISBLANK(I31),"",IF(ISNUMBER(FIND("Yes",I31)),"No","Yes"))
C32: =+IF(ISBLANK(B32),"",IFERROR(INDEX($T$3:$T$7,MATCH(B32,$S$3:$S$7,0)),"")) | G32: =+IF(ISBLANK(F32),"",IF(J32="Yes",F32,F32*(1+Economics!$AK$29))) | J32: =+IF(ISBLANK(I32),"",IF(ISNUMBER(FIND("Yes",I32)),"No","Yes"))
C33: =+IF(ISBLANK(B33),"",IFERROR(INDEX($T$3:$T$7,MATCH(B33,$S$3:$S$7,0)),"")) | G33: =+IF(ISBLANK(F33),"",IF(J33="Yes",F33,F33*(1+Economics!$AK$29))) | J33: =+IF(ISBLANK(I33),"",IF(ISNUMBER(FIND("Yes",I33)),"No","Yes"))
C34: =+IF(ISBLANK(B34),"",IFERROR(INDEX($T$3:$T$7,MATCH(B34,$S$3:$S$7,0)),"")) | G34: =+IF(ISBLANK(F34),"",IF(J34="Yes",F34,F34*(1+Economics!$AK$29))) | J34: =+IF(ISBLANK(I34),"",IF(ISNUMBER(FIND("Yes",I34)),"No","Yes"))
C35: =+IF(ISBLANK(B35),"",IFERROR(INDEX($T$3:$T$7,MATCH(B35,$S$3:$S$7,0)),"")) | G35: =+IF(ISBLANK(F35),"",IF(J35="Yes",F35,F35*(1+Economics!$AK$29))) | J35: =+IF(ISBLANK(I35),"",IF(ISNUMBER(FIND("Yes",I35)),"No","Yes"))
C36: =+IF(ISBLANK(B36),"",IFERROR(INDEX($T$3:$T$7,MATCH(B36,$S$3:$S$7,0)),"")) | G36: =+IF(ISBLANK(F36),"",IF(J36="Yes",F36,F36*(1+Economics!$AK$29))) | J36: =+IF(ISBLANK(I36),"",IF(ISNUMBER(FIND("Yes",I36)),"No","Yes"))
C37: =+IF(ISBLANK(B37),"",IFERROR(INDEX($T$3:$T$7,MATCH(B37,$S$3:$S$7,0)),"")) | G37: =+IF(ISBLANK(F37),"",IF(J37="Yes",F37,F37*(1+Economics!$AK$29))) | J37: =+IF(ISBLANK(I37),"",IF(ISNUMBER(FIND("Yes",I37)),"No","Yes"))
C38: =+IF(ISBLANK(B38),"",IFERROR(INDEX($T$3:$T$7,MATCH(B38,$S$3:$S$7,0)),"")) | G38: =+IF(ISBLANK(F38),"",IF(J38="Yes",F38,F38*(1+Economics!$AK$29))) | J38: =+IF(ISBLANK(I38),"",IF(ISNUMBER(FIND("Yes",I38)),"No","Yes"))
C39: =+IF(ISBLANK(B39),"",IFERROR(INDEX($T$3:$T$7,MATCH(B39,$S$3:$S$7,0)),"")) | G39: =+IF(ISBLANK(F39),"",IF(J39="Yes",F39,F39*(1+Economics!$AK$29))) | J39: =+IF(ISBLANK(I39),"",IF(ISNUMBER(FIND("Yes",I39)),"No","Yes"))
C40: =+IF(ISBLANK(B40),"",IFERROR(INDEX($T$3:$T$7,MATCH(B40,$S$3:$S$7,0)),"")) | G40: =+IF(ISBLANK(F40),"",IF(J40="Yes",F40,F40*(1+Economics!$AK$29))) | J40: =+IF(ISBLANK(I40),"",IF(ISNUMBER(FIND("Yes",I40)),"No","Yes"))
C41: =+IF(ISBLANK(B41),"",IFERROR(INDEX($T$3:$T$7,MATCH(B41,$S$3:$S$7,0)),"")) | G41: =+IF(ISBLANK(F41),"",IF(J41="Yes",F41,F41*(1+Economics!$AK$29))) | J41: =+IF(ISBLANK(I41),"",IF(ISNUMBER(FIND("Yes",I41)),"No","Yes"))
... C530: =+IF(ISBLANK(B530),"",IFERROR(INDEX($T$3:$T$7,MATCH(B530,$S$3:$S$7,0)),"")) | G530: =+IF(ISBLANK(F530),"",IF(J530="Yes",F530,F530*(1+Economics!$AK$29))) | J530: =+IF(ISBLANK(I530),"",IF(ISNUMBER(FIND("Yes",I530)),"No","Yes"))

Sheet Utilities
B2: # of Months | C2: Date | D2: Hydro | E2: Gas | F2: Water
B3: 1 | C3: 45566
B4: =B3+1 -> 2 | C4: =EDATE(C3,1) -> 45597
B5: =B4+1 -> 3 | C5: =EDATE(C4,1) -> 45627
B6: =B5+1 -> 4 | C6: =EDATE(C5,1) -> 45658
B7: =B6+1 -> 5 | C7: =EDATE(C6,1) -> 45689
B8: =B7+1 -> 6 | C8: =EDATE(C7,1) -> 45717
B9: =B8+1 -> 7 | C9: =EDATE(C8,1) -> 45748
B10: =B9+1 -> 8 | C10: =EDATE(C9,1) -> 45778
B11: =B10+1 -> 9 | C11: =EDATE(C10,1) -> 45809
B12: =B11+1 -> 10 | C12: =EDATE(C11,1) -> 45839
B13: =B12+1 -> 11 | C13: =EDATE(C12,1) -> 45870
B14: =B13+1 -> 12 | C14: =EDATE(C13,1) -> 45901
B15: =B14+1 -> 13 | C15: =EDATE(C14,1) -> 45931
B16: =B15+1 -> 14 | C16: =EDATE(C15,1) -> 45962
B17: Total | D17: =SUM(D3:D16) -> 0 | E17: =SUM(E3:E16) -> 0 | F17: =SUM(F3:F16) -> 0
B18: Monthly Avg. | D18: =IFERROR(AVERAGE(D3:D16),"") | E18: =IFERROR(AVERAGE(E3:E16),"") | F18: =IFERROR(AVERAGE(F3:F16),"") | H18: 2024 Total (O/S) | I18: $ Delta | J18: % Delta | L18: 2023 Total (O/S) | M18: $ Delta | N18: % Delta
B19: TTM | D19: {=SUMIFS(D3:D16, $C$3:$C$16, ">" & EOMONTH(MAX(IF(D3:D16<>"", $C$3:$C$16)), -12), $C$3:$C$16, "<=" & MAX(IF(D3:D16<>"", $C$3:$C$16)))} -> 0 | E19: {=SUMIFS(E3:E16, $C$3:$C$16, ">" & EOMONTH(MAX(IF(E3:E16<>"", $C$3:$C$16)), -12), $C$3:$C$16, "<=" & MAX(IF(E3:E16<>"", $C$3:$C$16)))} -> 0 | F19: {=SUMIFS(F3:F16, $C$3:$C$16, ">" & EOMONTH(MAX(IF(F3:F16<>"", $C$3:$C$16)), -12), $C$3:$C$16, "<=" & MAX(IF(F3:F16<>"", $C$3:$C$16)))} -> 0 | H19: 0 | I19: =D21-H19 -> 0 | J19: =IFERROR(I19/H19,"N/A") -> N/A | M19: =D21-L19 -> 0 | N19: =IFERROR(M19/L19,"N/A") -> N/A
C21: Total Utilities | D21: =SUM(D19:F19) -> 0

Sheet PNW Verification
Z2: Verified
B3: BENCHMARK: 25% min. net worth required | C3: =IFERROR(Economics!I64*25%,"Complete Economics Tab") -> Complete Economics Tab | Z3: Unverified
Z4: Estimated
B5: Name/Account | C5: Assets ($) | D5: Liabilities ($) | E5: % Owned | F5: Net Worth | G5: Status | H5: Comments
B7: [GUARANTOR NAME]
B8: Equity:
B9: [Assets] | C9: 0 | D9: 0 | E9: 1 | F9: =IF(G9="Unverified",0,(C9-D9)*E9) -> 0 | G9: Unverified
B10: [Assets] | C10: 0 | D10: 0 | E10: 1 | F10: =IF(G10="Unverified",0,(C10-D10)*E10) -> 0 | G10: Unverified
B11: [Assets] | C11: 0 | D11: 0 | E11: 1 | F11: =IF(G11="Unverified",0,(C11-D11)*E11) -> 0 | G11: Unverified
B13: Properties:
B14: [Address] | C14: 0 | E14: 1 | F14: =IF(G14="Unverified",0,(C14-D14)*E14) -> 0 | G14: Unverified
B15: [Address] | C15: 0 | D15: 0 | E15: 1 | F15: =IF(G15="Unverified",0,(C15-D15)*E15) -> 0 | G15: Unverified
B16: [Address] | C16: 0 | D16: 0 | E16: 1 | F16: =IF(G16="Unverified",0,(C16-D16)*E16) -> 0 | G16: Unverified
B19: [#2 GUARANTOR NAME]
B20: Equity:
B21: [Assets] | C21: 0 | D21: 0 | E21: 1 | F21: =IF(G21="Unverified",0,(C21-D21)*E21) -> 0 | G21: Unverified
B22: [Assets] | C22: 0 | D22: 0 | E22: 1 | F22: =IF(G22="Unverified",0,(C22-D22)*E22) -> 0 | G22: Unverified
B23: [Assets] | C23: 0 | D23: 0 | E23: 1 | F23: =IF(G23="Unverified",0,(C23-D23)*E23) -> 0 | G23: Unverified
B25: Properties:
B26: [Address] | C26: 0 | D26: 0 | E26: 1 | F26: =IF(G26="Unverified",0,(C26-D26)*E26) -> 0 | G26: Unverified
B27: [Address] | C27: 0 | D27: 0 | E27: 1 | F27: =IF(G27="Unverified",0,(C27-D27)*E27) -> 0 | G27: Unverified
B28: [Address] | C28: 0 | D28: 0 | E28: 1 | F28: =IF(G28="Unverified",0,(C28-D28)*E28) -> 0 | G28: Unverified
B31: [#3 GUARANTOR NAME]
B32: Equity:
B33: [Assets] | C33: 0 | D33: 0 | E33: 1 | F33: =IF(G33="Unverified",0,(C33-D33)*E33) -> 0 | G33: Unverified
B34: [Assets] | C34: 0 | D34: 0 | E34: 1 | F34: =IF(G34="Unverified",0,(C34-D34)*E34) -> 0 | G34: Unverified
B35: [Assets] | C35: 0 | D35: 0 | E35: 1 | F35: =IF(G35="Unverified",0,(C35-D35)*E35) -> 0 | G35: Unverified
B37: Properties:
B38: [Address] | C38: 0 | D38: 0 | E38: 1 | F38: =IF(G38="Unverified",0,(C38-D38)*E38) -> 0 | G38: Unverified
B39: [Address] | C39: 0 | D39: 0 | E39: 1 | F39: =IF(G39="Unverified",0,(C39-D39)*E39) -> 0 | G39: Unverified
B40: [Address] | C40: 0 | D40: 0 | E40: 1 | F40: =IF(G40="Unverified",0,(C40-D40)*E40) -> 0 | G40: Unverified
B44: [#4 GUARANTOR NAME]
B45: Equity:
B46: Cash | C46: 0 | D46: 0 | E46: 1 | F46: =IF(G46="Unverified",0,(C46-D46)*E46) -> 0 | G46: Unverified
B47: [Assets] | C47: 0 | D47: 0 | E47: 1 | F47: =IF(G47="Unverified",0,(C47-D47)*E47) -> 0 | G47: Unverified
B48: [Assets] | C48: 0 | D48: 0 | E48: 1 | F48: =IF(G48="Unverified",0,(C48-D48)*E48) -> 0 | G48: Unverified
B50: Properties:
B51: [Address] | C51: 0 | D51: 0 | E51: 1 | F51: =IF(G51="Unverified",0,(C51-D51)*E51) -> 0 | G51: Unverified
B52: [Address] | C52: 0 | D52: 0 | E52: 1 | F52: =IF(G52="Unverified",0,(C52-D52)*E52) -> 0 | G52: Unverified
B53: [Address] | C53: 0 | D53: 0 | E53: 1 | F53: =IF(G53="Unverified",0,(C53-D53)*E53) -> 0 | G53: Unverified
B56: [#5 GUARANTOR NAME]
B57: Equity:
B58: [Assets] | C58: 0 | D58: 0 | E58: 1 | F58: =IF(G58="Unverified",0,(C58-D58)*E58) -> 0 | G58: Unverified
B59: [Assets] | C59: 0 | D59: 0 | E59: 1 | F59: =IF(G59="Unverified",0,(C59-D59)*E59) -> 0 | G59: Unverified
B60: [Assets] | C60: 0 | D60: 0 | E60: 1 | F60: =IF(G60="Unverified",0,(C60-D60)*E60) -> 0 | G60: Unverified
B62: Properties:
B63: [Address] | C63: 0 | D63: 0 | E63: 1 | F63: =IF(G63="Unverified",0,(C63-D63)*E63) -> 0 | G63: Unverified
B64: [Address] | C64: 0 | D64: 0 | E64: 1 | F64: =IF(G64="Unverified",0,(C64-D64)*E64) -> 0 | G64: Unverified
B65: [Address] | C65: 0 | D65: 0 | E65: 1 | F65: =IF(G65="Unverified",0,(C65-D65)*E65) -> 0 | G65: Unverified
B69: [#6 GUARANTOR NAME]
B70: Equity:
B71: [Assets] | C71: 0 | D71: 0 | E71: 1 | F71: =IF(G71="Unverified",0,(C71-D71)*E71) -> 0 | G71: Unverified
B72: [Assets] | C72: 0 | D72: 0 | E72: 1 | F72: =IF(G72="Unverified",0,(C72-D72)*E72) -> 0 | G72: Unverified
B73: [Assets] | C73: 0 | D73: 0 | E73: 1 | F73: =IF(G73="Unverified",0,(C73-D73)*E73) -> 0 | G73: Unverified
B75: Properties:
B76: [Address] | C76: 0 | D76: 0 | E76: 1 | F76: =IF(G76="Unverified",0,(C76-D76)*E76) -> 0 | G76: Unverified
B77: [Address] | C77: 0 | D77: 0 | E77: 1 | F77: =IF(G77="Unverified",0,(C77-D77)*E77) -> 0 | G77: Unverified
B78: [Address] | C78: 0 | D78: 0 | E78: 1 | F78: =IF(G78="Unverified",0,(C78-D78)*E78) -> 0 | G78: Unverified
B81: [#7 GUARANTOR NAME]
B82: Equity:
B83: [Assets] | C83: 0 | D83: 0 | E83: 1 | F83: =IF(G83="Unverified",0,(C83-D83)*E83) -> 0 | G83: Unverified
B84: [Assets] | C84: 0 | D84: 0 | E84: 1 | F84: =IF(G84="Unverified",0,(C84-D84)*E84) -> 0 | G84: Unverified
B85: [Assets] | C85: 0 | D85: 0 | E85: 1 | F85: =IF(G85="Unverified",0,(C85-D85)*E85) -> 0 | G85: Unverified
B87: Properties:
B88: [Address] | C88: 0 | D88: 0 | E88: 1 | F88: =IF(G88="Unverified",0,(C88-D88)*E88) -> 0 | G88: Unverified
B89: [Address] | C89: 0 | D89: 0 | E89: 1 | F89: =IF(G89="Unverified",0,(C89-D89)*E89) -> 0 | G89: Unverified
B90: [Address] | C90: 0 | D90: 0 | E90: 1 | F90: =IF(G90="Unverified",0,(C90-D90)*E90) -> 0 | G90: Unverified
B93: Total Verified: | F93: =SUM(F9:F91) -> 0
B94: Min. Net Worth Required Surplus (Shortfall): | F94: =F93-C3 -> #VALUE!
B95: Percentage: | F95: =F93/Economics!I64 -> #N/A
B96: Check: | F96: =IFERROR(IF(F95<25%,"Insufficient","Sufficient"),"Complete Economics Tab") -> Complete Economics Tab

Sheet Sales Comps
B1: Use for Standard Rental | L1: Use for Student Housing
B3: No. | C3: Address | D3: Date | E3: Price | F3: Units | G3: Price/Unit | H3: OCR | I3: NOI/Unit | J3: Source / Comments | L3: No. | M3: Address | N3: Date | O3: Price | P3: Units | Q3: Price/Unit | R3: Beds | S3: Price/Bed | T3: OCR | U3: NOI/Unit | V3: NOI/Bed | W3: Source / Comments
B4: 1 | G4: =+E4/F4 -> #DIV/0! | I4: =+IFERROR(E4*H4/F4,"--") -> -- | L4: 1 | Q4: =+O4/P4 -> #DIV/0! | S4: =O4/R4 -> #DIV/0! | U4: =+IFERROR(O4*T4/P4,"--") -> -- | V4: =+IFERROR(O4*T4/R4,"--") -> --
B5: 2 | G5: =+E5/F5 -> #DIV/0! | I5: =+IFERROR(E5*H5/F5,"--") -> -- | L5: 2 | Q5: =+O5/P5 -> #DIV/0! | S5: =O5/R5 -> #DIV/0! | U5: =+IFERROR(O5*T5/P5,"--") -> -- | V5: =+IFERROR(O5*T5/R5,"--") -> --
B6: 3 | G6: =+E6/F6 -> #DIV/0! | I6: =+IFERROR(E6*H6/F6,"--") -> -- | L6: 3 | Q6: =+O6/P6 -> #DIV/0! | S6: =O6/R6 -> #DIV/0! | U6: =+IFERROR(O6*T6/P6,"--") -> -- | V6: =+IFERROR(O6*T6/R6,"--") -> --
B7: 4 | G7: =+E7/F7 -> #DIV/0! | I7: =+IFERROR(E7*H7/F7,"--") -> -- | L7: 4 | Q7: =+O7/P7 -> #DIV/0! | S7: =O7/R7 -> #DIV/0! | U7: =+IFERROR(O7*T7/P7,"--") -> -- | V7: =+IFERROR(O7*T7/R7,"--") -> --
B8: 5 | G8: =+E8/F8 -> #DIV/0! | I8: =+IFERROR(E8*H8/F8,"--") -> -- | L8: 5 | Q8: =+O8/P8 -> #DIV/0! | S8: =O8/R8 -> #DIV/0! | U8: =+IFERROR(O8*T8/P8,"--") -> -- | V8: =+IFERROR(O8*T8/R8,"--") -> --
B9: 6 | G9: =+E9/F9 -> #DIV/0! | I9: =+IFERROR(E9*H9/F9,"--") -> -- | L9: 6 | Q9: =+O9/P9 -> #DIV/0! | S9: =O9/R9 -> #DIV/0! | U9: =+IFERROR(O9*T9/P9,"--") -> -- | V9: =+IFERROR(O9*T9/R9,"--") -> --
B10: 7 | G10: =+E10/F10 -> #DIV/0! | I10: =+IFERROR(E10*H10/F10,"--") -> -- | L10: 7 | Q10: =+O10/P10 -> #DIV/0! | S10: =O10/R10 -> #DIV/0! | U10: =+IFERROR(O10*T10/P10,"--") -> -- | V10: =+IFERROR(O10*T10/R10,"--") -> --
B11: 8 | G11: =+E11/F11 -> #DIV/0! | I11: =+IFERROR(E11*H11/F11,"--") -> -- | L11: 8 | Q11: =+O11/P11 -> #DIV/0! | S11: =O11/R11 -> #DIV/0! | U11: =+IFERROR(O11*T11/P11,"--") -> -- | V11: =+IFERROR(O11*T11/R11,"--") -> --
D12: Min | E12: =MIN(E4:E11) -> 0 | F12: =MIN(F4:F11) -> 0 | G12: =MIN(G4:G11) -> #DIV/0! | H12: =MIN(H4:H11) -> 0 | I12: =MIN(I4:I11) -> 0 | J12: Source: Criteria: | N12: Min | O12: =MIN(O4:O11) -> 0 | P12: =MIN(P4:P11) -> 0 | Q12: =MIN(Q4:Q11) -> #DIV/0! | R12: =MIN(R4:R11) -> 0 | S12: =MIN(S4:S11) -> #DIV/0! | T12: =MIN(T4:T11) -> 0 | U12: =MIN(U4:U11) -> 0 | V12: =MIN(V4:V11) -> 0 | W12: Source: Criteria:
D13: Max | E13: =MAX(E4:E11) -> 0 | F13: =MAX(F4:F11) -> 0 | G13: =MAX(G4:G11) -> #DIV/0! | H13: =MAX(H4:H11) -> 0 | I13: =MAX(I4:I11) -> 0 | N13: Max | O13: =MAX(O4:O11) -> 0 | P13: =MAX(P4:P11) -> 0 | Q13: =MAX(Q4:Q11) -> #DIV/0! | R13: =MAX(R4:R11) -> 0 | S13: =MAX(S4:S11) -> #DIV/0! | T13: =MAX(T4:T11) -> 0 | U13: =MAX(U4:U11) -> 0 | V13: =MAX(V4:V11) -> 0
D14: Median | E14: =MEDIAN(E4:E11) -> #NUM! | F14: =MEDIAN(F4:F11) -> #NUM! | G14: =MEDIAN(G4:G11) -> #DIV/0! | H14: =MEDIAN(H4:H11) -> #NUM! | I14: =MEDIAN(I4:I11) -> #NUM! | N14: Median | O14: =MEDIAN(O4:O11) -> #NUM! | P14: =MEDIAN(P4:P11) -> #NUM! | Q14: =MEDIAN(Q4:Q11) -> #DIV/0! | R14: =MEDIAN(R4:R11) -> #NUM! | S14: =MEDIAN(S4:S11) -> #DIV/0! | T14: =MEDIAN(T4:T11) -> #NUM! | U14: =MEDIAN(U4:U11) -> #NUM! | V14: =MEDIAN(V4:V11) -> #NUM!
D15: Mean | E15: =AVERAGE(E4:E11) -> #DIV/0! | F15: =AVERAGE(F4:F11) -> #DIV/0! | G15: =AVERAGE(G4:G11) -> #DIV/0! | H15: =AVERAGE(H4:H11) -> #DIV/0! | I15: =AVERAGE(I4:I11) -> #DIV/0! | N15: Mean | O15: =AVERAGE(O4:O11) -> #DIV/0! | P15: =AVERAGE(P4:P11) -> #DIV/0! | Q15: =AVERAGE(Q4:Q11) -> #DIV/0! | R15: =AVERAGE(R4:R11) -> #DIV/0! | S15: =AVERAGE(S4:S11) -> #DIV/0! | T15: =AVERAGE(T4:T11) -> #DIV/0! | U15: =AVERAGE(U4:U11) -> #DIV/0! | V15: =AVERAGE(V4:V11) -> #DIV/0!
D16: Subject | E16: =+Economics!H34 -> 0 | F16: =+Economics!F15 -> 0 | G16: =E16/F16 -> #DIV/0! | H16: =+Economics!G34 -> 0 | I16: =+Economics!I33 -> #DIV/0! | N16: Subject | O16: =+Economics!H34 -> 0 | P16: =+Economics!F15 -> 0 | Q16: =O16/P16 -> #DIV/0! | S16: =P16/R16 -> #DIV/0! | T16: =+Economics!G53 -> 0 | U16: =+Economics!I52 -> #DIV/0!

Sheet Leasing Comps
B2: Bachelor Comps
B3: No. | C3: Address | D3: Market | E3: Size | F3: Rent | G3: PSF | H3: Source / Comments
B4: 1 | G4: =IFERROR(F4/E4,"--") -> --
B5: 2 | G5: =IFERROR(F5/E5,"--") -> --
B6: 3 | G6: =IFERROR(F6/E6,"--") -> --
B7: 5 | G7: =IFERROR(F7/E7,"--") -> --
B8: 6 | G8: =IFERROR(F8/E8,"--") -> --
B9: 7 | G9: =IFERROR(F9/E9,"--") -> --
B10: 8 | G10: =IFERROR(F10/E10,"--") -> --
D11: Min | E11: =MIN(E4:E10) -> 0 | F11: =MIN(F4:F10) -> 0 | G11: =MIN(G4:G10) -> 0 | H11: Source: Criteria:
D12: Max | E12: =MAX(E4:E10) -> 0 | F12: =MAX(F4:F10) -> 0 | G12: =MAX(G4:G10) -> 0
D13: Median | E13: =MEDIAN(E4:E10) -> #NUM! | F13: =MEDIAN(F4:F10) -> #NUM! | G13: =MEDIAN(G4:G10) -> #NUM!
D14: Mean | E14: =AVERAGE(E4:E10) -> #DIV/0! | F14: =AVERAGE(F4:F10) -> #DIV/0! | G14: =AVERAGE(G4:G10) -> #DIV/0!
D15: Subject | E15: =+Economics!G5 -> - | F15: =+Economics!I5 -> - | G15: =F15/E15 -> #VALUE!
B17: 1 Bed Comps
B18: No. | C18: Address | D18: Market | E18: Size | F18: Rent | G18: PSF | H18: Source / Comments
B19: 1 | G19: =IFERROR(F19/E19,"--") -> --
B20: 2 | G20: =IFERROR(F20/E20,"--") -> --
B21: 3 | G21: =IFERROR(F21/E21,"--") -> --
B22: 4 | G22: =IFERROR(F22/E22,"--") -> --
B23: 5 | G23: =IFERROR(F23/E23,"--") -> --
B24: 6 | G24: =IFERROR(F24/E24,"--") -> --
D25: Min | E25: =MIN(E19:E24) -> 0 | F25: =MIN(F19:F24) -> 0 | G25: =MIN(G19:G24) -> 0
D26: Max | E26: =MAX(E19:E24) -> 0 | F26: =MAX(F19:F24) -> 0 | G26: =MAX(G19:G24) -> 0
D27: Median | E27: =MEDIAN(E19:E24) -> #NUM! | F27: =MEDIAN(F19:F24) -> #NUM! | G27: =MEDIAN(G19:G24) -> #NUM!
D28: Mean | E28: =AVERAGE(E19:E24) -> #DIV/0! | F28: =AVERAGE(F19:F24) -> #DIV/0! | G28: =AVERAGE(G19:G24) -> #DIV/0!
D29: Subject | E29: =+Economics!G6 -> - | F29: =+Economics!I6 -> - | G29: =F29/E29 -> #VALUE!
B31: 2 Bed Comps
B32: No. | C32: Address | D32: Market | E32: Size | F32: Rent | G32: PSF | H32: Source / Comments
B33: =B19 -> 1 | G33: =IFERROR(F33/E33,"--") -> --
B34: =B20 -> 2 | G34: =IFERROR(F34/E34,"--") -> --
B35: =B21 -> 3 | G35: =IFERROR(F35/E35,"--") -> --
B36: =B22 -> 4 | G36: =IFERROR(F36/E36,"--") -> --
B37: =B23 -> 5 | G37: =IFERROR(F37/E37,"--") -> --
B38: 7 | G38: =IFERROR(F38/E38,"--") -> --
D39: Min | E39: =MIN(E33:E38) -> 0 | F39: =MIN(F33:F38) -> 0 | G39: =MIN(G33:G38) -> 0 | H39: Source: Criteria:
D40: Max | E40: =MAX(E33:E38) -> 0 | F40: =MAX(F33:F38) -> 0 | G40: =MAX(G33:G38) -> 0
D41: Median | E41: =MEDIAN(E33:E38) -> #NUM! | F41: =MEDIAN(F33:F38) -> #NUM! | G41: =MEDIAN(G33:G38) -> #NUM!
D42: Mean | E42: =AVERAGE(E33:E38) -> #DIV/0! | F42: =AVERAGE(F33:F38) -> #DIV/0! | G42: =AVERAGE(G33:G38) -> #DIV/0!
D43: Subject | E43: =+Economics!G7 -> - | F43: =+Economics!I7 -> - | G43: =F43/E43 -> #VALUE!
B45: 3 Bed Comps
B46: No. | C46: Address | D46: Market | E46: Size | F46: Rent | G46: PSF | H46: Source / Comments
B47: 1 | G47: =IFERROR(F47/E47,"--") -> --
B48: 2 | G48: =IFERROR(F48/E48,"--") -> --
B49: 3 | G49: =IFERROR(F49/E49,"--") -> --
B50: 7 | G50: =IFERROR(F50/E50,"--") -> --
B51: 8 | G51: =IFERROR(F51/E51,"--") -> --
B52: 9 | G52: =IFERROR(F52/E52,"--") -> --
D53: Min | E53: =MIN(E47:E52) -> 0 | F53: =MIN(F47:F52) -> 0 | G53: =MIN(G47:G52) -> 0 | H53: Source: Criteria:
D54: Max | E54: =MAX(E47:E52) -> 0 | F54: =MAX(F47:F52) -> 0 | G54: =MAX(G47:G52) -> 0
D55: Median | E55: =MEDIAN(E47:E52) -> #NUM! | F55: =MEDIAN(F47:F52) -> #NUM! | G55: =MEDIAN(G47:G52) -> #NUM!
D56: Mean | E56: =AVERAGE(E47:E52) -> #DIV/0! | F56: =AVERAGE(F47:F52) -> #DIV/0! | G56: =AVERAGE(G47:G52) -> #DIV/0!
D57: Subject | E57: =+Economics!G8 -> - | F57: =+Economics!I8 -> - | G57: =F57/E57 -> #VALUE!

Sheet Budget
B2: Step 1 - Project Stats (always complete this) | G2: Step 2 - Fill Out Budget Step 4 - Final Analysis
J3: Borrower UW | K3: KingSett UW
B4: Site Area (acres) | C4: Units | D4: GFA | E4: Efficiency % | G4: Uses of Funds | J4: Total | K4: Total | L4: Per Unit | M4: Per GFA | O4: Variance | P4: Notes
A5: Res. | B5: 0 | C5: =Economics!$F$15 -> 0 | D5: 0 | E5: =Economics!$H$125 -> #DIV/0! | G5: Land:
A6: Comm. | B6: 0 | C6: 0 | D6: 0 | E6: =Economics!$I$125 -> #DIV/0! | G6: Land Costs (Purchase Price @ xxxx) | J6: 0 | K6: 0 | L6: =IFERROR(K6/$C$7,0) -> 0 | M6: =K6/$D$7 -> #DIV/0! | O6: =+K6-J6 -> 0
A7: Total | B7: =SUM(B5:B6) -> 0 | C7: =SUM(C5:C6) -> 0 | D7: =SUM(D5:D6) -> 0 | E7: =Economics!$J$125 -> #DIV/0! | G7: Other Land Costs | J7: 0 | K7: 0 | L7: =IFERROR(K7/$C$7,0) -> 0 | M7: =K7/$D$7 -> #DIV/0! | O7: =+K7-J7 -> 0 | P7: Realty taxes & LTT should be checked. Information is publically available on places like ratehub.ca
A8: Other | B8: 0 | C8: 0 | G8: Appraisal Surplus | J8: =J9-J7-J6 -> 0 | K8: =K9-K7-K6 -> 0 | L8: =IFERROR(K8/$C$7,0) -> 0 | M8: =K8/$D$7 -> #DIV/0! | O8: =+K8-J8 -> 0
G9: Land Value | J9: 0 | K9: 0 | L9: =IFERROR(K9/$C$7,0) -> 0 | M9: =K9/$D$7 -> #DIV/0! | O9: =+K9-J9 -> 0
B10: Step 3 - Preliminary Budget Analysis | G10: Hard Costs:
G11: Constr. Costs | J11: 0 | K11: 0 | L11: =IFERROR(K11/$C$7,0) -> 0 | M11: =K11/$D$7 -> #DIV/0! | O11: =+K11-J11 -> 0 | P11: Is Div 1 included (if so, what % of HC is it)? MP/JT need to know below grade parkade area; and what it is as a % of the total construction area. Average suite size, location, foundation system, envelope system, level of finish and projections/balconies are other factors that can significantly impact cost
B12: Hard Costs (excl. parking) - Estimate | C12: Benchmark | D12: Total | E12: Per GFA | G12: Servicing | J12: 0 | K12: 0 | L12: =IFERROR(K12/$C$7,0) -> 0 | M12: =K12/$D$7 -> #DIV/0! | O12: =+K12-J12 -> 0 | P12: Is the project an infill project (services are available to the lot line)? If not, services need to be brought to the site, which will cost more
B13: Altus Cost Guide - Low End | C13: 0 | D13: =+C13*$D$7 -> 0 | E13: =D13/$D$7 -> #DIV/0! | G13: Demolition | J13: 0 | K13: 0 | L13: =IFERROR(K13/$C$7,0) -> 0 | M13: =K13/$D$7 -> #DIV/0! | O13: =+K13-J13 -> 0 | P13: Are there any major demolition costs?
B14: Altus Cost Guide - Average | C14: =AVERAGE(C13,C15) -> 0 | D14: =AVERAGE(D13,D15) -> 0 | E14: =D14/$D$7 -> #DIV/0! | G14: Remediation | J14: 0 | K14: 0 | L14: =IFERROR(K14/$C$7,0) -> 0 | M14: =K14/$D$7 -> #DIV/0! | O14: =+K14-J14 -> 0 | P14: Check if there are any remediation costs
B15: Altus Cost Guide - High End | C15: 0 | D15: =+C15*$D$7 -> 0 | E15: =D15/$D$7 -> #DIV/0! | G15: Furnishings | J15: 0 | K15: 0 | L15: =IFERROR(K15/$C$7,0) -> 0 | M15: =K15/$D$7 -> #DIV/0! | O15: =+K15-J15 -> 0 | P15: Confirm if this is required. Total cost depends on product type. Student res. $10k-$15k/bed, standard rental $20k/suite
B16: Altus Cost Guide - High End | C16: =_xlfn.XLOOKUP($B$16,$B$13:$B$15,C$13:C$15) -> 0 | D16: =_xlfn.XLOOKUP($B$16,$B$13:$B$15,D$13:D$15) -> 0 | E16: =_xlfn.XLOOKUP($B$16,$B$13:$B$15,E$13:E$15) -> #DIV/0! | G16: Utility Connections | J16: 0 | K16: 0 | L16: =IFERROR(K16/$C$7,0) -> 0 | M16: =K16/$D$7 -> #DIV/0! | O16: =+K16-J16 -> 0
B17: Borrower Hard Costs (excl. CM fee) | D17: =$J$19-$J$17 -> 0 | E17: =D17/$D$7 -> #DIV/0! | G17: Constr. Management Fees | I17: =+K17/(VLOOKUP("Total Hard Costs",$G$5:$K$52,5,FALSE)-K17) -> #DIV/0! | J17: 0 | K17: 0 | L17: =IFERROR(K17/$C$7,0) -> 0 | M17: =K17/$D$7 -> #DIV/0! | O17: =+K17-J17 -> 0 | P17: 3rd party CM fee is typically 3-4% of the construction cost
B18: Delta | C18: =D18/D16 -> #DIV/0! | D18: =D17-D16 -> 0 | E18: =D18/$D$7 -> #DIV/0! | G18: Other Hard Costs | J18: 0 | K18: 0 | L18: =IFERROR(K18/$C$7,0) -> 0 | M18: =K18/$D$7 -> #DIV/0! | O18: =+K18-J18 -> 0
G19: Total Hard Costs | J19: =SUM(J11:J18) -> 0 | K19: =SUM(K11:K18) -> 0 | L19: =IFERROR(K19/$C$7,0) -> 0 | M19: =K19/$D$7 -> #DIV/0! | O19: =+K19-J19 -> 0
B20: Soft Costs - Estimate | C20: Benchmark | D20: Total | E20: Per GFA
B21: Design & Consultants | C21: 0.035 | D21: =+C21*$K$19 -> 0 | E21: =D21/$D$7 -> #DIV/0! | G21: Soft Costs:
B22: Legal, Admin & Insurance | C22: 0.015 | D22: =+C22*$K$19 -> 0 | E22: =D22/$D$7 -> #DIV/0! | G22: DCs & Levies | J22: 0 | K22: =D75 -> 0 | L22: =IFERROR(K22/$C$7,0) -> 0 | M22: =K22/$D$7 -> #DIV/0! | O22: =+K22-J22 -> 0 | P22: Should be calculated by the UW prior to sending for review. UW to determine if there are municipal & regional DCs applicable. Should include building permit charges as well.
B23: Lease Commissions | C23: 50% of One Month's Rent | D23: =Economics!$I$15*Economics!$F$15*50% -> #DIV/0! | E23: =D23/$D$7 -> #DIV/0! | G23: Design & Consultants | I23: =+K23/VLOOKUP("Total Hard Costs",$G$5:$K$52,5,FALSE) -> #DIV/0! | J23: 0 | K23: 0 | L23: =IFERROR(K23/$C$7,0) -> 0 | M23: =K23/$D$7 -> #DIV/0! | O23: =+K23-J23 -> 0 | P23: Typically 3.5%-4% of hard costs. Lower than 3% is aggressive. Normally higher for a mid-rise building as a % of hard costs; % does drop a bit for simpler projects, especially if there are a lot of typical floors
B24: Financing Costs | C24: Single Loan (1st) | D24: =IF(C24="Single Loan (1st)",'Int Reserve - Single Loan'!$I$88,IF(C24="Single Loan (2nd)",'Int Reserve - Single Loan'!$V$88,'Int Reserve - A-B Loan'!$I$88))+Economics!$J$66 -> #N/A | E24: =D24/$D$7 -> #N/A | G24: Legal & Admin | I24: =+K24/VLOOKUP("Total Hard Costs",$G$5:$K$52,5,FALSE) -> #DIV/0! | J24: 0 | K24: 0 | L24: =IFERROR(K24/$C$7,0) -> 0 | M24: =K24/$D$7 -> #DIV/0! | O24: =+K24-J24 -> 0 | P24: Includes insurance, typically ends up being 1-2% of the hard costs
B25: Misc. Financing Costs | C25: 0.05 | D25: =D24*$C$25 -> #N/A | E25: =D25/$D$7 -> #N/A | G25: Marketing and Sales | J25: 0 | K25: 0 | L25: =IFERROR(K25/$C$7,0) -> 0 | M25: =K25/$D$7 -> #DIV/0! | O25: =+K25-J25 -> 0 | P25: Minimum $50k - $100k but depends on size/scope of the project & marketing approach
B26: Total | D26: =SUM(D21:D25) -> #DIV/0! | E26: =D26/$D$7 -> #DIV/0! | G26: Lease Commissions | H26: 0.5 | J26: 0 | K26: =IFERROR(IF(OR(K9<>0,K19<>0),Economics!$H$15/12*H26,0),0) -> 0 | L26: =IFERROR(K26/$C$7,0) -> 0 | M26: =K26/$D$7 -> #DIV/0! | O26: =+K26-J26 -> 0 | P26: Half a month's rent for standard rental projects
B27: Borrower Soft Costs (excl. DM fee & operating income) | D27: =J23+J24+J25+J46 -> 0 | E27: =D27/$D$7 -> #DIV/0! | G27: Development Management Fees | H27: =+K27/(K54-K27) -> #DIV/0! | J27: 0 | K27: 0 | L27: =IFERROR(K27/$C$7,0) -> 0 | M27: =K27/$D$7 -> #DIV/0! | O27: =+K27-J27 -> 0 | P27: Should be a minimum of 2%-3% of the HC budget. Will vary significantly project to project though
B28: Delta | C28: =D28/D26 -> #DIV/0! | D28: =D27-D26 -> #DIV/0! | E28: =D28/$D$7 -> #DIV/0! | G28: Sales Tax Self-Assessment | I28: =IFERROR(VLOOKUP($H$28,$G$62:$H$71,2,FALSE),"N/A") -> N/A | J28: 0 | K28: =IFERROR(Economics!$H$34*-I28,0) -> 0 | L28: =IFERROR(K28/$C$7,0) -> 0 | M28: =K28/$D$7 -> #DIV/0! | O28: =+K28-J28 -> 0 | P28: Running to ground if this is payable and then refunded, or simply waived
G29: Operating Costs | J29: 0 | K29: 0 | L29: =IFERROR(K29/$C$7,0) -> 0 | M29: =K29/$D$7 -> #DIV/0! | O29: =+K29-J29 -> 0 | P29: Costs related to operating the building until stabilization / loan repayment
B30: Management Fees - Estimate | C30: Benchmark | D30: Total | E30: Per GFA | G30: Operating Income | J30: 0 | K30: 0 | L30: =IFERROR(K30/$C$7,0) -> 0 | M30: =K30/$D$7 -> #DIV/0! | O30: =+K30-J30 -> 0 | P30: Revenue related to operating the building until stabilization / loan repayment
B31: Construction Management | C31: 0.035 | D31: =+C31*$K$19 -> 0 | E31: =D31/$D$7 -> #DIV/0! | G31: Other Soft Costs | J31: 0 | K31: 0 | L31: =IFERROR(K31/$C$7,0) -> 0 | M31: =K31/$D$7 -> #DIV/0! | O31: =+K31-J31 -> 0
B32: Development Management | C32: 0.025 | D32: =+C32*$K$19 -> 0 | E32: =D32/$D$7 -> #DIV/0! | G32: Total Soft Costs | J32: =SUM(J22:J31) -> 0 | K32: =SUM(K22:K31) -> 0 | L32: =IFERROR(K32/$C$7,0) -> 0 | M32: =K32/$D$7 -> #DIV/0! | O32: =+K32-J32 -> 0
B33: Total | D33: =SUM(D31:D32) -> 0 | E33: =D33/$D$7 -> #DIV/0! | Q33: delta to fee in economics
B34: Borrower Management Fees | D34: =J17+J27 -> 0 | E34: =D34/$D$7 -> #DIV/0! | G34: Financing Costs: | Q34: =K35-Economics!J66 -> #N/A
B35: Delta | C35: =D35/D33 -> #DIV/0! | D35: =D34-D33 -> 0 | E35: =D35/$D$7 -> #DIV/0! | G35: Senior Lender Fees | J35: 0 | K35: 0 | L35: =IFERROR(K35/$C$7,0) -> 0 | M35: =K35/$D$7 -> #DIV/0! | O35: =+K35-J35 -> 0 | P35: based off of Economics tab, do not link due to circular reference
G36: Senior Lender Interest Reserve | J36: 0 | K36: =IF(C24="Single Loan (1st)",'Int Reserve - Single Loan'!$H$14,IF(C24="Single Loan (2nd)",'Int Reserve - Single Loan'!$H$15,'Int Reserve - A-B Loan'!$H$16)) -> 0 | L36: =IFERROR(K36/$C$7,0) -> 0 | M36: =K36/$D$7 -> #DIV/0! | O36: =+K36-J36 -> 0 | P36: linked to IR calculators
B37: Development Charges Analysis | G37: Subordinate Lender Fees | J37: 0 | K37: 0 | L37: =IFERROR(K37/$C$7,0) -> 0 | M37: =K37/$D$7 -> #DIV/0! | O37: =+K37-J37 -> 0
G38: Subordinate Lender Interest Reserve | J38: 0 | K38: 0 | L38: =IFERROR(K38/$C$7,0) -> 0 | M38: =K38/$D$7 -> #DIV/0! | O38: =+K38-J38 -> 0
B39: Municipal DCs | C39: Units/m2 | D39: Total | E39: DC per Door/m2 | G39: Admin Fees | J39: 0 | K39: 0 | L39: =IFERROR(K39/$C$7,0) -> 0 | M39: =K39/$D$7 -> #DIV/0! | O39: =+K39-J39 -> 0
B40: =Economics!$C5 -> Bachelor | C40: =_xlfn.XLOOKUP($B40,Economics!$C$5:$C$14,Economics!$F$5:$F$14,0) -> 0 | D40: =+C40*E40 -> 0 | E40: 0 | G40: Discharge Fees | J40: 0 | K40: 0 | L40: =IFERROR(K40/$C$7,0) -> 0 | M40: =K40/$D$7 -> #DIV/0! | O40: =+K40-J40 -> 0
B41: =Economics!$C6 -> 1 Bedroom | C41: =_xlfn.XLOOKUP($B41,Economics!$C$5:$C$14,Economics!$F$5:$F$14,0) -> 0 | D41: =+C41*E41 -> 0 | E41: 0 | G41: Project Monitor Fees | J41: 0 | K41: 0 | L41: =IFERROR(K41/$C$7,0) -> 0 | M41: =K41/$D$7 -> #DIV/0! | O41: =+K41-J41 -> 0
B42: =Economics!$C7 -> 2 Bedroom | C42: =_xlfn.XLOOKUP($B42,Economics!$C$5:$C$14,Economics!$F$5:$F$14,0) -> 0 | D42: =+C42*E42 -> 0 | E42: 0 | G42: L/C Fees | J42: 0 | K42: 0 | L42: =IFERROR(K42/$C$7,0) -> 0 | M42: =K42/$D$7 -> #DIV/0! | O42: =+K42-J42 -> 0
B43: =Economics!$C8 -> 3 Bedroom | C43: =_xlfn.XLOOKUP($B43,Economics!$C$5:$C$14,Economics!$F$5:$F$14,0) -> 0 | D43: =+C43*E43 -> 0 | E43: 0 | G43: Appraisal | J43: 0 | K43: 0 | L43: =IFERROR(K43/$C$7,0) -> 0 | M43: =K43/$D$7 -> #DIV/0! | O43: =+K43-J43 -> 0
B44: =Economics!$C9 -> 4+ Bedroom | C44: =_xlfn.XLOOKUP($B44,Economics!$C$5:$C$14,Economics!$F$5:$F$14,0) -> 0 | D44: =+C44*E44 -> 0 | E44: 0 | G44: Land Loan Interest & Fees | J44: 0 | K44: 0 | L44: =IFERROR(K44/$C$7,0) -> 0 | M44: =K44/$D$7 -> #DIV/0! | O44: =+K44-J44 -> 0 | P44: Check if this cost is reasonable, as we might not want to recognize the full cost
B45: Total | C45: =SUM(C40:C44) -> 0 | D45: =SUM(D40:D44) -> 0 | E45: =D45/C45 -> #DIV/0! | G45: Other Financing Costs | J45: 0 | K45: 0 | L45: =IFERROR(K45/$C$7,0) -> 0 | M45: =K45/$D$7 -> #DIV/0! | O45: =+K45-J45 -> 0
B46: Commercial (m2) | C46: =Economics!$G$42*0.09290304 -> 0 | D46: =+C46*E46 -> 0 | E46: 0 | G46: Total Financing Costs | J46: =SUM(J35:J45) -> 0 | K46: =SUM(K35:K45) -> 0 | L46: =IFERROR(K46/$C$7,0) -> 0 | M46: =K46/$D$7 -> #DIV/0! | O46: =+K46-J46 -> 0
B47: Total Municipal DCs | C47: =C45 -> 0 | D47: =SUM(D45:D46) -> 0 | E47: =D47/C47 -> #DIV/0!
G48: Contingency:
B49: Regional DCs | C49: Units or m2 | D49: Total | E49: DC per Door or m2 | G49: Hard Cost Contingency | I49: 0.05 | J49: 0 | K49: =I49*VLOOKUP("Total Hard Costs",$G$5:$K$52,5,FALSE) -> 0 | L49: =IFERROR(K49/$C$7,0) -> 0 | M49: =K49/$D$7 -> #DIV/0! | O49: =+K49-J49 -> 0 | P49: Minimum 5.00% of hard costs, can be higher (deal specific)
B50: =Economics!$C5 -> Bachelor | C50: =C40 -> 0 | D50: =+C50*E50 -> 0 | E50: 0 | G50: Soft Cost Contingency | I50: 0.05 | J50: 0 | K50: =I50*(VLOOKUP("Total Soft Costs",$G$5:$K$52,5,FALSE)+VLOOKUP("Total Financing Costs",$G$5:$K$52,5,FALSE)) -> 0 | L50: =IFERROR(K50/$C$7,0) -> 0 | M50: =K50/$D$7 -> #DIV/0! | O50: =+K50-J50 -> 0 | P50: Minimum 5.00% of soft costs, can be higher (deal specific)
B51: =Economics!$C6 -> 1 Bedroom | C51: =C41 -> 0 | D51: =+C51*E51 -> 0 | E51: 0 | G51: Other Contingency | J51: 0 | K51: 0 | L51: =IFERROR(K51/$C$7,0) -> 0 | M51: =K51/$D$7 -> #DIV/0! | O51: =+K51-J51 -> 0
B52: =Economics!$C7 -> 2 Bedroom | C52: =C42 -> 0 | D52: =+C52*E52 -> 0 | E52: 0 | G52: Total Contingency | I52: =+K52/(VLOOKUP("Total Hard Costs",$G$5:$K$52,5,FALSE)+VLOOKUP("Total Soft Costs",$G$5:$K$52,5,FALSE)+VLOOKUP("Total Financing Costs",$G$5:$K$52,5,FALSE)) -> #DIV/0! | J52: =SUM(J49:J51) -> 0 | K52: =SUM(K49:K51) -> 0 | L52: =IFERROR(K52/$C$7,0) -> 0 | M52: =K52/$D$7 -> #DIV/0! | O52: =+K52-J52 -> 0
B53: =Economics!$C8 -> 3 Bedroom | C53: =C43 -> 0 | D53: =+C53*E53 -> 0 | E53: 0
B54: =Economics!$C9 -> 4+ Bedroom | C54: =C44 -> 0 | D54: =+C54*E54 -> 0 | E54: 0 | G54: Total Uses of Funds | J54: =+J9+J19+J32+J46+J52 -> 0 | K54: =+K9+K19+K32+K46+K52 -> 0 | L54: =IFERROR(K54/$C$7,0) -> 0 | M54: =K54/$D$7 -> #DIV/0! | O54: =+K54-J54 -> 0
B55: Total | C55: =SUM(C50:C54) -> 0 | D55: =SUM(D50:D54) -> 0 | E55: =D55/C55 -> #DIV/0!
B56: Commercial (m2) | C56: =C46 -> 0 | D56: =+C56*E56 -> 0 | E56: 0 | G56: Combined Property Valuation | J56: 0 | K56: =Economics!$H$54 -> 0
B57: Total Regional DCs | C57: =C55 -> 0 | D57: =SUM(D55:D56) -> 0 | E57: =D57/C57 -> #DIV/0!
G58: Profit | H58: =J58/J54 -> #DIV/0! | J58: =J56-J54 -> 0 | K58: =K56-K54 -> 0 | L58: =K58/K54 -> #DIV/0! | O58: =+K58-J58 -> 0
B59: Education DCs | C59: Units/GFA | D59: Total | E59: DC per Door/GFA | G59: Return on Equity | J59: =+J58/Economics!$H$107 -> #DIV/0! | K59: =+K58/Economics!$H$107 -> #DIV/0! | O59: =+K59-J59 -> #DIV/0!
B60: Residential | C60: =+C45 -> 0 | D60: =+C60*E60 -> 0 | E60: 0
B61: Commercial (GFA) | C61: =D6 -> 0 | D61: =+C61*E61 -> 0 | E61: 0 | G61: Province | H61: HST/GST | K61: =IF(K54=Economics!H118,"OK","CHECK BUDGET") -> OK
B62: Total Education DCs | C62: =C60 -> 0 | D62: =SUM(D60:D61) -> 0 | E62: =D62/C62 -> #DIV/0! | G62: ON | H62: 0.13
G63: BC | H63: 0.05
B64: Other Charges | C64: Units | D64: Total | E64: DC per Door | G64: QC | H64: 0.05
B65: Parkland Dedication | C65: 0 | D65: =C65*$J$9 -> 0 | E65: =D65/$C$5 -> #DIV/0! | G65: AB | H65: 0.05
B66: Community Benefits | C66: 0 | D66: =C66*$J$9 -> 0 | E66: =D66/$C$5 -> #DIV/0! | G66: MB | H66: 0.05
B67: [Other Charge] | C67: 0 | D67: =+C67*E67 -> 0 | E67: 0 | G67: SK | H67: 0.05
B68: Total Other Charges | C68: =C47 -> 0 | D68: =SUM(D65:D67) -> 0 | E68: =D68/C68 -> #DIV/0! | G68: NB | H68: 0.15
G69: NL | H69: 0.15
B70: Development Charges Summary | G70: NS | H70: 0.15
G71: PEI | H71: 0.15
B72: DCs & Levies | C72: Benchmark | D72: Total | E72: Per Door
B73: Development Charges | D73: =D47+D62+D57+D68 -> 0 | E73: =D73/$C$7 -> #DIV/0!
B74: Building Permits & Misc. | C74: 0.005 | D74: =$K$19*C74 -> 0 | E74: =D74/$C$7 -> #DIV/0!
B75: Total | D75: =+SUM(D73:D74) -> 0 | E75: =D75/$C$7 -> #DIV/0!
